Workbook
Name _MON_1607936487: 'COT.ESCANEOACERO'!$A$21
Name _MON_1607936487: 'COT.ING'!#REF!
Name _MON_1607936487: 'COTIZACION INACAL ANTIGUO'!#REF!
Name _MON_1607936487: 'COTIZACION INACAL ASF'!#REF!
Name _MON_1607936487: 'COTIZACION INACAL DENSIDAD'!#REF!
Name _MON_1607936487: 'COTIZACION INACAL EQUIPO'!#REF!
Name _MON_1607936487: 'COTIZACION INACAL GH'!#REF!
Name _MON_1607936487: 'COTIZACION INACAL PROBETAS'!#REF!
Name _MON_1607936487: 'COTIZACION INACAL VARIOS'!#REF!
Name _MON_1607936487: 'COTIZACION PERSONAL'!#REF!
Name _MON_1607936487: 'COTIZACION VARIOS '!#REF!
Name _MON_1607936487: D.MEZCLA3!#REF!
Name _MON_1607936487: 'DENS-AG1'!#REF!
Name _MON_1607936487: 'DENS-AG2'!#REF!
Name _MON_1607936487: 'DENS-AG3'!#REF!
Name _MON_1607936487: 'DENS-AG4'!#REF!
Name _MON_1607936487: 'DENS-AG5'!#REF!
Name _MON_1607936487: 'DENS-AG5 (2)'!#REF!
Name _MON_1607936487: ING!#REF!
Name _MON_1607936487: MORT1!#REF!
Name _MON_1607936487: MORT2!#REF!
Name _MON_1607936487: 'PROB6 (2)'!#REF!
Name _MON_1607936487: 'PROB6 (3)'!#REF!
Name _MON_1607936487: 'PROB7 (2)'!#REF!
Name _MON_1607936487: 'PRUEBA 1'!#REF!
Name _MON_1607936487: 'SU-AG1'!#REF!
Name _MON_1607936487: 'SU-AG10'!#REF!
Name _MON_1607936487: 'SU-AG11'!#REF!
Name _MON_1607936487: 'SU-AG12'!#REF!
Name _MON_1607936487: 'SU-AG2'!#REF!
Name _MON_1607936487: 'SU-AG3'!#REF!
Name _MON_1607936487: 'SU-AG4'!#REF!
Name _MON_1607936487: 'SU-AG5'!#REF!
Name _MON_1607936487: 'SU-AG6'!#REF!
Name _MON_1607936487: 'SU-AG7'!#REF!
Name _MON_1607936487: 'SU-AG8'!#REF!
Name _MON_1607936487: 'SU-AG9'!#REF!
Name asar: ENS.!$B$60:$H$167
Name BD_Clientes: 'CLI.'!$B$4:$K$1048576
Name CLIENTE: 'CLI.'!$B$5:$L$65
Name CLIENTE1: 'CLI.'!$B$5:$L$979
Name CLIENTES: 'CLI.'!$B$37:$L$65
Name clientes1: 'CLI.'!$B$5:$L$300
Name CONDICIONES: CONDICIONES!$A$1:$K$58
Name MAMA: 'CLI.'!$B$5:$L$979
Name SERVICIOENSAYOS: 'ENSAYO ANTIGUO'!$B$4:$F$211
Name SERVICIOENSAYOS: ENS.!$B$60:$H$167

Sheet Hoja2
A3: ITEM | B3: Descripcion | F3: ASTM | G3: P.Unitario (S/.)
B4: Agregado grueso
A5: 1 | B5: Granulometria | F5: D 422 | G5: 60
A6: 2 | B6: Abrasion los angeles | F6: C 131 | G6: 115
A7: 3 | B7: Particulas con una cara fracturada | F7: D 5821 | G7: 48
A8: 4 | B8: Particulas con dos cara fracturada | F8: D 5821 | G8: 48
A9: 5 | B9: Particulas chatas y Alargadas | F9: D 4791 | G9: 48
A10: 6 | B10: Pérdidas con sulfatos de Magnesio | F10: C 88 | G10: 245
A11: 7 | B11: Limite Liquido | F11: D 4318 | G11: 30
A12: 8 | B12: Indice de Plasticidad (LL Y LP) | F12: D 4318 | G12: 53
A13: 9 | B13: Equivalencia de Arena | F13: D 2419 | G13: 60
A14: 10 | B14: Sales Solubles totales | F14: D 1888 | G14: 60
A15: 11 | B15: Limite de Plastico | F15: D 4318 | G15: 30
A16: 12 | B16: CBR (incluye proctor) | F16: D 1883 | G16: 245
A17: 13 | B17: Proctor Modificado | F17: D 1557 | G17: 78
A18: 14 | B18: Absorcion y peso especifico | G18: 35
A19: 15 | B19: adherencia (riedel weber) | G19: 115
A20: 16 | B20: Densidades de Campo (minimo 4 puntos por salida) no incluye mov. | F20: D 1556 | G20: 140
A21: 17 | B21: Ensayo de deflectometrica ( viga Benkelman) (x dia) | G21: 1500
B22: Ensayos del Agua
A23: 18 | B23: Contenido de sales solubles totales | F23: D5907 | G23: 60
A24: 19 | B24: Contenido de sulfatos | F24: D516 | G24: 75
A25: 20 | B25: Contenido de cloruros | F25: D512 | G25: 70
A26: 21 | B26: Sólidos en suspensión | F26: D5907 | G26: 35
A27: 22 | B27: Determinación del pH | F27: D1293 | G27: 45
B28: Bitumen
A29: 23 | B29: viscosidad cinematica | F29: D 2170 | G29: 120
A30: 24 | B30: Punto de Inflamacion | F30: D 92 | G30: 75
A31: 25 | B31: Destilacion y determinacion del residuo | F31: D 244 | G31: 65
A32: 26 | B32: ductibilidad | F32: D 113 | G32: 85
A33: 27 | B33: Solubilidad en tricloetileno | F33: D 2042 | G33: 85
A34: 28 | B34: viscosidad saybolt furol | F34: D 244/D88 | G34: 100
A35: 29 | B35: estabilidad de almacenamiento | F35: D 244 | G35: 40
A36: 30 | B36: tamizado malla N°20 | F36: D 244 | G36: 20
A37: 31 | B37: penetracion | F37: D 5 | G37: 75
A38: 32 | B38: ensayo de pelicula delgada (incl. Perdida por calentamiento, penetracion del residuo, ductibilidad del residuo) | F38: D 1754 | G38: 200
A39: 33 | B39: Ensayo de la mancha (Oliensis) | F39: AASHTO T102 | G39: 100
A44: Movilidad | G44: 50

Sheet ensayos en mecanica de suelos
A1: ENSAYO EN SUELOS
A3: Item | B3: Descripción | C3: NTP | D3: ASTM | E3: P.Unit (S/.)
A4: ENSAYO ESTÁNDAR
A5: 1 | B5: Contenido Humedad | C5: 339127 | D5: D2216 | E5: 15
A6: 2 | B6: Análisis granulométrico por tamizado | C6: 339128 | D6: D422 | E6: 60
A7: 3 | B7: Límite líquido | C7: 339129 | D7: D4318 | E7: 25
A8: 4 | B8: Límite plástico | C8: 339129 | D8: D4318 | E8: 25
A9: 5 | B9: Límite de contracción | C9: 339140 | D9: D427 | E9: 45
A10: 6 | B10: Peso volumétrico de suelos cohesivos | C10: 339139 | D10: BS 1377 | E10: 30
A11: 7 | B11: Gravedad específica de sólidos | C11: 339131 | D11: D854 | E11: 35
A12: ENSAYO ESPECIALES
A13: 8 | B13: Corte Directo | C13: 339171 | D13: D3080 | E13: 350
A14: 9 | B14: Compresión no confinada | C14: 339167 | D14: D2166 | E14: 250
A15: 10 | B15: Consolidación unidimensional | C15: 339154 | D15: D2435 | E15: 550
A16: ENSAYO DE COMPACTACION
A17: 11 | B17: Próctor estándar | C17: 339142 | D17: D698 | E17: 85
A18: 12 | B18: Próctor modificado | C18: 339141 | D18: D1557 | E18: 85
A19: 13 | B19: Valor relativo de soporte CBR (incluye proctor) | C19: 339145 | D19: D1883 | E19: 250
A20: 14 | B20: Densidades de Campo (minimo 4 puntos por salida) no incluye mov. | C20: 339143 | D20: D1556 | E20: 30
A21: 15 | B21: Densidad máxima y minima | C21: INVE-136-07 | E21: 120
A22: PRUBAS IN SITU
A23: 16 | B23: Deflexion con Viga Benkelman | C23: MTC E 1002 | E23: 1500/DIA
A25: Servicio de Movilidad | E25: 50

Sheet Ensayos en suelos
A1: ENSAYO QUIMICOS EN SUELOS
A3: item | B3: Descripción | C3: NTP | D3: ASTM | E3: P. Unit (S/.)
A5: 1 | B5: Sales solubles totales | C5: 339.152 | E5: 75
A6: 2 | B6: Contenido de sulfatos solubles | C6: 339.178 | E6: 75
A7: 3 | B7: Contenido de cloruros solubles | C7: 339.177 | E7: 75
A8: 4 | B8: Determinacion del PH | C8: 339.176 | E8: 60
A10: Servicio de Movilidad | E10: 50

Sheet Ensayos en Concreto
A1: ENSAYO EN CONCRETO
A3: item | B3: Descripción | C3: NTP | D3: ASTM | E3: P. Unit (S/.)
A5: 1 | B5: Diseño de Mezclas | C5: REC ACI 211 | E5: 350
A6: 2 | B6: Verificación de Diseño | C6: - | E6: 120
A7: 3 | B7: Control calidad de concreto en obra | C7: Varias | E7: 180
A8: 4 | B8: Exudación | C8: 339077 | D8: C 232 | E8: 60
A9: 5 | B9: Compresión | C9: 339034 | D9: C 39 | E9: 6.5
A10: 6 | B10: Temperatura del concreto fresco | C10: 339184 | D10: C 1064 | E10: 10
A11: 7 | B11: Asentamiento | C11: 339035 | D11: C 143 | E11: 15
A12: 8 | B12: Extracción, tallado y compresión de testigos por corte diamantina | C12: 339059 | D12: C 42 | E12: 170
A13: 9 | B13: Densidad, Absorción y % de Vacíos Concreto Endurecido | C13: 339187 | D13: C642 | E13: 85
A14: 10 | B14: Refrentado con yeso y ensayo de Compresion | C14: REF. 339.037 | D14: REF. C 617 | E14: 30
A15: 11 | B15: Ensayo de esclerometria | D15: C 805 | E15: 30
A17: Servicio de Movilidad | E17: 50

Sheet Ensayos en agregado
A1: ENSAYO EN AGREGADOS
A3: Código | B3: Descripción | C3: NTP | D3: ASTM | E3: P.U. (S/.)
A5: 1 | B5: Equivalente de arena | C5: 339146 | D5: D2419 | E5: 60
A6: 2 | B6: Partículas chatas y alargadas | C6: 400040 | D6: D4791 | E6: 60
A7: 3 | B7: Caras fracturadas | C7: --- | D7: D5821 | E7: 60
A8: 4 | B8: Análisis Granulométrico por tamizado | C8: 400012 | D8: C 136 | E8: 60
A9: 5 | B9: Impurezas Orgánicas (Fino) | C9: 400024 | D9: C 40 | E9: 40
A10: 6 | B10: Terrones de arcilla y partículas friables | C10: 400015 | D10: C 142 | E10: 80
A11: 7 | B11: Material más fino Malla 200 | C11: 400018 | D11: C 117 | E11: 15
A12: 8 | B12: Inalterabilidad (con sulfato de Magnesio) | C12: 400016 | D12: C 88 | E12: 300
A13: 9 | B13: Peso específico y absorción (F, G) | C13: 400022 | D13: C 128 | E13: 40
A14: 10 | B14: Contenido de humedad (F, G o Glb) | C14: 339185 | D14: C 566 | E14: 15
A15: 11 | B15: Peso unitario | C15: 400017 | D15: C 29 | E15: 35
A16: 12 | B16: desgaste por abracion | C16: MTC E 207 | D16: C 131 | E16: 100
A17: 13 | B17: granulometria - fraccion fino | C17: MTC E 204 | D17: C 136 | E17: 60
A18: 14 | B18: granulometria - global | C18: MTC E 204 | D18: C 136 | E18: 60
A19: 15 | B19: diseño de mezclas de agregados | E19: 70
A21: Servicio de Movilidad | E21: 50

Sheet Ensayos en asfalto
A2: ENSAYO EN PAVIMENTO Y ASFALTO
A4: Código | B4: Descripción | C4: NTP | D4: ASTM | E4: P.Unit (S/.)
A5: MEZCLA ASFALTICA
A6: 1 | B6: Lavado asfáltico (incluye tricloroetileno) | D6: D2172 | E6: 200
A7: 2 | B7: Estabilidad Marshall (Incluye: elaboración de briqueta, estabilidad, flujo, % de vacíos) (costo por briqueta) | D7: D1559 | E7: 190
A8: 3 | B8: Densidad de briqueta de mezcla asfáltica | D8: D2726 | E8: 45
A9: 4 | B9: Densidad máxima teórica (Rice) | D9: D2041 | E9: 80
A10: 5 | B10: Porcentaje de vacíos (incluye: densidad de especimen y densidad máxima teórica (Rice)) (costo por briqueta) | D10: --- | E10: 125
A11: 6 | B11: Elaboración de briquetas (juego de 3) | D11: D1559 | E11: 75
A12: 7 | B12: Adherencia en agregado fino (Riedel y Weber) | C12: MTC E220 | E12: 120
A13: 8 | B13: Adherencia en agregado grueso (Revestimiento y desprendimiento) | C13: MTC E521 | D13: D3625 | E13: 120
A14: 9 | B14: Textura del pavimento (Circulo de Arena) | C14: MTC 1005 | D14: E 965 | E14: 30
A15: 10 | B15: Deflexion con Viga Benkelman | C15: MTC E 1002 | E15: 1500/DIA
A16: 11 | B16: extraccion de briquetas por corte diamantina | E16: 140
A17: 12 | B17: Azul de Metileno | E17: 60
A18: 13 | B18: Penetracion | D18: D5 | E18: 75
A19: 14 | B19: Punto de inflamacion | D19: D92 | E19: 75
A20: 15 | B20: solubilidad de tricloroetileno | D20: D2042 | E20: 85
A21: 16 | B21: ensayo de la mancha (oliensis) | D21: AASHTO T102 | E21: 100
A22: 17 | B22: Ductibilidad | D22: D112 | E22: 85
A23: 18 | B23: Pelicula delgada | D23: D1754 | E23: 200
A24: 19 | B24: Punto de ablandamiento | D24: D36 | E24: 75
A25: 20 | B25: Viscosidad saybolt furol | D25: D244 | E25: 100
A26: 21 | B26: Indice de penetracion | D26: D5 | E26: 225
A27: 22 | B27: Peso especifico | D27: D70 | E27: 85
A28: 23 | B28: Viscosidad cinematica | D28: D2170 | E28: 120
A29: 24 | B29: contenido de agua | D29: D95 | E29: 55
... A36: 31 | B36: sedimentacion a los 5 dias | D36: D244 | E36: 70
A38: Servicio de Movilidad | E38: 50

Sheet ENSAYO ANTIGUO
B1: PRECIOS UNITARIOS DEL SERVICIO
A3: SUELOS | B3: CÓDIGO | C3: DESCRIPCION | D3: NORMA | E3: ASTM | F3: PRECIO A | H3: PRECIO B | I3: PRECIO C | J3: COMENTARIOS | K3: NORMA ADQUIRIDA | L3: PROCEDIMIENTO GEOFAL | M3: FORMATO | N3: CERTIFICADO
B4: SU03 | C4: Determinación del pH | D4: NTP 339.176 | E4: D4972 | F4: 60 | G4: 60 | L4: SI
B5: SU04 | C5: Contenido de humedad con Speedy | D5: NTP 339.25 | E5: D4944 | F5: 30 | G5: 60 | L5: SI
B6: SU05 | C6: Corte Directo | D6: NTP 339.171 | E6: D3080 | F6: 350 | G6: 350 | L6: SI
B7: SU06A | C7: Densidad natural, cono de arena 6" | D7: NTP 339.143 | E7: D1556 | F7: 35 | G7: 35 | H7: 35 | I7: 450 | J7: Puede variar de acuerdo cantidad y servicio | L7: SI
B8: SU06B | C8: Densidad natural, cono de arena 12" | D8: NTP 339.143 | E8: D1556 | F8: 80 | G8: 80 | J8: Puede variar de acuerdo cantidad y servicio | L8: SI
B9: SU07 | C9: Valor relativo de soporte CBR | D9: NTP 339.145 | E9: D1883 | F9: 250 | G9: 250 | L9: SI
B10: SU08 | C10: Próctor modificado (OBSOLETO) | D10: NTP 339.141 | E10: D1557 | F10: 120 | G10: 90 | H10: 95 | J10: Puede variar de acuerdo a la prioridad
B11: SU09 | C11: Peso específico relativo de partículas del suelo | D11: NTP 339.131 | E11: D854 | F11: 60 | G11: 50 | L11: SI
B12: SU10 | C12: Análisis granulométrico por tamizado | D12: NTP 339.128 | E12: D422 | F12: 70 | G12: 100 | L12: SI
B13: SU11 | C13: Límite líquido y Limite Plastico | D13: NTP 339.129 | E13: D4318 | F13: 70 | G13: 100 | L13: SI
B14: SU12 | C14: Contenido de humedad (OBSOLETO) | D14: NTP 339.127 | E14: D 2216 | F14: 25 | G14: 25
B15: SU13 | C15: Sales solubles totales | D15: NTP 339.152 | E15: BS 1377 | F15: 70 | G15: 70 | H15: 70 | J15: Puede variar de acuerdo a la prioridad | L15: SI
B16: SU14 | C16: Contenido de cloruros solubles | D16: NTP 339.177 | E16: AASHTO T291 | F16: 90 | G16: 80 | L16: SI
B17: SU15 | C17: Contenido de sulfatos solubles | D17: NTP 339.178 | E17: AASHTO T290 | F17: 100 | G17: 90 | H17: 100 | J17: Puede variar de acuerdo a la prioridad | L17: SI
B18: SU16 | C18: Ensayo de SPT | L18: SI
B19: SU17 | C19: Equivalente de arena (OBSOLETO) | D19: NTP 339.146 | E19: D2419 | F19: 80 | G19: 60
B20: SU18 | C20: Ensayo de Placa de Carga | D20: ASTM D-1194 | F20: 2500 | G20: 2000 | L20: SI
B21: SU19 | C21: Próctor modificado | D21: ASTM D1557 | F21: 120 | G21: 120 | L21: SI
B22: SU20 | C22: Contenido de humedad | D22: ASTM D 2216 | F22: 25 | L22: SI
B23: SU21 | C23: Equivalente de arena | D23: ASTM D2419 | F23: 80 | L23: SI
B24: SU22 | C24: Clasificación suelo SUCS - AASHTO | D24: ASTM D2487 / 3282 | F24: 20 | G24: 30 | L24: SI
B25: SU23 | C25: Límite líquido y Limite Plastico | D25: ASTM D4318 | F25: 70 | L25: SI
B26: SU24 | C26: Análisis granulométrico por tamizado | D26: ASTM D6913 | F26: 70 | L26: SI
B27: SU25 | C27: Clasificación suelo SUCS - AASHTO | D27: NTP 339.134 / 339.135 | F27: 20 | L27: SI
B28: SU26 | C28: Contenido de materia organica | D28: NTP 339.071 | F28: 90
B29: SU27 | C29: Solidos en suspensión | D29: ASTM C1603 | F29: 90
B30: SU28 | C30: Densidad de campo por metodo de reemplazo por agua | D30: ASTM D5030 | F30: - | L30: SI
B31: SU29 | C31: Prueba de Infiltración | D31: ASTM D3385 | F31: - | L31: SI
B32: SU30 | C32: Próctor Estándar | D32: ASTM D698 | F32: 120 | L32: SI
B33: SU31 | C33: Correccion de proctor modificado | D33: ASTM D4718-87 | F33: - | L33: SI
B39: SU21 | C39: CBR insitu | D39: ASTM D-4429 | F39: =2350+1500 -> 3850
B40: ESP01 | C40: Compresión Triaxial UU | D40: ASTM D 2850 | F40: 1400
B41: ESP02
B42: ESP03
B43: ESP04 | C43: COLAPSO | D43: ASTM D 5333 | F43: 500
B44: CA1 | C44: Calicata 1.5mt prof | D44: - | F44: 150
B45: CA2 | C45: Calicata 3mt prof | D45: - | F45: 300
B46: MOV. | C46: Movilidad | D46: - | F46: 60
B47: MOV | C47: Movilidad | D47: - | F47: 50
B48: MOV.. | C48: Movilizacion y desmovilizacion de equipos | D48: - | F48: 200
A49: ESCANEO ACERO | B49: E01 | C49: Escaneo de acero de refuerzo x M2 | D49: - | F49: 547
B50: E02 | C50: Escaneo de acero por portico | D50: - | F50: 785
B51: E03 | C51: Escaneo de acero por estructura | D51: - | F51: 450
B52: EMS | C52: Estudio de suelos con fines de pavimentacion | D52: - | F52: 5000
A54: AGREGADOS | B54: AG01 | C54: Peso unitario (f, g o glb.) (OBSOLETO) | D54: NTP 400.017 | E54: C 29/C29M | F54: 50 | G54: 50
B55: AG02 | C55: Contenido de humedad (f g o glb) (OBSOLETO) | D55: NTP 339.185 | E55: NTP 339.185 | F55: 25
B56: AG03 | C56: Analisis granulométrico (f o g) (OBSOLETO) | D56: NTP 400.012 | E56: C 136 | F56: 70
B57: AG04 | C57: Peso específico y absorción (g) | D57: NTP 400.021 | E57: ASTM C127 | F57: 60 | G57: 50 | H57: 35 | L57: SI
B58: AG05 | C58: Peso específico y absorción (f) (OBSOLETO) | D58: NTP 400.022 | E58: ASTM C128 | F58: 60 | H58: 35
B59: AG06 | C59: Desgaste por abrasión (g) | D59: NTP 400.019 | E59: ASTM C131 | F59: 150 | L59: SI
B60: AG07 | C60: Partículas chatas y alargadas | D60: NTP 400.040 | E60: ASTM D4791 | F60: 60 | L60: SI
B61: AG08 | C61: Inalterabilidad (f o g) con sulfato de magnesio | D61: NTP 400.016 | E61: ASTM C88 | F61: 350 | G61: 250 | L61: SI
B62: AG09 | C62: Indice de durabilidad | D62: MTC E-214 | F62: 200 | L62: SI
B63: AG10 | C63: Caras fracturadas | D63: ASTM D5821 | F63: 70 | L63: SI
B64: AG11 | C64: Sales solubles totales | D64: MTC E-219 | E64: MTC E-219 | F64: 70 | H64: 70 | L64: SI
B65: AG12 | C65: Riedel Weber | D65: MTC E 220-20 | F65: 80 | L65: SI
B66: AG13 | C66: Impurezas Organicas (f) | D66: ASTM C40-99 | F66: 70 | L66: SI
B67: AG14 | C67: Material que pasa la malla N° 200 (OBSOLETO) | D67: NTP 400.018 | E67: NTP 400.018 | F67: 70
B68: AG15 | C68: Materia organica
B69: AG16 | C69: Contenido de cloruros solubles | D69: NTP 400.042 | F69: 90
B70: AG17 | C70: Contenido de sulfatos solubles | D70: NTP 400.042 | F70: 100 | H70: 100
B71: AG18 | C71: Peso específico y absorción (f) | D71: ASTM C128 | F71: 80 | L71: SI
B72: AG19 | C72: Analisis granulométrico (f o g) | D72: ASTM C136 | F72: 90 | L72: SI
B73: AG20 | C73: Contenido de humedad del agregado | D73: ASTM C566 | F73: 25 | L73: SI
B74: AG22 | C74: Peso unitario del agregado | D74: ASTM C29 | F74: 60 | L74: SI
B75: AG23 | C75: Material que pasa la malla N° 200 | D75: ASTM C117 | F75: 70 | L75: SI
B76: AG24 | C76: Carbón y lignito | D76: NTP 400.023 | F76: 90 | L76: SI
B77: - | C77: Método de prueba para la determinación del valor azul de metileno | E77: AASHTO TP57 | F77: 110
B82: AG25 | C82: Terrones de arcilla y partículas friables | D82: NTP 400.015 | F82: 90
B83: AG15 | C83: Analisis granulométrico (glb) | D83: NTP 400.012 | E83: C 136 | F83: 700
A84: CONCRETO | B84: CO01 | C84: Compresión | D84: NTP 339.034 | E84: C 39 | F84: 9 | G84: 9 | H84: 7 | J84: Puede variar de acuerdo al servicio y cantidad | L84: SI
B85: CO03A | C85: Extracción, tallado y ensayo de compresión de tes. diam. broca de 2" en lab. | D85: NTP 339.059 | E85: C 42 | F85: 120 | H85: 210 | I85: 120 | J85: Puede variar de acuerdo al servicio y cantidad | L85: SI
B86: CO03B | C86: Extracción, tallado y ensayo de compresión de tes. diam. broca de 3" en lab. | D86: NTP 339.059 | E86: C 42 | F86: 150 | L86: SI
B87: CO03C | C87: Extracción, tallado y ensayo de compresión de tes. diam. broca de 4" en lab. | D87: NTP 339.059 | E87: C 42 | F87: 200 | L87: SI
B88: CO03D | C88: Extracción 2 pulg (no incluye tallado ni compresión) | D88: NTP 339.059 | E88: C 42 | F88: 110 | L88: SI
B89: CO03E | C89: Extracción 3 pulg (no incluye tallado ni compresión) | D89: NTP 339.059 | E89: C 42 | F89: 130 | L89: SI
B90: CO03F | C90: Extracción 4 pulg (no incluye tallado ni compresión) | D90: NTP 339.059 | E90: C 42 | F90: 150 | L90: SI
B91: CO03G | C91: Extracción de diamantina de concreto asfaltico y su evaluación | D91: NTP 339.059 | E91: C 42 | F91: 130 | L91: SI
B92: CO03H | C92: Ensayo de compresion, tallado y refrentado, de Testigos Diamantinos | D92: - | E92: C 42 | F92: 40
B93: CO04 | C93: Esclerometría | D93: NTP 339.181 | E93: C 805 | F93: 50 | L93: SI
B94: CO05 | C94: Muestreo del concreto fresco | D94: NTP 339.036 | F94: 120 | L94: SI
B95: CO06 | C95: Procedimiento para la medicion asentamiento | D95: NTP 339-035 | E95: - | F95: - | L95: SI
B96: CO07 | C96: Flexión | D96: NTP 339.078/079 | F96: 70 | L96: SI
B97: CO08 | C97: Resistencia a la compresión de mortero con especimen cubicos de 50ml de lado | D97: NTP 334.051 | F97: 15 | L97: SI
B98: CO09 | C98: Procedimiento para la medicion asentamiento | D98: ASTM C143 | E98: - | F98: - | L98: SI
B99: CO10 | C99: Determinación PH concreto endurecido / Carbonatación | D99: ASTM D1293 | F99: 50 | L99: SI
B105: CO10 | C105: Resistencia a la compresión de mortero con especimen cubicos de 50ml de lado | F105: 120
B106: CO11 | C106: Control de calidad del concreto fresco en obra, 6 probetas y ensayo Slump | D106: - | F106: 200
B107: DIS01 | C107: Diseño de mezclas | D107: ACI 211 | F107: 350 | G107: 450 | H107: 300 | J107: Puede variar de acuerdo cantidad
B108: DIS02 | C108: Diseño de mezclas Calc. | D108: ACI 211 | F108: 150 | H108: 150 | J108: Puede variar de acuerdo cantidad
B109: DIS03 | C109: Verificación de diseño | D109: ACI 211 | F109: 200
B111: CO07 | C111: Tallado, refrentado con yeso y ensayo de compresión | D111: REF. 339.037 | E111: REF. C 617 | F111: 25 | H111: 20
B112: CO08 | C112: Extracción de testigo diamantino de 4 pulg. en m.asfaltica | D112: REF. 339.037 | E112: REF. C 617 | H112: minimo 3
B113: CO12 | C113: Verificación de diseño
B114: CO13 | C114: Exudación | D114: 339.077 | E114: C 232
B115: CO14 | C115: Peso por metro cúbico, rendimiento, cont. aire | D115: 339.046 | E115: C 138
B116: CO15 | C116: Medición contenido de aire del concreto fresco | D116: 339.083 | E116: C 231 | F116: 80
B117: CO16 | C117: Tiempo de fraguado | D117: 339.082 | E117: C 403
...

Sheet PRUEBA 1
G3: 222 | P3: ID CLIENTE | Q3: 1210
B5: CLIENTE: | D5: =VLOOKUP($Q$3,BD_Clientes,2,FALSE) -> BATALLA DE JUNIN S.A.C | J5: PROYECTO1: | L5: =VLOOKUP($Q$3,BD_Clientes,9,FALSE) -> Bicentenario | P5: 222
B6: R.U.C.1: | D6: =VLOOKUP($Q$3,BD_Clientes,3,FALSE) -> 20603173156 | P6: 222
B7: CONTACTO: | D7: =VLOOKUP($Q$3,BD_Clientes,5,FALSE) -> Alondra Neira Salas | J7: UBICACIÓN1: | L7: =VLOOKUP($Q$3,BD_Clientes,10,FALSE) -> Av. José Leguía y Meléndez 301, Pueblo Libr | P7: 222
B8: TELÉFONO DE CONTACTO: | E8: =VLOOKUP($Q$3,BD_Clientes,7,FALSE) -> 977504836 | J8: PERSONAL COMERCIAL: | L8: Silvia Peralta
B9: CORREO: | D9: =VLOOKUP($Q$3,BD_Clientes,8,FALSE) -> calidadbatalladejunin@gmail.com | J9: TELÉFONO DE COMERCIAL: | L9: 982429895
B10: FECHA SOLICITUD: | E10: 45970 | J10: FECHA DE EMISIÓN: | L10: 45970
B11: REFERENCIA: Segùn lo solicitado vìa correo electrònico / Whatsapp / Telèfono / Personalmente.
B12: 1: Información no considerada para las personas naturales.
B13: Por medio de la presente, tenemos el agrado de remitirle nuestra cotización en base a su solicitud, por los servicios de los siguientes ensayos de laboratorio.
B16: CÒDIGO | C16: DESCRIPCIÒN | J16: NORMA | K16: ACREDITADO | L16: COSTO UNITARIO | M16: CANTIDAD | N16: COSTO PARCIAL
B17: SU19 | C17: =VLOOKUP(B17,ENS.!$B$5:$H$167,2,FALSE) -> Próctor modificado | J17: =VLOOKUP(B17,ENS.!$B$5:$H$167,3,FALSE) -> ASTM D1557-12 (Reapproved 2021) | K17: =VLOOKUP(B17,ENS.!$B$5:$H$167,4,FALSE) -> SI | L17: =VLOOKUP(B17,ENS.!$B$5:$H$167,7,FALSE) -> 150 | M17: 1 | N17: =+L17*M17 -> 150
B18: SU20 | C18: =VLOOKUP(B18,ENS.!$B$5:$H$167,2,FALSE) -> Contenido de humedad en suelos | J18: =VLOOKUP(B18,ENS.!$B$5:$H$167,3,FALSE) -> ASTM D2216-19 | K18: =VLOOKUP(B18,ENS.!$B$5:$H$167,4,FALSE) -> SI | L18: =VLOOKUP(B18,ENS.!$B$5:$H$167,7,FALSE) -> 30 | M18: 1 | N18: =+L18*M18 -> 30
B19: SU20A | C19: =VLOOKUP(B19,ENS.!$B$5:$H$167,2,FALSE) -> Contenido de humedad en Roca. | J19: =VLOOKUP(B19,ENS.!$B$5:$H$167,3,FALSE) -> ASTM D2216-19 | K19: =VLOOKUP(B19,ENS.!$B$5:$H$167,4,FALSE) -> NO | L19: =VLOOKUP(B19,ENS.!$B$5:$H$167,7,FALSE) -> 30 | M19: 1 | N19: =+L19*M19 -> 30
B20: SU21 | C20: =VLOOKUP(B20,ENS.!$B$5:$H$167,2,FALSE) -> Equivalente de arena | J20: =VLOOKUP(B20,ENS.!$B$5:$H$167,3,FALSE) -> ASTM D2419-22 | K20: =VLOOKUP(B20,ENS.!$B$5:$H$167,4,FALSE) -> SI | L20: =VLOOKUP(B20,ENS.!$B$5:$H$167,7,FALSE) -> 150 | M20: 1 | N20: =+L20*M20 -> 150
B21: SU19 | C21: =VLOOKUP(B21,ENS.!$B$5:$H$167,2,FALSE) -> Próctor modificado | J21: =VLOOKUP(B21,ENS.!$B$5:$H$167,3,FALSE) -> ASTM D1557-12 (Reapproved 2021) | K21: =VLOOKUP(B21,ENS.!$B$5:$H$167,4,FALSE) -> SI | L21: =VLOOKUP(B21,ENS.!$B$5:$H$167,7,FALSE) -> 150 | M21: 1 | N21: =+L21*M21 -> 150
B22: SU20 | C22: =VLOOKUP(B22,ENS.!$B$5:$H$167,2,FALSE) -> Contenido de humedad en suelos | J22: =VLOOKUP(B22,ENS.!$B$5:$H$167,3,FALSE) -> ASTM D2216-19 | K22: =VLOOKUP(B22,ENS.!$B$5:$H$167,4,FALSE) -> SI | L22: =VLOOKUP(B22,ENS.!$B$5:$H$167,7,FALSE) -> 30 | M22: 11 | N22: =+L22*M22 -> 330
B23: SU20A | C23: =VLOOKUP(B23,ENS.!$B$5:$H$167,2,FALSE) -> Contenido de humedad en Roca. | J23: =VLOOKUP(B23,ENS.!$B$5:$H$167,3,FALSE) -> ASTM D2216-19 | K23: =VLOOKUP(B23,ENS.!$B$5:$H$167,4,FALSE) -> NO | L23: =VLOOKUP(B23,ENS.!$B$5:$H$167,7,FALSE) -> 30 | M23: 1 | N23: =+L23*M23 -> 30
B24: SU21 | C24: =VLOOKUP(B24,ENS.!$B$5:$H$167,2,FALSE) -> Equivalente de arena | J24: =VLOOKUP(B24,ENS.!$B$5:$H$167,3,FALSE) -> ASTM D2419-22 | K24: =VLOOKUP(B24,ENS.!$B$5:$H$167,4,FALSE) -> SI | L24: =VLOOKUP(B24,ENS.!$B$5:$H$167,7,FALSE) -> 150 | M24: 1 | N24: =+L24*M24 -> 150
L25: Costo parcial | N25: =SUM(N17:N24) -> 1020
L26: IGV 18% | N26: =+N25*0.18 -> 183.6
L27: Costo Total (S/) | N27: =+N25+N26 -> 1203.6
B29: VALIDEZ DE LA OFERTA: 30 días calendario. Si la cotización llegó al límite de su validez, solicite una actualización.
B30: CONDICIONES ESPECÍFICAS PARA LOS ENSAYOS DE LABORATORIO: - El cliente deberá de entregar las muestras debidamente identificadas. - El cliente deberá especificar la Norma a ser utilizada para la ejecución del ensayo, caso contrario el laboratorio considera la Norma ASTM y/o NTP vigente de acuerdo con su alcance. - El cliente deberá entregar las muestras en las instalaciones del Laboratorio de Ensayos de Materiales, ubicado en la Av. Rio Marañon N° 763, Los Olivos, Perú
B31: PLAZO ESTIMADO DE EJECUCIÓN DE SERVICIO: - El plazo de entrega de los resultados se estima en 10 días hábiles, este tiempo será evaluado de acuerdo a la cantidad de muestra recepcionada y está sujeto a la programacion enviada por el Laboratorio de Ensayos de Materiales. - El laboratorio enviará un correo de confirmación de recepción y fecha de entrega del informe.
B33: COM-F-01 Página 1 de 2 Versión: 04 (10-11-2025)
B34: CONTRAMUESTRA Al finalizar los ensayos, la muestra sobrante/contramuestra permanecerán en custodia por un tiempo de 10 dias calendario después de emitido el informe de ensayo. Siempre que se trate de una muestra dirimente, las contramuestras serán devueltas a los clientes, previa coordinación y autorización, caso contrario, serán eliminadas si se trata de residuos del ensayo o contramuestras de ensayo.
B35: CONFIDENCIALIDAD: GEOFAL S.A.C mantiene acuerdos de confidencialidad entre el cliente y el laboratorio, la divulgación de la información sin la autorización de las partes, no es permitida. El laboratorio mantiene reserva de la información brindada por el cliente, salvo solicitud de la información por ley, o por entidades gubernamentales inmersos dentro del presente servicio de ensayo.
B36: QUEJAS Y SUGERENCIAS: El plazo máximo para la recepción de quejas relacionadas con un informe técnico es de diez (10) días calendarios, contados a partir de la fecha de emisión del documento correspondiente. Transcurrido dicho plazo, no se aceptarán quejas bajo ninguna circunstancia. En caso de tener alguna queja o sugerencia, lo invitamos a conocer nuestro Proceso de Atención de Quejas, el cual dará inicio 24 horas después de la recepción formal de la queja.
B37: ENTREGA DE INFORME DE ENSAYO: - De acuerdo a los lineamientos de INACAL - DM, los informes de ensayo son emitidos de forma digital con firma electrónica y QR. - La entrega de los informes de ensayo será mediante la plataforma de Intranet de la pagina web www.geofal.com.pe, y se enviará un correo de confirmación al cliente con el usuario y clave para el acceso. Asi mismo el cliente puede ingresar a la gruía deusuario que es visible en la página web. - Geofal no declara conformidad de sus informes de ensayo. - En caso se requiera la modificación del informe de ensayo a consecuencia de los datos proporcionados por el cliente, esta se realizará mediante la emisión de un nuevo informe que tendrá un costo adicional de acuerdo a evaluación.
B38: HORARIO DE ATENCIÓN El horario para recepción de muestra y entrega de informes es de Lunes a Viernes de 8:30am a 1:00pm y 2:00pm a 5:30pm, y Sábado de 8:30am a 12:30pm
B41: CONDICIÓN: | P41: CONDICIONES DE PAGO
B42: RAZON SOCIAL: Geofal S.A.C. RUC: 20549356762 | P42: CONDICIÓN: El pago del servicio se realizara de acuerdo a la valorización mensual
B43: Sírvase realizar el depósito correspondiente de los servicios a nuestra cuenta bancaria: | P43: CONDICIÓN: El pago del servicio deberá ser realizado por Adelantado.
B44: Cuenta de detraccion Banco de La Nación: | P44: CONDICIÓN: El pago del servicio Adelanto el 50% y saldo previo a la entrega del Informe.
B45: - Cuenta de detraccion Banco de La Nación: Nº 00-074-045472 | P45: CONDICIÓN: El pago del servicio Crédito a 7 días, previa orden de servicio.
B46: Cuenta corriente Interbank: | P46: CONDICIÓN: El pago del servicio Crédito a 30 días, previa orden de servicio.
B47: - Cuenta Corriente en Soles de Interbank: Nº 200-3005201096 | P47: CONDICIÓN: El pago del servicio Crédito a 15 días, previa orden de servicio.
B48: - Código Interbancario (CCI) de Interbank: Nº 003-200- 003005201096-31
B49: Cuenta corriente BCP:
B50: - Cuenta Corriente en Soles del Banco de Crédito del Perú (BCP): Nº 192 2024 3030 04
B51: - Código Interbancario (CCI) del Banco de Crédito del Perú (BCP): Nº 002-192-002 02430 3004-34
B52: Cuenta corriente BBVA:
B53: - Cuenta Corriente en Soles BBVA: Nº 0011-0174-0100082311-00
B54: - Código Interbancario (CCI) BBVA: Nº 011-174-000100082311-00
B58: La aceptación de la cotización por parte del cliente podrá manifestarse a través de cualquiera de las siguientes acciones: el pago correspondiente al servicio, el envío de la orden de servicio, o el envío de un correo electrónico confirmando la aceptación del servicio según la presente cotización, al correo asesorcomercial@geofal.com.pe y/o mediante mensaje de WhatsApp al número del asesor comercial, en señal de conformidad.
B60: Atentamente,
B62: Geofal SAC
B63: Av. Marañón N° 763, Los Olivos, Lima, Perù
B64: Teléfono laboratorio: (01) 7543070 / Teléfono Oficina: (01) 9051911
B65: Web: www.geofal.com.pe
B67: COM-F-01 Página 2 de 2 Versión: 04 (10-11-2025) | M67: Fin del documento

Sheet CLI.
B2: LISTA DE CLIENTES GEOFAL
B4: ID CLIENTE | C4: CLIENTE | D4: RUC | E4: DIRECCION | F4: CONTACTO | G4: CARGO | H4: TELÉFONO | I4: CORREO | J4: PROYECTO | K4: UBICACIÓN | L4: SERVICIO
B5: 1 | C5: CONSTRUCTORA GALLO SEMINARIO SA | D5: 20268387031 | E5: JR. JUAN DE DIOS BEDOYA S. NRO. 1150 URB. LOS CIPRECES | F5: Roberto Carlos Chiuyari Cusi | G5: - | H5: 936789506 | I5: robertochiuyari@gmail.com | L5: ENSAYO DE LABORATORIO
B6: 2 | C6: CONKRETO INGENIERÍA Y CONSTRUCCIÓN SAC | D6: 20600118197 | E6: CAL.FUENTES MANUEL ATANASIO NRO. 977 URB. CHACARILLA DE SANTA CRUZ | F6: Fresia Guerra | G6: - | H6: - | I6: fresia.guerra@conkreto.net | L6: ENSAYO DE LABORATORIO
B7: 3 | C7: CONSTRUCTURA Y SERVICIOS GENERALES KALLPA SAC | D7: 20515734636 | E7: AV. JOSE PARDO NRO. 434 INT. 1302 , MIRAFLORES | F7: Carlos Murriel | G7: - | H7: 920363423 | I7: c.murriel@inkall.com.pe | L7: ENSAYO DE LABORATORIO
B8: 4 | C8: CJ TELECOM SAC | D8: 20505958111 | E8: CAL.SANTA JUSTINA NRO. 620 URB. PANDO III ETAPA LIMA | F8: Belmarys Rondon | G8: COORDINADOR DE INGENIERÍA | H8: 967765603 | I8: brondon@cj-telecom.com | J8: - | K8: - | L8: ENSAYO DE LABORATORIO
B9: 5 | C9: AZ INVERSIONES INMOBILIARIAS SAC | D9: 20516862506 | E9: AV. JOSE PARDO NRO. 434 INT. 1302 URB. SURQUILLO | F9: Rolando Canta | G9: LOGISTICA | H9: 983510023 | I9: r.canta@inhouse.com.pe | J9: TOP 818 | K9: AV PRINCIPAL 818, SURQUILLO | L9: ENSAYO DE LABORATORIO
B10: 6 | C10: MIRANDA ROQUE | E10: - | F10: Alan Miranda Roque | G10: - | I10: amiranda@mirandaroque.com | L10: ENSAYO DE LABORATORIO
B11: 7 | C11: AZ INVERSIONES INMOBILIARIAS SAC | D11: 20516862506 | E11: AV. JOSE PARDO NRO. 434 INT. 1302 URB. SURQUILLO | F11: Alan Incio | G11: - | H11: 960852630 | I11: a.incio@inhouse.com.pe | J11: - | K11: - | L11: ENSAYO DE LABORATORIO
B12: 8 | C12: AZ INVERSIONES INMOBILIARIAS SAC | D12: 20516862506 | E12: AV. JOSE PARDO NRO. 434 INT. 1302 URB. SURQUILLO | F12: Hernan Tuppia | G12: - | H12: 920363418 | I12: h.tuppia@inhouse.com.pe / htuppia7@gmail.com | J12: EDIFICIO MULTIFAMILIAR TREVITA | K12: JR.MORRO SOLAR N° 336 - SURCO | L12: ENSAYO DE LABORATORIO
B13: 9 | C13: JG3 CONSTRUCCIONES S.A.C | D13: 20505212739 | E13: JR. LOS ALAMOS NRO. 409 URB. EL OLIVAR - CALLAO | F13: Gilmer Garay | G13: - | H13: 968 800 818 | I13: ggaray@jg3construcciones.com | J13: - | K13: - | L13: ENSAYO DE LABORATORIO
B14: 10 | C14: PENTATECH INGENIERIA Y CONSTRUCCION | D14: 20553327971 | E14: CAL.8 DE OCTUBRE NRO. 271 DPTO. 302 URB. SANTA CRUZ - MIRAFLORES | F14: Josselyn Cobeñas Vela | G14: LOGISTICA | H14: 929684224 | I14: logistica2@pentatechasac.com | L14: ENSAYO DE LABORATORIO
B15: 11 | C15: MARIO DANIEL CUBAS ROMERO | D15: - | E15: - | F15: Mario Daniel Cubas Romero | G15: - | H15: 999566333 | I15: mariocubas80@gmail.com | L15: ENSAYO DE LABORATORIO
B16: 12 | C16: CORPORACION IVEDO SAC | D16: 20600836031 | E16: AV. AVIACION NRO. 0412 CAS. CUILLAS | F16: Rocio Mendoza L. | G16: - | H16: 987154818 | I16: rocio.mendoza@ivedosac.com | L16: ENSAYO DE LABORATORIO
B17: 13 | C17: TAC GERENCIA Y CONSTRUCCIONES SAC | D17: 20601237840 | E17: CAL.5 MZA. J LOTE. 22 URB. LOS PINOS LIMA - LIMA - PUENTE PIEDRA | F17: Cristina Tasayco | G17: - | H17: 993688546 | I17: cristina.tasayco@tacgyc.com | L17: ENSAYO DE LABORATORIO
B18: 14 | C18: TREYAL SAC | D18: 20605254331 | E18: ZONA Z HUAYCAN MZA. G LOTE. 1 ASC. DE PRODUCTORES LOS JARDINES DE VILLA - ATE | F18: Elmer Condezo | G18: - | I18: eacondezo@gmail.com | L18: ENSAYO DE LABORATORIO
B19: 15 | C19: B & P DISEÑO E INGENIERIA DEL ACERO SAC | D19: 20523767934 | E19: MZA. D LOTE. 1 ASC. EL MANANTIAL - SAN MARTIN DE PORRES | F19: Liset Maza | G19: - | H19: 4014245 | I19: lmaza@byp-ingenieria.com.pe | L19: ENSAYO DE LABORATORIO
B20: 16 | C20: MINERA LAYTARUMA S.A. | D20: 20125959483 | E20: JR. TIZIANO NRO. 301 URB. SAN BORJA | F20: Marlon Cabanillas | G20: - | H20: 968370132 | I20: marlon.cabanillas@laytaruma.com.pe | L20: ENSAYO DE LABORATORIO
B21: 17 | C21: OC&T | E21: - | F21: Candy Romero Yacolca | G21: - | H21: 934709610 | I21: cromero@ocyt.com.pe | L21: ENSAYO DE LABORATORIO
B22: 18 | C22: CONSTRUCTORA Y MULTISERVICIOS ASHMARK SAC | D22: 20545508398 | E22: JR. RIO CHICAMA NRO. 5637 URB. VILLA NORTE - LOS OLIVOS | F22: Melchor Sanchez | G22: - | H22: 987089525 | I22: melchorsanchez1970@hotmail.com | L22: ENSAYO DE LABORATORIO
B23: 19 | C23: GARI BERRIO | E23: - | F23: Gari Berrio | G23: - | H23: 993184846 | I23: gariberrio@yahoo.es | L23: ENSAYO DE LABORATORIO
B24: 20 | C24: 3X3 INGENIERIA DE LA CONSTRUCCIÓN Y SERVICIOS GENERALES SAC | D24: 20549297570 | E24: AV. JOSE GRANDA NRO. 2412 URB. CONDEVILLA SEÑOR Y VALDIVIESO - SMP | F24: Aristdes Ocmin Paredes | G24: - | H24: 917693170 | I24: aopselva@hotmail.com | L24: ENSAYO DE LABORATORIO
B25: 21 | C25: INVERSIONES INMOBILIARIAS DEL INDICO S.A. | D25: 20514048071 | E25: AV. DEL PINAR NRO. 134 INT. 301 URB. CHACARILLA DEL ESTANQUE - SURCO | F25: Alvaro Morales | G25: - | H25: 963 313 844 | I25: amorales@imagina.com.pe | L25: ENSAYO DE LABORATORIO
B26: 22 | C26: IFIT PERU | D26: 20516233801 | E26: JR. LIMA NRO. 757 LA PERLA, PROV. CONST. DEL CALLAO - CALLAO | F26: Jorge Luis Cabanillas Carpio | G26: - | H26: 978436300 | I26: jcabanillas@ifitperu.net | J26: AMERICAN TOWER PERU S.A | K26: LIMA / PIURA | L26: ENSAYO DE LABORATORIO
B27: 23 | C27: JHONATAN MARCA MEDINA | E27: - | F27: Jhonatan Marca Medina | G27: - | H27: 910529876 | I27: jmarcam@uni.pe | L27: ENSAYO DE LABORATORIO
B28: 24 | C28: C&SG VIRGEN DE GUADALUPE SAC | D28: 20605411372 | E28: - | F28: Juan Jobiniano Medina Arista | G28: - | H28: 938331539 | I28: csg.v.guadalupe.sac@gmail.com | L28: ENSAYO DE LABORATORIO
B29: 25 | C29: JME INGENIERÍA ESTRUCTURAL Y TECNOLOGÍA DE MATERIALES EIRL | D29: 20537919991 | E29: AV. UNIVERSITARIA NORTE NRO. 2713 A.V. SAN JUAN DE DIOS ETP 1 - SMP | F29: Madevelia Valladares Cabello | G29: - | H29: 998845609 | I29: administracion@jme.pe | J29: - | K29: - | L29: ENSAYO DE LABORATORIO
B30: 26 | C30: SANTANDER CONSULTORES Y CONTRATISTAS EIRL | E30: - | F30: Lizeth Chirinos | G30: - | H30: 958345595 | I30: lizett.chirinos@santandercyc.com / lizett.chirinos@gmail.com | L30: ENSAYO DE LABORATORIO
B31: 27 | C31: TECSUR S.A | D31: 20206018411 | E31: PJ. CALANGO NRO. 158 (ALT.CDRA.3 Y 4 AV.P.MIOTTA) - SAN JUAN DE MIRAFLORES | F31: Mishely Castro | G31: DEPARTAMENTO DE COMPRAS | H31: 926687304 | I31: mcastro@tecsur.com.pe | J31: LT60KV PACHACUTEC VES | K31: Av. Los Alamos, Av. Modelo, VES | L31: ENSAYO DE LABORATORIO
B32: 28 | C32: VECTOR CONTRATISTAS GENERALES SAC | D32: 20569090289 | E32: - | G32: - | H32: 917424689 | I32: vectorcgsac@gmail.com | L32: ENSAYO DE LABORATORIO
B33: 29 | C33: CONSTRUCTORA Y CONSULTORIA REMAR SAC | D33: 20601489521 | E33: - | F33: Katiuska | G33: - | H33: 940475009 | I33: katiuscavt@gmail.com | L33: ENSAYO DE LABORATORIO
B34: 30 | C34: PLAYDE S.A.C. | D34: 20541103831 | E34: AV. PROLONGACION JAVIER PRADO MZA. J1 LOTE. 29 INT. B URB. LOS PORTALES - ATE | F34: Miklail Rivera | G34: - | I34: mrivera@playde.pe | L34: ENSAYO DE LABORATORIO
B35: 31 | C35: MJR CONSTRUCCIONES S.A.C. | D35: 20562660896 | E35: CAL.SANDINO MZA. E LOTE. 5, CRUCE DE LAS AV. HUANDOY Y RIO MARAÑON - LOS OLIVOS | F35: Cristian Bobadilla | G35: - | H35: 963338932 | I35: cristiam1925@gmail.com | J35: - | K35: - | L35: ENSAYO DE LABORATORIO
B36: 32 | C36: VIRGEN DE GUADALUPE SAC | D36: 20605411372 | E36: - | F36: Honey Medina Ortiz | G36: - | H36: 937473122 | I36: honeymedinaortiz@gmail.com | L36: ENSAYO DE LABORATORIO
B37: 33 | C37: TELECOM A.V. S.A.C. | D37: 20601508878 | E37: JR. REJALGAR N°1394 DPTO. 401, LOS OLIVOS | F37: Magaly Vela Portocarrero | G37: - | H37: 985998448 | I37: proyectos@telecomav.com.pe | L37: ENSAYO DE LABORATORIO
B38: 34 | C38: CONSORICO JOTAME SAC | D38: 20548536457 | E38: - | F38: Jose Tafur Melendez | G38: - | H38: 963986864 | I38: jotame20@hotmail.com | L38: ENSAYO DE LABORATORIO
B39: 35 | C39: TECSUR S.A | D39: 20206018411 | E39: PJ. CALANGO NRO. 158 (ALT.CDRA.3 Y 4 AV.P.MIOTTA) - SAN JUAN DE MIRAFLORES | F39: Mishely Castro | G39: - | H39: 926687304 | I39: mcastro@tecsur.com.pe | L39: ENSAYO DE LABORATORIO
B40: 36 | C40: CJ CONTRATISTAS ASOCIADOS SAC | D40: 20510303386 | E40: MZA. C LOTE. 16 ASOC VIV JUAN CARLOS NOR - SAN MARTIN DE PORRES | F40: Noris Lucia Aquino Urruchi | G40: - | H40: 968201908 | I40: naquino@cj.com.pe | J40: - | K40: - | L40: ENSAYO DE LABORATORIO
B41: 37 | C41: JUAN VILCHEZ | D41: - | E41: - | F41: Juan Vilchez | G41: - | H41: 986658220 | I41: jvilchez94@hotmail.com | L41: ENSAYO DE LABORATORIO
B42: 38 | C42: TECSUR S.A | D42: 20206018411 | E42: PJ. CALANGO NRO. 158 (ALT.CDRA.3 Y 4 AV.P.MIOTTA) - SAN JUAN DE MIRAFLORES | F42: Nicolas Mendoza Cavero | G42: - | H42: 960641783 | I42: nmendoza@tecsur.com.pe | L42: ENSAYO DE LABORATORIO
B43: 39 | C43: PROINGCOM SAC | D43: 20600159098 | E43: PJ. JOHN IMPETT NRO. 210 DPTO. 203 URB. SAN JOSE - BELLAVISTA, CALLAO | F43: Cinthya Mercado | G43: - | H43: 999335533 | I43: logistica01@proingcom.com | L43: ENSAYO DE LABORATORIO
B44: 40 | C44: SANTO DOMINGO INGENIERIA Y PROYECTOS SAC | D44: 20605491201 | E44: - | F44: Victoria Escalante Saldaña | G44: - | H44: - | I44: vescalante@santodomingocg.com | L44: ENSAYO DE LABORATORIO
B45: 41 | C45: ENACORP | D45: 20543329984 | E45: AV. JOSE PARDO 231 502 - MIRAFLORES | F45: Linda Campos | G45: ING. DE OFICINA TÉCNICA | H45: 946473128 | I45: lcampos@enacorp.pe | J45: VALLE GRANDE 2 | K45: AV. PERIMETRICA LOTE 6 - C, CARABAYLLO, LIMA | L45: ENSAYO DE LABORATORIO
B46: 42 | C46: ENACORP | D46: 20543329984 | E46: AV. JOSE PARDO 231 502 - MIRAFLORES | F46: Niells Jamanca | G46: INGENIERO DE CALIDAD | H46: 946232416 | I46: njamanca@enacorp.pe | J46: VALLE GRANDE 2 | K46: AV. PERIMETRICA LOTE 6 - C, CARABAYLLO, LIMA | L46: ENSAYO DE LABORATORIO
B47: 43 | C47: PLAYDE S.A.C. | D47: 20541103831 | E47: AV. PROLONGACION JAVIER PRADO MZA. J1 LOTE. 29 INT. B URB. LOS PORTALES - ATE | F47: Adriana Gabriela Díaz | G47: - | H47: 930930270 | I47: adiaz@playde.pe | L47: ENSAYO DE LABORATORIO
B48: 44 | C48: CORPORACION BRINPER SAC | D48: 20601163277 | E48: - | F48: Ernest Rea Prado | G48: - | H48: - | I48: lrea_94@hotmail.com | L48: ENSAYO DE LABORATORIO
B49: 45 | C49: MADRID EDIFICACIONES | D49: 20536763164 | E49: - | F49: Jorge Tovar Zevallos | G49: - | H49: 946223912 | I49: jtovar@madridedificaciones.com | L49: ENSAYO DE LABORATORIO
B50: 46 | C50: CARLOS GASPAR PACO | D50: 10232618979 | E50: - | F50: Carlos Gaspar Paco | G50: - | H50: 944245799 | I50: carlosgp999@hotmail.com | L50: ENSAYO DE LABORATORIO
B51: 47 | C51: PLAYDE S.A.C. | D51: 20541103831 | E51: AV. PROLONGACION JAVIER PRADO MZA. J1 LOTE. 29 INT. B URB. LOS PORTALES - ATE | F51: Miklail Rivera | G51: - | H51: - | I51: mrivera@playde.pe | L51: ENSAYO DE LABORATORIO
B52: 48 | C52: TECSUR S.A | D52: 20206018411 | E52: PJ. CALANGO NRO. 158 (ALT.CDRA.3 Y 4 AV.P.MIOTTA) - SAN JUAN DE MIRAFLORES | F52: Rebeca Garcia Peña | G52: - | H52: 961106569 | I52: rgarcia@tecsur.com.pe | L52: ENSAYO DE LABORATORIO
B53: 49 | C53: MATUTE INGENIEROS SAC | D53: 20603796137 | E53: JR. C. FIGUEROA MZA. V1 LOTE. 9 URB. STA. LUZMILA (MERCADO STA. LUZMILA) LIMA - LIMA - COMAS | F53: Luis Huamani | G53: - | H53: 943619841 | I53: matuteingenieros@gmail.com | J53: SITE LI5279 MONTECARLO CARABAYLLO | K53: PROGRAMA DE VIVIENDA EL ROBLE III MZ B LOTE 9 - CARABAYLLO | L53: ENSAYO DE LABORATORIO
B54: 50 | C54: INVERSIONES ZUTA EIRL | D54: 20600785177 | E54: JR. OMBU MZA. 55 LOTE. 01B URB. CIUDAD SATELITE - VENTANILLA - CALLAO | F54: Juan Zuñiga | G54: - | H54: 977546799 | I54: j.azt@hotmail.com | L54: ENSAYO DE LABORATORIO
B55: 51 | C55: INARCO | D55: - | E55: - | F55: Alcides Hermoza Mejia | G55: - | H55: 987590211 | I55: ahermoza@inarco.com.pe | L55: ENSAYO DE LABORATORIO
B56: 52 | C56: CONSORCIO CUSCO | E56: - | F56: Eduardo Loza | G56: - | H56: 980545518 | I56: eduardo_loza317@hotmail.com | L56: ENSAYO DE LABORATORIO
B57: 53 | C57: GDUR MUNICIPALIDAD DISTRITAL DE SANTIAGO DE TUNA | D57: 20206864215 | E57: - | F57: Wilfredo Ricra | G57: - | H57: 996526276 | I57: ing-ricra@hotmail.com | L57: ENSAYO DE LABORATORIO
B58: 54 | C58: ALIANZA CONSTRUCTORA DE OBRA SAC | D58: 20476423539 | E58: - | F58: Fernando Caballero | G58: - | H58: - | I58: obramanuelcoxanan@gmail.com | L58: ENSAYO DE LABORATORIO
B59: 55 | C59: LA VENTUROSA | D59: - | E59: - | F59: Edgar Camargo | G59: - | H59: 994032350 | I59: ecamargo@laventurosa.com | L59: ENSAYO DE LABORATORIO
B60: 56 | C60: HENRY ESPIRITU DIESTRA | D60: - | E60: - | F60: Henry Espiritu Diestra | G60: - | H60: 947266197 | I60: henryespiritud@gmail.com | L60: ENSAYO DE LABORATORIO
B61: 57 | C61: GUZMAN YANA | D61: - | E61: - | F61: Guzman Yana | G61: - | H61: 964284309 | I61: yanaaytapele@gmail.com | L61: ENSAYO DE LABORATORIO
B62: 58 | C62: TECSUR S.A | D62: 20206018411 | E62: PJ. CALANGO NRO. 158 (ALT.CDRA.3 Y 4 AV.P.MIOTTA) - SAN JUAN DE MIRAFLORES | F62: Yiliam Gomez Paredes | G62: - | H62: 902731909 | I62: ygomez@tecsur.com.pe | L62: ENSAYO DE LABORATORIO
B63: 59 | C63: INGECCA SAC | D63: - | E63: - | F63: Julian Aguado | G63: - | H63: 992864325 | I63: jaguado@ingecca.com.pe | L63: ENSAYO DE LABORATORIO
B64: 60 | C64: DAVID RODRIGUEZ MINAYA | D64: - | E64: - | F64: David Rodriguez Minaya | G64: - | H64: 944993131 | I64: davidrodriguez6822@gmail.com | L64: ENSAYO DE LABORATORIO
B65: 61 | C65: ERHA CONSTRUIR | D65: - | E65: - | F65: Sr. Cristian | G65: - | H65: 960938861 | I65: erha-construir@outlook.com | L65: ENSAYO DE LABORATORIO
B66: 62 | C66: CONSTRUCTORA GALLO SEMINARIO SA | D66: 2.0564842e+10 | E66: JR. JUAN DE DIOS BEDOYA S. NRO. 1150 URB. LOS CIPRECES | F66: Roberto Carlos Chiuyari Cusi | G66: - | H66: 936789507 | I66: robertochiuyari@gmail.com | L66: ENSAYO DE LABORATORIO
B67: 63 | C67: SERVICIOS GENERALES LAMARC E.I.R.L. | D67: 20601455456 | E67: CAL.CALLE 38 MZA. I1 LOTE. 10 URB. ALAMEDA DEL PINAR - COMAS | F67: Martha Calderon | G67: - | H67: 998795541 | I67: mcalderon.lamarc@gmail.com | L67: ENSAYO DE LABORATORIO
B68: 64 | C68: CALOPINO CONSTRUCCIONES | D68: - | E68: - | F68: Jhoon Hardy Saavedra Cordova | G68: - | H68: 970381291 | I68: jhoon.saavedra@gmail.com | L68: ENSAYO DE LABORATORIO
B69: 65 | C69: NEIL BALDIN LAZO | D69: - | E69: - | F69: Neil Baldin Lazo | G69: - | H69: 996710711 | I69: nbalbin@cip.org.pe | L69: ENSAYO DE LABORATORIO
B70: 66 | C70: IPG SAC | D70: - | E70: - | F70: Walter Quispe | G70: - | H70: 969009694 | I70: wquispe@ipgsac.com | L70: ENSAYO DE LABORATORIO
B71: 67 | C71: PMS-DRS | D71: - | E71: AV. PRIMAVERA 939 OFIC. 401 SAN BORJA, LIMA | F71: Javier Salvador Lopez | G71: JEFE DE PRODUCCION | H71: 977876784 | I71: jsalvador@pms-drs-com.pe | L71: ENSAYO DE LABORATORIO
B72: 68 | C72: INSSEL INGENIERIA SAC | D72: 20551851665 | E72: - | F72: Nilton Cordova | G72: - | H72: 981845842 | I72: niltonficuni@hotmail.com | L72: ENSAYO DE LABORATORIO
B73: 69 | C73: ARCHITECTURAL CIRCLE S.A.C. | D73: 20552228198 | E73: CAL.16 MZA. A LOTE. 26 URB. LOS JAZMINES - SMP | F73: Wilhelm Balbin | G73: - | H73: 980718915 | I73: acsacgerencia@hotmail.com | L73: ENSAYO DE LABORATORIO
B74: 70 | C74: CGML | D74: - | E74: - | F74: Danny Quispe | G74: - | H74: - | I74: en.obras@outlook.com | L74: ENSAYO DE LABORATORIO
B75: 71 | C75: HUMBERTO CHUQUITAYPE | D75: - | E75: - | F75: Humberto Chuquitaype | G75: - | H75: 996640518 | I75: humbertoquintana1958@gmail.com | L75: ENSAYO DE LABORATORIO
B76: 72 | C76: SERGIO CACERES | D76: - | E76: - | F76: Sergio Caceres | G76: - | H76: 959268647 | I76: sergio_ecm@hotmail.com | J76: - | K76: - | L76: ENSAYO DE LABORATORIO
B77: 73 | C77: GDUR MUNICIPALIDAD DISTRITAL DE SANTIAGO DE TUNA | D77: 20206864215 | E77: - | F77: Sergio Caceres | G77: - | H77: 959268647 | I77: sergio_ecm@hotmail.com | L77: ENSAYO DE LABORATORIO
B78: 74 | C78: FRANCO DE LA CRUZ | D78: - | E78: - | F78: Franco De La Cruz | G78: - | H78: 989302527 | I78: fdelacruz@gmail.com | L78: ENSAYO DE LABORATORIO
B79: 75 | C79: COORPORACION CUENCA | D79: 20601497469 | E79: - | F79: Aldo Cuenca Ortiz | G79: - | H79: 971504929 | I79: cuencacorporacion@gmail.com | L79: ENSAYO DE LABORATORIO
B80: 76 | C80: J&F CONTRATISTAS SAC | D80: 20548650586 | E80: - | F80: Flavio De J&F | G80: - | H80: 966535431 | I80: ramireztaboada84@gmail.com | L80: ENSAYO DE LABORATORIO
B81: 77 | C81: ARKHOS INGENIERIA ANTISISMICA SAC | D81: 20605283137 | E81: - | F81: Manuel Enrique Reyes La Rosa | G81: - | H81: 933360185 | I81: dpantojarod@gmail.com | L81: ENSAYO DE LABORATORIO
B82: 78 | C82: CORBET SA | D82: 20392790617 | E82: - | F82: Beatriz Matos | G82: - | H82: 995517963 | I82: bmatos@corbet.pe | L82: ENSAYO DE LABORATORIO
B83: 79 | C83: CB & J CONTRATISTAS GENERALES SAC | D83: 20549521551 | E83: - | F83: Hugo Jara | G83: - | H83: 912482730 | I83: hugjara_1995@hotmail.com | L83: ENSAYO DE LABORATORIO
B84: 80 | C84: INVERSIONES INMOBILIARIAS DEL INDICO S.A. | D84: 20514048071 | E84: AV. DEL PINAR NRO. 134 INT. 301 URB. CHACARILLA DEL ESTANQUE - SURCO | F84: Mary Carmen Carnero Vargas | G84: - | H84: 991960703 | I84: Mary.Carnero@imagina.pe | L84: ENSAYO DE LABORATORIO
B85: 81 | C85: PROINGCOM SAC | D85: 20600159098 | E85: PJ. JOHN IMPETT NRO. 210 DPTO. 203 URB. SAN JOSE - BELLAVISTA, CALLAO | F85: Betzabe Espinoza | G85: - | H85: 989199294 | I85: logistica01@proingcom.com / operaciones01@proingcom.com | L85: ENSAYO DE LABORATORIO
B86: 82 | C86: CONSORCIO AERONAVAL CALLAO | D86: 20602182577 | E86: CAL.CORONEL ANDRES REYES NRO. 360 INT. 501 URB. JARDIN - SAN ISIDRO | F86: Norma Mayorca | G86: - | H86: 995141802 | I86: nmayorca.caeronavalc@gmail.com | L86: ENSAYO DE LABORATORIO
B87: 83 | C87: JG3 CONSTRUCCIONES S.A.C | D87: 20505212739 | E87: JR. LOS ALAMOS NRO. 409 URB. EL OLIVAR - CALLAO | F87: Diego Gallardo Pinedo | G87: - | H87: 957679250 | I87: dgallardo@jg3construcciones.com | L87: ENSAYO DE LABORATORIO
B88: 84 | C88: MADRID EDIFICACIONES | D88: 20536763164 | E88: - | F88: Marcelo Lovon Paliza | G88: - | H88: 993461180 | I88: mlovon@madridedificaciones.com | L88: ENSAYO DE LABORATORIO
B89: 85 | C89: CAFISAC | D89: - | E89: - | F89: John Tineo | G89: - | H89: 995603936 | I89: jtineo@cafisac.com.pe | L89: ENSAYO DE LABORATORIO
B90: 86 | C90: TECSUR S.A | D90: 20206018411 | E90: PJ. CALANGO NRO. 158 (ALT.CDRA.3 Y 4 AV.P.MIOTTA) - SAN JUAN DE MIRAFLORES | F90: Manuel Correa | G90: - | H90: 998373769 | I90: mcorrea@tecsur.com | L90: ENSAYO DE LABORATORIO
B91: 87 | C91: GRUPO BINOMIO S.A.C. | D91: 20536803646 | E91: AV. PETIT THOUARS NRO. 1775 INT. 1402, LINCE, LIMA | F91: Angela Urbano | G91: - | H91: 959650048 | I91: aurbano@binomio.com.pe | L91: ENSAYO DE LABORATORIO
B92: 88 | C92: ANGGIE MORALES MORANTE | D92: 10454134503 | E92: - | F92: Anggie Morales Morante | G92: - | H92: 987341155 | I92: moralesanggie@gmail.com | J92: - | K92: - | L92: ENSAYO DE LABORATORIO
B93: 89 | C93: ANMA CONTRATISTAS GENERALES SRL | D93: 20504032460 | E93: CAL.BOYACA NRO. 126 URB. MARANGA - SAN MIGUEL | F93: Oscar Anicama | G93: - | H93: 993276528 | I93: oanicamac@hotmail.com | L93: ENSAYO DE LABORATORIO
B94: 90 | C94: JESUS PAJARES | D94: - | E94: - | F94: Jesus Pajares | G94: - | H94: - | I94: jesusemph123@gmail.com | L94: ENSAYO DE LABORATORIO
B95: 91 | C95: GRUPO BINOMIO S.A.C. | D95: 20536803646 | E95: AV. PETIT THOUARS NRO. 1775 INT. 1402, LINCE, LIMA | F95: German Chirinos | G95: - | H95: 944834946 | I95: german.chirinos@binomio.com.pe | L95: ENSAYO DE LABORATORIO
B96: 92 | C96: JOANNA CLAUDIO | D96: - | E96: - | F96: Joanna Claudio | G96: - | H96: 992269585 | I96: joanclaud9@gmail.com | L96: ENSAYO DE LABORATORIO
B97: 93 | C97: QUANTA SERVICES | D97: - | E97: - | F97: Christian Hilares | G97: - | H97: 989820292 | I97: chilares@quantaservices.com | L97: ENSAYO DE LABORATORIO
B98: 94 | C98: NILTON CORDOVA | D98: 20605400338 | E98: - | F98: Nilton Cordova | G98: - | H98: 981845842 | I98: niltonficuni@hotmail.com | J98: - | K98: - | L98: ENSAYO DE LABORATORIO
B99: 95 | C99: EMPRESA CONSTRUCTORA ARC S.R.LTDA | D99: 20277977509 | E99: AV. ALAMEDA DEL CORREGIDOR NRO. 718 - LA MOLINA | F99: Srta Lourdes | G99: AREA LOGISTICA | H99: 988010026 | I99: arcsrl12@hotmail.com | J99: CONSTRUCCION CERCO PERIMETRICO - SUNAT | K99: CERCADO DE LIMA - LIMA | L99: ENSAYO DE LABORATORIO
B100: 96 | C100: CONSTRUCTORA Y SERVICIOS RODEMA E.I.R.L | D100: 20154727826 | E100: CAL.JOSÉ GRANDA NRO. 459 URB. COUNTRY CLUB - SAN ISIDRO | F100: Diego Vences Martinez | G100: - | H100: 964977780 | I100: dvences@constructorarodema.com | L100: ENSAYO DE LABORATORIO
B101: 97 | C101: PROMOTORA SAN FELIPE SAC | D101: 20602814263 | E101: CAL.JUAN ALFARO NRO. 198 URB. SAN ANTONIO - MIRAFLORES | F101: Ricardo Contreras | G101: - | H101: 956 598 560 | I101: rcontreras@danielson.pe | L101: ENSAYO DE LABORATORIO
B102: 98 | C102: SAUL LIMA VASQUEZ | D102: - | E102: - | F102: Saul Lima Vasquez | G102: - | H102: -
...

Sheet ENS.
B2: LISTA DE PRECIOS ENSAYOS DE LABORATORIO
B4: CÓDIGO | C4: DESCRIPCION | D4: NORMA | E4: ACREDITADO | F4: REFERENCIA OTRA NORMA | G4: UBICACIÓN | H4: PRECIO | I4: TIEMPO | J4: COMENTARIOS
C5: ENSAYO ESTÁNDAR SUELO
B6: SU04 | C6: Contenido de humedad con Speedy. | D6: NTP 339.25 | E6: NO | F6: D4944 | G6: LABORATORIO | H6: 30 | I6: 15 minutos
B7: SU19 | C7: Próctor modificado | D7: ASTM D1557-12 (Reapproved 2021) | E7: SI | F7: - | G7: LABORATORIO | H7: 150 | I7: 2 dias | J7: Para realizar el ensayo de proctor se requiere tambien realizar: granulometria SU24 y/o AG19/ peso especifico grueso AG28 / peso relativo del solido SU32 / correccion por grava SU31
B8: SU20 | C8: Contenido de humedad en suelos | D8: ASTM D2216-19 | E8: SI | F8: - | G8: LABORATORIO | H8: 30 | I8: 2 dias
B9: SU20A | C9: Contenido de humedad en Roca. | D9: ASTM D2216-19 | E9: NO | F9: - | G9: LABORATORIO | H9: 30 | I9: 2 dias | J9: No estamos acreditados en este alcance
B10: SU21 | C10: Equivalente de arena | D10: ASTM D2419-22 | E10: SI | F10: - | G10: LABORATORIO | H10: 150 | I10: 3 dias
B11: SU22 | C11: Clasificación suelo SUCS - AASHTO | D11: ASTM D2487-17 (Reapproved 2025) / ASTM D3282-24 | E11: SI | F11: - | G11: LABORATORIO | H11: 20 | I11: 3 dias | J11: Para el ensayo se requiere de granulometria SU24 y/o AG28 y limites SU23
B12: SU23 | C12: Límite líquido y Límite Plástico del Suelo | D12: ASTM D4318-17ε1 | E12: SI | F12: - | G12: LABORATORIO | H12: 90 | I12: 3 dias
B13: SU24 | C13: Análisis granulométrico por tamizado en Suelo | D13: ASTM D6913/D6913M-17 | E13: SI | F13: - | G13: LABORATORIO | H13: 100 | I13: 3 dias
B14: SU30 | C14: Ensayo de Compactación Próctor Estándar. | D14: ASTM D698 | E14: NO | F14: - | G14: LABORATORIO | H14: 150 | I14: 3 dias
B15: SU31 | C15: Corrección de Peso Unitario para Partícula de gran tamaño. | D15: ASTM D4718-87 | E15: NO | F15: - | G15: LABORATORIO | H15: 20 | I15: 3 dias
B16: SU32 | C16: Gravedad específica de los sólidos del suelo. | D16: ASTM D854-14 | E16: NO | F16: - | G16: LABORATORIO | H16: 120 | I16: 3 dias | J16: Si La Muestra Tiene Grava Se Tendria Que Hacer Tambien El Ensayo De Peso Especifico Del Grueso
B17: SU34 | C17: Densidad y peso unitario de muestra suelo | D17: ASTM D 7263 | E17: NO | F17: - | H17: 70 | I17: 3 dias | J17: Esto se repite en roca, xq para contrrol de calidad en roca el cliente solicito el ensayo
B18: SU35 | C18: Densidad del peso unitario máximo del suelo. | D18: NTP 339.137 | E18: NO | F18: - | G18: LABORATORIO | H18: 350 | I18: 3 dias
B19: SU36 | C19: Densidad del peso unitario mínimo del suelo. | D19: NTP 339.138 | E19: NO | F19: - | G19: LABORATORIO | H19: 150 | I19: 3 dias
B20: SU38 | C20: Determinación de sólidos totales suspendidos. | D20: NTP 214.039 | E20: NO | F20: - | G20: LABORATORIO | H20: 150 | I20: 3 dias
B21: SU39 | C21: Análisis granulométrico por hidrómetro (incl. Granulometría por tamizado). | D21: NTP 339.128 1999 (revisada el 2019) | E21: NO | F21: - | G21: LABORATORIO | H21: 350 | I21: 4 dias
C22: ENSAYOS ESPECIALES SUELO
B23: SU05 | C23: Corte Directo. | D23: NTP 339.171 | E23: NO | F23: D3080 | G23: LABORATORIO | H23: 350 | I23: 3 dias | J23: Solicitar al cliente la densidad del suelo. Si el cliente no tiene la densidad, se cotiza tambien el ensayo de proctor con ello hallaremos la densidad del suelo y lo remoldearemos al 95% Maxima densidad seca
B24: SU33 | C24: Resistencia a la Compresión no confinada de suelos cohesivos | D24: NTP 339.167 | E24: NO | F24: ASTM D2166 | G24: LABORATORIO | H24: 250 | I24: 3 dias
B25: SU37 | C25: California Bearing Ratio (CBR) | D25: ASTM D1883-21 | E25: SI | F25: NTP 339.145 | G25: LABORATORIO | H25: 300 | I25: 7 dias
B26: SU38 | C26: CBR INSITU | E26: NO | I26: 1/2 dia
B27: SU40 | C27: Hinchamiento suelo | D27: ASTM D4546-21 | E27: NO | I27: 3 dias
B28: SU41 | C28: Potencial de Colapso en suelo. | D28: ASTM D5333 | E28: NO | F28: - | G28: LABORATORIO | H28: 370 | I28: 3 dias | J28: El Costo De Clasificacion En La Uni 210
B29: SU42 | C29: Conductividad hidráulica en pared rígida (Permeabilidad). | D29: ASTM D2434 | E29: NO | F29: - | G29: LABORATORIO | H29: 530 | I29: 2 dias | J29: Para el ensayo se requiere realizar previo el ensayo de granulometria, limites, clasificación sucs, peso relativo del solido, peso especifico del grueso (solo si tiene grava), adicional ensayo de pasane de la malla 200 menor al 12%.
B30: SU43 | C30: Conductividad hidráulica en pared flexible (Permeabilidad). | D30: ASTM D5084 | E30: NO | F30: - | G30: LABORATORIO | H30: =560+80 -> 640 | I30: 2 dias | J30: Para el ensayo se requiere realizar previo el ensayo de granulometria, limites y clasificación sucs, peso relativo del solido, peso especifico del grueso (solo si tiene grava). Cantidad de muestra: 60 kilos, Tiempo de entrega: 05 días
B31: SU44 | C31: Conductividad térmica / Resistividad térmica | D31: ASTM D5334-14 | E31: NO | F31: - | G31: LABORATORIO | H31: 1500 | I31: 3 dias | J31: Se requiere de ensayos de granulometria, límites y clasificación.
B32: SU45 | C32: Compresión triaxial no consolidado no drenado UU, diametro 75 mm | D32: ASTM D2850 | E32: NO | F32: - | G32: LABORATORIO | H32: 1500 | I32: 3 dias | J32: UU: cuando halla licuacion de suelo (densidad baja, arena fina sin mucho contenido en la malla 200, que no tenga limites, nivel freatico), otro suelo arena muy sueltas cuando se excaven se hace un embudo, arcillas blandas (solo fino, densidades bajas), en conclusion suelos criticos, TIEMPO 1.1/2 DIAS EN ARENA Y ARCILLA
B33: SU46 | C33: Compresión triaxial consolidado no drenado CU, diametro 75 mm | D33: ASTM D4767 | E33: NO | F33: - | G33: LABORATORIO | H33: 2000 | I33: 3 dias | J33: CU: Se realizara cuando el agua nunca se pueda drenar, ejemplo orilla del mar, donde hay nivel freatico, ems para puente, etc. TIEMPO 3 DIAS ARENA Y 4 DIAS ARCILLA
B34: SU47 | C34: Compresión triaxial consolidado drenado CD, diametro 75 mm | D34: ASTM D7181 | E34: NO | F34: - | G34: LABORATORIO | H34: Sujeto a evaluación | I34: 3 dias | J34: CD: Se realiza donde no hay nivel freatico, porque el suelo drena el agua, ejemplo se rompio una tuberia el suelo se inunda esto en un determinado tiempo drenara el agua. TIEMPO 6 DIAS EN ARENA Y ARCILLA
B35: EE01 | C35: Consolidación unidimensional. | D35: ASTM D2435 | E35: NO | F35: - | G35: LABORATORIO | H35: 800 | I35: 7 dias
B36: EE02 | C36: Expansión libre. | D36: ASTM D4546 | E36: NO | F36: - | G36: LABORATORIO | H36: 350 | I36: 3 dias
B37: EE03 | C37: Expansión controlada Método A. | D37: ASTM D4546 | E37: NO | F37: - | G37: LABORATORIO | H37: 670 | I37: 3 dias
C38: ENSAYO QUÍMICO SUELO Y AGUA SUBTERRÁNEO
B39: SU03 | C39: Determinación del PH en Suelo y Agua. | D39: NTP 339.176 | E39: NO | F39: D4972 | G39: LABORATORIO | H39: 70 | I39: 3 dias
B40: SU13 | C40: Sales solubles en Suelos y Agua. | D40: NTP 339.152 | E40: NO | F40: BS 1377 | G40: CAMPO | H40: 80 | I40: 3 dias | J40: Puede variar de acuerdo a la prioridad
B41: SU14 | C41: Cloruros Solubles en Suelos y Agua. | D41: NTP 339.177 | E41: NO | F41: AASHTO T291 | G41: LABORATORIO | H41: 80 | I41: 3 dias
B42: SU15 | C42: Sulfatos Solubles en Suelos y Agua. | D42: NTP 339.178 | E42: NO | F42: AASHTO T290 | G42: LABORATORIO | H42: 120 | I42: 3 dias | J42: Puede variar de acuerdo a la prioridad
B43: SU26 | C43: Contenido de materia orgánica. | D43: AASHTO T267 | E43: NO | F43: - | G43: LABORATORIO | H43: 120 | I43: 3 dias | J43: Solo para suelo
C44: ENSAYOS DE CAMPO EN SUELO
B45: SU02 | C45: Ensayo de penetración dinámica DPL. | D45: NTP 339.159 | E45: NO | F45: - | G45: CAMPO | H45: Sujeto a evaluación | I45: 2,1/2 hora | J45: Solamente se realiza hasta 3 metros de profundidad
B46: SU06A | C46: Densidad del suelo IN-SITU, Cono de Arena 6" | D46: NTP 339.143:1999 (revisada el 2019) | E46: SI | F46: D1556 | G46: CAMPO | H46: 50 | I46: 1/2 hora | J46: Salida minima 4 puntos, se requiere el ensayo de proctor
B47: SU06B | C47: Densidad del suelo IN-SITU, Cono de Arena 12". | D47: NTP 339.143:1999 (revisada el 2019) | E47: NO | F47: D1556 | G47: CAMPO | H47: 80 | I47: 1,1/2 hora | J47: Salida minima 4 puntos, se requiere el ensayo de proctor
B48: SU06C | C48: Control de calidad de suelo compactado por 1 dìa: Densidad del suelo IN-SITU con Cono de Arena 6" Contenido de humedad en suelos | D48: NTP 339.143:1999 (revisada el 2019) ASTM D2216-19 | E48: SI | F48: D1556 | G48: CAMPO | H48: =70*7 -> 490 | I48: 1 dia | J48: No hay puntos minimos, rendiemiento del personal 40 minutos por punto
B49: SU06D | C49: Control de calidad de suelo compactado por 1 dìa: Densidad del suelo IN-SITU con Cono de Arena 6" contenido de humedad con equipo Speedy | D49: NTP 339.143:1999 (revisada el 2019) | E49: NO | F49: D1556 | G49: CAMPO | H49: =70*7 -> 490 | I49: 1 dia | J49: No hay puntos minimos, rendiemiento del personal 40 minutos por punto
B50: SU16 | C50: Ensayo de Penetración Estándar (SPT). | D50: NTP 339.133 | E50: NO | F50: - | G50: CAMPO | H50: Sujeto a evaluación | I50: varia por tipo de suelo | J50: El Cliente Proporcionara Ubicación, Cantidad Puntos Y Profundidad De Investigacion
B51: SU18 | C51: Capacidad de carga del Suelo (Placa de Carga). | D51: ASTM D-1194 | E51: NO | F51: - | G51: CAMPO | H51: 2500 | I51: 1 dia | J51: El cliente proporcionara un volquete de 32 tonelada y/o excavadora
B52: SU28 | C52: Densidad del suelo y roca IN SITU por reemplazo de agua. | D52: ASTM D5030 | E52: NO | F52: - | G52: CAMPO | H52: Sujeto a evaluación | I52: 1 dia | J52: Depende Del Diametro De La Grava, Y Cantidad Solicitada
B53: SU29 | C53: Infiltración de suelos en campo. | D53: ASTM D3385 | E53: NO | F53: - | G53: CAMPO | H53: 3500 | I53: 1 dia | J53: Depende del tipo de suelo
B54: SU40 | C54: Métodos de prueba estándar para el análisis del tamaño de partículas de materiales de escollera naturales y artificiales. | D54: ASTM D5519-07 | E54: NO | F54: - | G54: CAMPO | H54: 250 | I54: 3 dias | J54: Esto lo usaron para granulometria macro en TERRAMOVE
B55: SU41 | C55: Determinación de la densidad de suelo en terreno (Método Densímetro Nuclear). | D55: ASTM D2922 | E55: NO | F55: - | G55: LABORATORIO | H55: 90 | I55: 10 minutos
C56: ENSAYO AGREGADO
B57: AG08A | C57: Inalterabilidad Agregado Grueso con Sulfato de Magnesio. | D57: NTP 400.016 | E57: NO | F57: ASTM C88 | G57: LABORATORIO | H57: 350 | I57: 7 dias | J57: * Se requiere realizar granulometria agregado AG19
B58: AG08B | C58: Inalterabilidad Agregado Fino con Sulfato de Magnesio. | D58: NTP 400.016 | E58: NO | F58: ASTM C88 | G58: LABORATORIO | H58: 350 | I58: 7 dias | J58: * Se requiere realizar granulometria agregado AG19
B59: AG09 | C59: Índice de Durabilidad Agregado. | D59: MTC E-214 | E59: NO | F59: - | G59: LABORATORIO | H59: 350 | I59: 3 dias
B60: AG18 | C60: Gravedad específica y absorción del agregado fino | D60: ASTM C128-22 | E60: SI | F60: - | G60: LABORATORIO | H60: 150 | I60: 3 dias
B61: AG19 | C61: Análisis granulométrico por tamizado en agregado | D61: ASTM C136/C136M-19 | E61: SI | F61: - | G61: LABORATORIO | H61: 100 | I61: 3 dias
B62: AG20 | C62: Contenido de humedad en agregado | D62: ASTM C566-19 | E62: SI | F62: - | G62: LABORATORIO | H62: 30 | I62: 2 dias
B63: AG22 | C63: Peso Unitario y Vacío de agregados | D63: ASTM C29/C29M-23 | E63: SI | F63: - | G63: LABORATORIO | H63: 120 | I63: 3 dias | J63: * Se requiere hacer el peso especifico fino AG18 o grueso AG28, fino si es arena y grueso si es grava
B64: AG23 | C64: Pasante de la malla No.200 | D64: ASTM C117-23 | E64: SI | F64: - | G64: LABORATORIO | H64: 120 | I64: 3 dias
B65: AG26 | C65: Abrasión los Ángeles de agregado grueso de gran tamaño | D65: ASTM C535-16 (Reapproved 2024) | E65: SI | F65: - | G65: LABORATORIO | H65: 350 | I65: 3 dias | J65: * Se requiere realizar granulometria agregado AG19
B66: AG28 | C66: Gravedad especifica y absorción de agregado grueso | D66: ASTM C127-24 | E66: SI | F66: - | G66: LABORATORIO | H66: 120 | I66: 3 dias
B67: AG33 | C67: Angularidad del agregado fino. | D67: MTC E222 | E67: NO | F67: - | G67: LABORATORIO | H67: 120 | I67: 3 dias | J67: *Para realizar este ensayo se requiere del ensayo de Gravedad especifica del agregado fino
B68: AG34 | C68: Partículas planas y alargadas en agregado grueso | D68: ASTM D4791-19 (Reapproved 2023) | E68: SI | F68: ASTM D4791 | G68: LABORATORIO | H68: 120 | I68: 3 dias | J68: * Se requiere realizar granulometria agregado AG19
B69: AG35 | C69: Porcentaje de Caras fracturadas en agregado grueso | D69: ASTM D5821-13 (Reapproved 2017) | E69: SI | F69: - | G69: LABORATORIO | H69: 120 | I69: 3 dias | J69: * Se requiere realizar granulometria agregado AG19
B70: AG36 | C70: Abrasión los Ángeles de agregado grueso de tamaño pequeño. | D70: ASTM C131/C131M-20 | E70: SI | F70: - | G70: LABORATORIO | H70: 250 | I70: 3 dias | J70: * Se requiere realizar granulometria agregado AG19
C71: ENSAYO QUÍMICO AGREGADO
B72: AG11 | C72: Contenido Sales solubles, fino o grueso. | D72: MTC E-219 | E72: NO | F72: MTC E-219 | G72: LABORATORIO | H72: 150 | I72: 3 dias
B73: AG16 | C73: Contenido de cloruros solubles. | D73: NTP 400.042 | E73: NO | F73: - | G73: LABORATORIO | H73: 90 | I73: 3 dias
B74: AG17 | C74: Contenido de sulfatos solubles. | D74: NTP 400.042 | E74: NO | F74: - | G74: LABORATORIO | H74: 150 | I74: 3 dias
B75: AG29 | C75: Valor de azul de metileno. | D75: AASHTO TP57 | E75: NO | F75: AASHTO TO3 | G75: LABORATORIO | H75: 150 | I75: 3 dias
B76: AG30 | C76: Reactividad agregado alcálisis. | D76: ASTM C289-07 | E76: NO | F76: MTC E 217 | G76: LABORATORIO | H76: 650 | I76: 3 dias
B77: AG24 | C77: Partículas Liviana en los agregados (carbon y lignito), Fino o grueso. | D77: NTP 400.023 | E77: NO | F77: - | G77: LABORATORIO | H77: 220 | I77: 3 dias | J77: Antes era: Carbón y Lignito en agregado fino MTC E215
B78: AG25 | C78: Terrones de arcilla y partículas friables, Fino o grueso. | D78: NTP 400.015 | E78: NO | F78: ASTM C142 | G78: LABORATORIO | H78: 120 | I78: 3 dias | J78: ASTM C142/MTC E212 UNI
B79: AG12 | C79: Adherencia en agregado fino - Riedel Weber. | D79: MTC E 220 | E79: NO | F79: - | G79: LABORATORIO | H79: 150 | I79: 3 dias
B80: AG13 | C80: Impurezas Orgánicas en los áridos finos. | D80: ASTM C40-99 | E80: NO | F80: - | G80: LABORATORIO | H80: 150 | I80: 3 dias
C81: ENSAYO CONCRETO
B82: CO07 | C82: Resistencia a la Flexión del concreto. | D82: NTP 339.078/079 | E82: NO | F82: - | G82: LABORATORIO | H82: 100 | I82: 20 minutos
B83: CO08 | C83: Resistencia a la compresión de mortero con especimen cubicos de 50 mm. | D83: NTP 334.051 | E83: NO | F83: - | G83: LABORATORIO | H83: 25 | I83: 20 minutos
B84: CO12 | C84: Compresión de testigos cilíndricos de concreto | D84: ASTM C39/C39M-24 | E84: SI | F84: - | G84: LABORATORIO | H84: 15 | I84: 20 minutos | J84: Podemos curar las probetas
B85: CO12A | C85: El servicio incluye: - Suministro de modulo de madera, moldes para probetas cilíndricas de 4x8", varilla compactadora, comba de goma y cucharón. - Recojo de probetas. - Compresión de testigos cilíndricos de concreto - Emisión de informe. - Cantidad: Kit por 06 unidades | D85: ASTM C39/C39M-24 | E85: NO | G85: LABORATORIO | H85: 90
B86: CO14 | C86: Resistencia tracción simple por compresión diametral. | D86: NTP 339.084 | E86: NO | F86: - | G86: LABORATORIO | H86: 30 | I86: 20 minutos
B87: CO19 | C87: Refrentado de probetas cilíndricas de concreto (por cara). | D87: ASTM C617/C617M-23 | E87: NO | F87: - | G87: LABORATORIO | H87: 15 | I87: 20 minutos | J87: * Solo Es Para Probetas Que Se Realizara El Servicio De Ensayo De Compresion
B88: DIS01 | C88: Verificación diseño de mezcla | D88: ACI 211 | E88: NO | F88: - | G88: LABORATORIO | H88: 250 | I88: 1/2 dia | J88: Puede variar de acuerdo cantidad
B89: DIS02 | C89: Verificación diseño de mezcla con aditivo. | D89: ACI 211 | E89: NO | F89: - | G89: LABORATORIO | H89: 500 | I89: 1/2 dia | J89: Puede variar de acuerdo cantidad
B90: DIS03 | C90: Diseño de mezcla Teórico. | D90: ACI 211 | E90: NO | F90: - | G90: LABORATORIO | H90: 100 | I90: 20 minutos | J90: Siempre se debe realizar verificacion del diseño de mezcla
C91: ENSAYO CONCRETO DE CAMPO
B92: CO03A | C92: Extracción, tallado, refrentado y ensayo de compresión de testigos diamantino de concreto | D92: NTP 339.059 | E92: NO | F92: C 42 | G92: CAMPO | H92: 250 | I92: 4 hora | J92: Minimo por salida 3 puntos, se requiere saber en que estructura se sacara. Broca 2", 3" y 4" este ultimo recomendado por norma
B93: CO03B | C93: Extracción de testigos diamantino de concreto | D93: NTP 339.059 | E93: NO | F93: C 42 | G93: CAMPO | H93: 200 | I93: 1,1/2 hora | J93: Minimo por salida 3 puntos, se requiere saber en que estructura se sacara. Broca 2", 3" y 4" este ultimo recomendado por norma
B94: CO03C | C94: Tallado, refrentado y ensayo de compresión de testigos diamantino de concreto | D94: NTP 339.059 ASTM C39/C39M-24 | E94: NO | F94: C 42 | G94: LABORATORIO | H94: 80 | I94: 2 horas | J94: El cliente proporcionara las diamantina en laboratorio
B95: CO03D | C95: Resane de estructura a causa de la extracción de diamantino. | D95: - | E95: NO | F95: - | G95: CAMPO | H95: Sujeto a evaluación | I95: 30 minutos | J95: Esta sujeto a evaluacion de acuerdo a cantidad
B96: CO04 | C96: Esclerometría. | D96: NTP 339.181 | E96: NO | F96: C 805 | G96: CAMPO | H96: 80 | I96: 1,1/2 hora | J96: Minimo por salida 6 puntos
B97: CO11 | C97: Control de calidad del concreto fresco en obra: * Muestreo de concreto fresco cant. 6 probetas * Ensayo asentamiento del concreto (Slump) * Control de temperatura en el concreto * Resistencia a la compresión | D97: NTP 339.036 ASTM C39/C39M-24 | E97: NO | F97: - | G97: CAMPO | H97: 250 | I97: - | J97: El costo no incluye movilidad
C98: ENSAYO QUÍMICO EN CONCRETO
B99: CO15 | C99: Determinar el pH de las aguas usadas para elaborar morteros y concretos. | D99: NTP 334.190:2016 | E99: NO | F99: - | G99: LABORATORIO | H99: 100 | I99: 3 dias | J99: Ensayo en agua para concreto
B100: CO16 | C100: Determinar el contenido de sulfatos en las aguas usadas en la elaboración de morteros y concretos de cemento Pórtland. | D100: NTP 339.227:2016 | E100: NO | F100: - | G100: LABORATORIO | H100: 120 | I100: 3 dias | J100: Ensayo en agua para concreto
B101: CO17 | C101: Determinar el contenido del ion cloruro en las aguas usadas en la elaboración de concretos y morteros de cemento Pórtland. | D101: NTP 339.076:2017 | E101: NO | F101: - | G101: LABORATORIO | H101: 120 | I101: 3 dias | J101: Ensayo en agua para concreto
B102: SU27 | C102: Método de prueba estándar para la medición de sólidos en agua. | D102: ASTM C1603 | E102: NO | F102: - | G102: LABORATORIO | H102: 120 | I102: 3 dias | J102: Ensayo en agua para concreto
...

Sheet COND.
B2: CONDICIONES ESPECIFICAS PARA COTIZACION
B4: MUESTRA DE SUELO Y/O AGREGADO
B5: CONDICIONES ESPECÍFICAS - El cliente proporcionara al laboratorio para realizar el ensayo de suelo y/o agregados la cantidad mínima de 100 kg por cada muestra. - El cliente deberá de entregar las muestras debidamente identificadas. - El cliente deberá especificar la Norma a ser utilizada para la ejecución del ensayo, caso contrario se considera Norma ASTM o NTP vigente de acuerdo con el alcance del laboratorio. - El cliente deberá entregar las muestras en las instalaciones del LEM, ubicado en la Av. Marañón N° 763, Los Olivos, Lima.
B8: MUESTRA AGREGADO PARA DISEÑO MEZCLA
B9: CONDICIONES ESPECÍFICAS - El cliente proporcionara al laboratorio para realizar el diseño de mezcla de concreto la cantidad mínima de 70 kg de agregado grueso, 50 kg de agregado fino, 01 bolsa de cemento y 1 litro aditivo. - El cliente deberá entregar las muestras debidamente identificadas. - El cliente deberá especificar la Norma a ser utilizada para la ejecución del ensayo, caso contrario se considera Norma ASTM o NTP vigente de acuerdo con el alcance del laboratorio. - El cliente deberá entregar las muestras en las instalaciones del LEM, ubicado en la Av. Marañón N° 763, Los Olivos, Lima.
B12: PROBETAS
B13: CONDICIONES ESPECÍFICAS - La emisión de informes de ensayo con acreditación INACAL se realizará solo si la fuerza de falla de la probeta está dentro del rango de 50 kN a 800 kN. - El cliente deberá de entregar las muestras debidamente identificadas. - El cliente deberá especificar la Norma a ser utilizada para la ejecución del ensayo, caso contrario se considera Norma ASTM o NTP vigente de acuerdo con el alcance del laboratorio. - El cliente deberá entregar las muestras en las instalaciones del LEM, ubicado en la Av. Marañón N° 763, Los Olivos, Lima.
B15: DENSIDAD DE CAMPO POR PUNTO
B16: CONDICIONES ESPECÍFICAS - Para programar el ensayo de densidad de campo, la cantidad mínima de puntos por salida es de cuatro (4). - El cliente deberá de programar el servicio, Densidad de campo, con 24 horas de anticipación. - El cliente deberá especificar la Norma a ser utilizada para la ejecución del ensayo, caso contrario se considera Norma ASTM o NTP vigente de acuerdo con el alcance del laboratorio.
B18: DENSIDAD DE CAMPO POR DIA
B19: CONDICIONES ESPECÍFICAS - El servicio de Densidad en campo es por 01 día. - El cliente deberá de programar el servicio, con 24 horas de anticipación. - El servicio de movilización de personal y equipo (Densidad de campo), incluye ida y vuelta. - La movilización del personal técnico y de los equipos dentro del proyecto estarán a cargo del cliente. - El informe de ensayo de densidad de campo serán emitidos por Geofal y estará firmado por un ingeniero civil colegiado. - Los equipos de protección personal (EPP) y SCTR estará a cargo de Geofal. - El horario para los ensayos es de lunes a viernes de 9:00 am a 4:00 pm. - El cliente deberá especificar la Norma a ser utilizada para la ejecución del ensayo, caso contrario se considera Norma ASTM o NTP vigente de acuerdo con el alcance del laboratorio.
B21: DENSIDAD DE CAMPO Y RECOJO MUESTRA (AFIRMADO Y OTROS)
... B42: PLAZO ESTIMADO DE EJECUCIÓN DE SERVICIO - El plazo de entrega de los resultados se estima 08 dias hábiles, este tiempo será evaluado de acuerdo a la cantidad de muestra recepcionada y está sujeto a la programacion enviada por el área de LEM. - El laboratorio enviará un correo de confirmación de recepción y fecha de entrega del informe.

Sheet ING
G3: 41 | P3: ID CLIENTE | Q3: 560
B5: CLIENTE: | D5: =VLOOKUP($Q$3,BD_Clientes,2,FALSE) -> GEOFAL SAC | J5: PROYECTO1: | L5: URB. EL BOSQUE DE LA VICTORIA | P5: 222
B6: R.U.C.1: | D6: =VLOOKUP($Q$3,BD_Clientes,3,FALSE) -> 20549356762 | P6: 222
B7: CONTACTO: | D7: Angela Rosalia Paredes Curi | J7: UBICACIÓN1: | L7: - | P7: 222
B8: TELÉFONO DE CONTACTO: | E8: 913072224 | J8: PERSONAL COMERCIAL: | L8: Silvia Peralta
B9: CORREO: | D9: =VLOOKUP($Q$3,BD_Clientes,8,FALSE) -> ingenieria@geofal.com.pe | J9: TELÉFONO DE COMERCIAL: | L9: 982429895
B10: FECHA SOLICITUD: | E10: 46031 | J10: FECHA DE EMISIÓN: | L10: 46031
B11: REFERENCIA: Segùn lo solicitado vía correo electrónico / Whatsapp / Teléfono / Personalmente.
B12: 1: Información no considerada para las personas naturales.
B13: Por medio de la presente, tenemos el agrado de remitirle nuestra cotización en base a su solicitud, por los servicios de los siguientes ensayos de laboratorio.
B16: CÓDIGO | C16: DESCRIPCIÓN | J16: NORMA | K16: ACREDITADO | L16: COSTO UNITARIO | M16: CANTIDAD | N16: COSTO PARCIAL
C17: ENSAYOS DE LABORATORIO | L17: 900 | M17: 1 | N17: 900
B18: SU24 | C18: =VLOOKUP(B18,ENS.!$B$5:$H$167,2,FALSE) -> Análisis granulométrico por tamizado en Suelo | J18: =VLOOKUP(B18,ENS.!$B$5:$H$167,3,FALSE) -> ASTM D6913/D6913M-17 | K18: =VLOOKUP(B18,ENS.!$B$5:$H$167,4,FALSE) -> SI | M18: 1
B19: SU23 | C19: =VLOOKUP(B19,ENS.!$B$5:$H$167,2,FALSE) -> Límite líquido y Límite Plástico del Suelo | J19: =VLOOKUP(B19,ENS.!$B$5:$H$167,3,FALSE) -> ASTM D4318-17ε1 | K19: =VLOOKUP(B19,ENS.!$B$5:$H$167,4,FALSE) -> SI | M19: 1
B20: SU20 | C20: =VLOOKUP(B20,ENS.!$B$5:$H$167,2,FALSE) -> Contenido de humedad en suelos | J20: =VLOOKUP(B20,ENS.!$B$5:$H$167,3,FALSE) -> ASTM D2216-19 | K20: =VLOOKUP(B20,ENS.!$B$5:$H$167,4,FALSE) -> SI | M20: 1
B21: SU22 | C21: =VLOOKUP(B21,ENS.!$B$5:$H$167,2,FALSE) -> Clasificación suelo SUCS - AASHTO | J21: =VLOOKUP(B21,ENS.!$B$5:$H$167,3,FALSE) -> ASTM D2487-17 (Reapproved 2025) / ASTM D3282-24 | K21: =VLOOKUP(B21,ENS.!$B$5:$H$167,4,FALSE) -> SI | M21: 1
B22: SU13 | C22: =VLOOKUP(B22,ENS.!$B$5:$H$167,2,FALSE) -> Sales solubles en Suelos y Agua. | J22: =VLOOKUP(B22,ENS.!$B$5:$H$167,3,FALSE) -> NTP 339.152 | K22: =VLOOKUP(B22,ENS.!$B$5:$H$167,4,FALSE) -> NO | M22: 1
B23: SU14 | C23: =VLOOKUP(B23,ENS.!$B$5:$H$167,2,FALSE) -> Cloruros Solubles en Suelos y Agua. | J23: =VLOOKUP(B23,ENS.!$B$5:$H$167,3,FALSE) -> NTP 339.177 | K23: =VLOOKUP(B23,ENS.!$B$5:$H$167,4,FALSE) -> NO | M23: 1
B24: SU15 | C24: =VLOOKUP(B24,ENS.!$B$5:$H$167,2,FALSE) -> Sulfatos Solubles en Suelos y Agua. | J24: =VLOOKUP(B24,ENS.!$B$5:$H$167,3,FALSE) -> NTP 339.178 | K24: =VLOOKUP(B24,ENS.!$B$5:$H$167,4,FALSE) -> NO | M24: 1
B25: SU03 | C25: =VLOOKUP(B25,ENS.!$B$5:$H$167,2,FALSE) -> Determinación del PH en Suelo y Agua. | J25: =VLOOKUP(B25,ENS.!$B$5:$H$167,3,FALSE) -> NTP 339.176 | K25: =VLOOKUP(B25,ENS.!$B$5:$H$167,4,FALSE) -> NO | M25: 1
B26: SU05 | C26: =VLOOKUP(B26,ENS.!$B$5:$H$167,2,FALSE) -> Corte Directo. | J26: =VLOOKUP(B26,ENS.!$B$5:$H$167,3,FALSE) -> NTP 339.171 | K26: =VLOOKUP(B26,ENS.!$B$5:$H$167,4,FALSE) -> NO | M26: 1
B27: SU33 | C27: =VLOOKUP(B27,ENS.!$B$5:$H$167,2,FALSE) -> Resistencia a la Compresión no confinada de suelos cohesivos | J27: =VLOOKUP(B27,ENS.!$B$5:$H$167,3,FALSE) -> NTP 339.167 | K27: =VLOOKUP(B27,ENS.!$B$5:$H$167,4,FALSE) -> NO
B28: SU06A | C28: =VLOOKUP(B28,ENS.!$B$5:$H$167,2,FALSE) -> Densidad del suelo IN-SITU, Cono de Arena 6" | J28: =VLOOKUP(B28,ENS.!$B$5:$H$167,3,FALSE) -> NTP 339.143:1999 (revisada el 2019) | K28: =VLOOKUP(B28,ENS.!$B$5:$H$167,4,FALSE) -> SI
B29: RO01 | C29: =VLOOKUP(B29,ENS.!$B$5:$H$167,2,FALSE) -> Carga Puntual (incluye tallado y ensayo 10 especimenes). | J29: =VLOOKUP(B29,ENS.!$B$5:$H$167,3,FALSE) -> ASTM D 5731 | K29: =VLOOKUP(B29,ENS.!$B$5:$H$167,4,FALSE) -> NO
B30: RO02 | C30: =VLOOKUP(B30,ENS.!$B$5:$H$167,2,FALSE) -> Gravedad especifica y absorción de roca. | J30: =VLOOKUP(B30,ENS.!$B$5:$H$167,3,FALSE) -> ASTM D 6473 | K30: =VLOOKUP(B30,ENS.!$B$5:$H$167,4,FALSE) -> NO
B31: AG28 | C31: =VLOOKUP(B31,ENS.!$B$5:$H$167,2,FALSE) -> Gravedad especifica y absorción de agregado grueso | J31: =VLOOKUP(B31,ENS.!$B$5:$H$167,3,FALSE) -> ASTM C127-24 | K31: =VLOOKUP(B31,ENS.!$B$5:$H$167,4,FALSE) -> SI
B32: SU32 | C32: =VLOOKUP(B32,ENS.!$B$5:$H$167,2,FALSE) -> Gravedad específica de los sólidos del suelo. | J32: =VLOOKUP(B32,ENS.!$B$5:$H$167,3,FALSE) -> ASTM D854-14 | K32: =VLOOKUP(B32,ENS.!$B$5:$H$167,4,FALSE) -> NO
B33: SU19 | C33: =VLOOKUP(B33,ENS.!$B$5:$H$167,2,FALSE) -> Próctor modificado | J33: =VLOOKUP(B33,ENS.!$B$5:$H$167,3,FALSE) -> ASTM D1557-12 (Reapproved 2021) | K33: =VLOOKUP(B33,ENS.!$B$5:$H$167,4,FALSE) -> SI
B34: SU37 | C34: =VLOOKUP(B34,ENS.!$B$5:$H$167,2,FALSE) -> California Bearing Ratio (CBR) | J34: =VLOOKUP(B34,ENS.!$B$5:$H$167,3,FALSE) -> ASTM D1883-21 | K34: =VLOOKUP(B34,ENS.!$B$5:$H$167,4,FALSE) -> SI
B35: SU06A | C35: =VLOOKUP(B35,ENS.!$B$5:$H$167,2,FALSE) -> Densidad del suelo IN-SITU, Cono de Arena 6" | J35: =VLOOKUP(B35,ENS.!$B$5:$H$167,3,FALSE) -> NTP 339.143:1999 (revisada el 2019) | K35: =VLOOKUP(B35,ENS.!$B$5:$H$167,4,FALSE) -> SI
B36: SU45 | C36: =VLOOKUP(B36,ENS.!$B$5:$H$167,2,FALSE) -> Compresión triaxial no consolidado no drenado UU, diametro 75 mm | J36: =VLOOKUP(B36,ENS.!$B$5:$H$167,3,FALSE) -> ASTM D2850 | K36: =VLOOKUP(B36,ENS.!$B$5:$H$167,4,FALSE) -> NO
B37: SU46 | C37: =VLOOKUP(B37,ENS.!$B$5:$H$167,2,FALSE) -> Compresión triaxial consolidado no drenado CU, diametro 75 mm | J37: =VLOOKUP(B37,ENS.!$B$5:$H$167,3,FALSE) -> ASTM D4767 | K37: =VLOOKUP(B37,ENS.!$B$5:$H$167,4,FALSE) -> NO
B38: SU47 | C38: =VLOOKUP(B38,ENS.!$B$5:$H$167,2,FALSE) -> Compresión triaxial consolidado drenado CD, diametro 75 mm | J38: =VLOOKUP(B38,ENS.!$B$5:$H$167,3,FALSE) -> ASTM D7181 | K38: =VLOOKUP(B38,ENS.!$B$5:$H$167,4,FALSE) -> NO
L39: Costo parcial | N39: =SUM(N17:N38) -> 900
L40: IGV 18% | N40: =+N39*0.18 -> 162
L41: Costo Total (S/) | N41: =+N39+N40 -> 1062
B43: VALIDEZ DE LA OFERTA: 30 días calendario. Si la cotización llegó al límite de su validez, solicite una actualización.
B44: CONDICIONES ESPECÍFICAS PARA LOS ENSAYOS DE LABORATORIO: - El cliente deberá enviar al laboratorio, para los ensayo en suelos, la cantidad mínima de 30 kg para muestra fina y 70 kg para muestra gruesa. - El cliente deberá de entregar las muestras debidamente identificadas. - El cliente deberá especificar la Norma a ser utilizada para la ejecución del ensayo, caso contrario se considera Norma ASTM o NTP vigente de acuerdo con el alcance del laboratorio. - El cliente deberá entregar las muestras en las instalaciones del LEM, ubicado en la Av. Marañón N° 763, Los Olivos, Lima.
B45: PLAZO ESTIMADO DE EJECUCIÓN DE SERVICIO: - El plazo de entrega de los resultados se estima en 04 días hábiles, este tiempo será evaluado de acuerdo a la cantidad de muestra recepcionada y está sujeto a la programacion enviada por el Laboratorio de Ensayos de Materiales. - El laboratorio enviará un correo de confirmación de recepción y fecha de entrega del informe.
B46: COM-F-01 Página 1 de 2 Versión: 04 (10-11-2025)
B47: CONTRAMUESTRA Al finalizar los ensayos, la muestra sobrante/contramuestra permanecerán en custodia por un tiempo de 10 dias calendario después de emitido el informe de ensayo. Siempre que se trate de una muestra dirimente, las contramuestras serán devueltas a los clientes, previa coordinación y autorización, caso contrario, serán eliminadas si se trata de residuos del ensayo o contramuestras de ensayo.
B48: CONFIDENCIALIDAD: GEOFAL S.A.C mantiene acuerdos de confidencialidad entre el cliente y el laboratorio, la divulgación de la información sin la autorización de las partes, no es permitida. El laboratorio mantiene reserva de la información brindada por el cliente, salvo solicitud de la información por ley, o por entidades gubernamentales inmersos dentro del presente servicio de ensayo.
B49: QUEJAS Y SUGERENCIAS: El plazo máximo para la recepción de quejas relacionadas con un informe técnico es de diez (10) días calendarios, contados a partir de la fecha de emisión del documento correspondiente. Transcurrido dicho plazo, no se aceptarán quejas bajo ninguna circunstancia. En caso de tener alguna queja o sugerencia, lo invitamos a conocer nuestro Proceso de Atención de Quejas, el cual dará inicio 24 horas después de la recepción formal de la queja.
B50: ENTREGA DE INFORME DE ENSAYO: - De acuerdo a los lineamientos de INACAL - DM, los informes de ensayo son emitidos de forma digital con firma electrónica y QR. - La entrega de los informes de ensayo será mediante la plataforma de Intranet de la pagina web www.geofal.com.pe, y se enviará un correo de confirmación al cliente con el usuario y clave para el acceso. Asi mismo el cliente puede ingresar a la gruía deusuario que es visible en la página web. - Geofal no declara conformidad de sus informes de ensayo. - En caso se requiera la modificación del informe de ensayo a consecuencia de los datos proporcionados por el cliente, esta se realizará mediante la emisión de un nuevo informe que tendrá un costo adicional de acuerdo a evaluación.
B51: HORARIO DE ATENCIÓN El horario para recepción de muestra y entrega de informes es de Lunes a Viernes de 8:30am a 1:00pm y 2:00pm a 5:30pm, y Sábado de 8:30am a 12:30pm
B54: CONDICIÓN: El pago del servicio deberá ser realizado por Adelantado. | P54: CONDICIONES DE PAGO
B55: RAZON SOCIAL: Geofal S.A.C. RUC: 20549356762 | P55: CONDICIÓN: El pago del servicio se realizara de acuerdo a la valorización mensual
B56: Sírvase realizar el depósito correspondiente de los servicios a nuestra cuenta bancaria: | P56: CONDICIÓN: El pago del servicio deberá ser realizado por Adelantado.
B57: Cuenta de detraccion Banco de La Nación: | P57: CONDICIÓN: El pago del servicio Adelanto el 50% y saldo previo a la entrega del Informe.
B58: - Cuenta de detraccion Banco de La Nación: Nº 00-074-045472 | P58: CONDICIÓN: El pago del servicio Crédito a 7 días, previa orden de servicio.
B59: Cuenta corriente Interbank: | P59: CONDICIÓN: El pago del servicio Crédito a 30 días, previa orden de servicio.
B60: - Cuenta Corriente en Soles de Interbank: Nº 200-3005201096 | P60: CONDICIÓN: El pago del servicio Crédito a 15 días, previa orden de servicio.
B61: - Código Interbancario (CCI) de Interbank: Nº 003-200- 003005201096-31
B62: Cuenta corriente BCP:
B63: - Cuenta Corriente en Soles del Banco de Crédito del Perú (BCP): Nº 192 2024 3030 04
B64: - Código Interbancario (CCI) del Banco de Crédito del Perú (BCP): Nº 002-192-002 02430 3004-34
B65: Cuenta corriente BBVA:
B66: - Cuenta Corriente en Soles BBVA: Nº 0011-0174-0100082311-00
B67: - Código Interbancario (CCI) BBVA: Nº 011-174-000100082311-00
B71: La aceptación de la cotización por parte del cliente podrá manifestarse a través de cualquiera de las siguientes acciones: el pago correspondiente al servicio, el envío de la orden de servicio, o el envío de un correo electrónico confirmando la aceptación del servicio según la presente cotización, al correo asesorcomercial@geofal.com.pe y/o mediante mensaje de WhatsApp al número del asesor comercial, en señal de conformidad.
B73: Atentamente,
B75: Geofal SAC
B76: Av. Marañón N° 763, Los Olivos, Lima, Perù
B77: Teléfono laboratorio: (01) 7543070 / Teléfono Oficina: (01) 9051911
B78: Web: www.geofal.com.pe
B80: COM-F-01 Página 2 de 2 Versión: 04 (10-11-2025) | M80: Fin del documento

Sheet PROB7 (2)
G3: 44 | P3: ID CLIENTE | Q3: 1275
B5: CLIENTE: | D5: =VLOOKUP($Q$3,BD_Clientes,2,FALSE) -> INVERSIONES INMOBILIARIAS DE LAS CONDES S.A. (IMAGINA) | J5: PROYECTO1: | L5: =VLOOKUP($Q$3,BD_Clientes,9,FALSE) -> OCEAN BREATH | P5: 222
B6: R.U.C.1: | D6: =VLOOKUP($Q$3,BD_Clientes,3,FALSE) -> 20537745631 | P6: 222
B7: CONTACTO: | D7: =VLOOKUP($Q$3,BD_Clientes,5,FALSE) -> Ing. Vania Carhuamaca | J7: UBICACIÓN1: | L7: =VLOOKUP($Q$3,BD_Clientes,10,FALSE) -> Av. Costanera 2880 - San Miguel | P7: 222
B8: TELÉFONO DE CONTACTO: | E8: =VLOOKUP($Q$3,BD_Clientes,7,FALSE) -> 933372811 | J8: PERSONAL COMERCIAL: | L8: Silvia Peralta
B9: CORREO: | D9: =VLOOKUP($Q$3,BD_Clientes,8,FALSE) -> Vania.Carhuamaca@imagina.pe | J9: TELÉFONO DE COMERCIAL: | L9: 982429895
B10: FECHA SOLICITUD: | E10: 46031 | J10: FECHA DE EMISIÓN: | L10: 46031
B11: REFERENCIA: Según lo solicitado vía correo electrónico / Whatsapp / Teléfono / Personalmente.
B12: 1: Información no considerada para las personas naturales.
B13: Por medio de la presente, tenemos el agrado de remitirle nuestra cotización en base a su solicitud, por los servicios de los siguientes ensayos de laboratorio.
B16: CÓDIGO | C16: DESCRIPCIÓN | J16: NORMA | K16: ACREDITADO | L16: COSTO UNITARIO | M16: CANTIDAD | N16: COSTO PARCIAL
B17: CO12 | C17: =VLOOKUP(B17,ENS.!$B$5:$H$167,2,FALSE) -> Compresión de testigos cilíndricos de concreto | J17: =VLOOKUP(B17,ENS.!$B$5:$H$167,3,FALSE) -> ASTM C39/C39M-24 | K17: =VLOOKUP(B17,ENS.!$B$5:$H$167,4,FALSE) -> SI | L17: =VLOOKUP(B17,ENS.!$B$5:$H$167,7,FALSE) -> 15 | M17: 6 | N17: =+L17*M17 -> 90
B18: SER04 | C18: =VLOOKUP(B18,ENS.!$B$5:$H$167,2,FALSE) -> Movilización | J18: =VLOOKUP(B18,ENS.!$B$5:$H$167,3,FALSE) -> - | K18: =VLOOKUP(B18,ENS.!$B$5:$H$167,4,FALSE) -> NO | L18: 60 | M18: 1 | N18: =+L18*M18 -> 60
L19: Costo parcial | N19: =SUM(N17:N18) -> 150
L20: IGV 18% | N20: =+N19*0.18 -> 27
L21: Costo Total (S/) | N21: =+N19+N20 -> 177
B23: VALIDEZ DE LA OFERTA: 30 días calendario. Si la cotización llegó al límite de su validez, solicite una actualización.
B24: CONDICIONES ESPECÍFICAS PARA LOS ENSAYOS DE LABORATORIO: - Los informes de ensayo serán emitidos bajo la acreditación de INACAL únicamente si la fuerza de falla aplicada a la probeta se encuentra dentro del rango de 50 kN a 800 kN. - La cantidad mínima requerida para el recojo de testigos cilíndricos de concreto es de seis (06) unidades. - El cliente deberá de entregar las muestras debidamente identificadas. - El cliente deberá especificar la Norma a ser utilizada para la ejecución del ensayo, caso contrario se considera Norma ASTM vigente de acuerdo con el alcance del laboratorio.
B25: PLAZO ESTIMADO DE EJECUCIÓN DE SERVICIO: - El plazo de entrega de los resultados se estima de acuerdo a su programación de recepción, este tiempo será evaluado de acuerdo a la cantidad de muestra recepcionada y está sujeto a la programacion enviada por el área de LEM. - El laboratorio enviará un correo de confirmación de recepción y fecha de entrega del informe.
B27: COM-F-01 Página 1 de 2 Versión: 04 (10-11-2025)
B28: CONTRAMUESTRA Al finalizar los ensayos, la muestra sobrante/contramuestra permanecerán en custodia por un tiempo de 10 dias calendario después de emitido el informe de ensayo. Siempre que se trate de una muestra dirimente, las contramuestras serán devueltas a los clientes, previa coordinación y autorización, caso contrario, serán eliminadas si se trata de residuos del ensayo o contramuestras de ensayo.
B29: CONFIDENCIALIDAD: GEOFAL S.A.C mantiene acuerdos de confidencialidad entre el cliente y el laboratorio, la divulgación de la información sin la autorización de las partes, no es permitida. El laboratorio mantiene reserva de la información brindada por el cliente, salvo solicitud de la información por ley, o por entidades gubernamentales inmersos dentro del presente servicio de ensayo.
B30: QUEJAS Y SUGERENCIAS: El plazo máximo para la recepción de quejas relacionadas con un informe técnico es de diez (10) días calendarios, contados a partir de la fecha de emisión del documento correspondiente. Transcurrido dicho plazo, no se aceptarán quejas bajo ninguna circunstancia. En caso de tener alguna queja o sugerencia, lo invitamos a conocer nuestro Proceso de Atención de Quejas, el cual dará inicio 24 horas después de la recepción formal de la queja.
B31: ENTREGA DE INFORME DE ENSAYO: - De acuerdo a los lineamientos de INACAL - DM, los informes de ensayo son emitidos de forma digital con firma electrónica y QR. - La entrega de los informes de ensayo será mediante la plataforma de Intranet de la pagina web www.geofal.com.pe, y se enviará un correo de confirmación al cliente con el usuario y clave para el acceso. Asi mismo el cliente puede ingresar a la gruía deusuario que es visible en la página web. - Geofal no declara conformidad de sus informes de ensayo. - En caso se requiera la modificación del informe de ensayo a consecuencia de los datos proporcionados por el cliente, esta se realizará mediante la emisión de un nuevo informe que tendrá un costo adicional de acuerdo a evaluación.
B32: HORARIO DE ATENCIÓN El horario para recepción de muestra y entrega de informes es de Lunes a Viernes de 8:30am a 1:00pm y 2:00pm a 5:30pm, y Sábado de 8:30am a 12:30pm
B35: CONDICIÓN: El pago del servicio Crédito a 30 días, previa orden de servicio. | P35: CONDICIONES DE PAGO
B36: RAZON SOCIAL: Geofal S.A.C. RUC: 20549356762 | P36: CONDICIÓN: El pago del servicio se realizara de acuerdo a la valorización mensual
B37: Sírvase realizar el depósito correspondiente de los servicios a nuestra cuenta bancaria: | P37: CONDICIÓN: El pago del servicio deberá ser realizado por Adelantado.
B38: Cuenta de detraccion Banco de La Nación: | P38: CONDICIÓN: El pago del servicio Adelanto el 50% y saldo previo a la entrega del Informe.
B39: - Cuenta de detraccion Banco de La Nación: Nº 00-074-045472 | P39: CONDICIÓN: El pago del servicio Crédito a 7 días, previa orden de servicio.
B40: Cuenta corriente Interbank: | P40: CONDICIÓN: El pago del servicio Crédito a 30 días, previa orden de servicio.
B41: - Cuenta Corriente en Soles de Interbank: Nº 200-3005201096 | P41: CONDICIÓN: El pago del servicio Crédito a 15 días, previa orden de servicio.
B42: - Código Interbancario (CCI) de Interbank: Nº 003-200- 003005201096-31
B43: Cuenta corriente BCP:
B44: - Cuenta Corriente en Soles del Banco de Crédito del Perú (BCP): Nº 192 2024 3030 04
B45: - Código Interbancario (CCI) del Banco de Crédito del Perú (BCP): Nº 002-192-002 02430 3004-34
B46: Cuenta corriente BBVA:
B47: - Cuenta Corriente en Soles BBVA: Nº 0011-0174-0100082311-00
B48: - Código Interbancario (CCI) BBVA: Nº 011-174-000100082311-00
B52: La aceptación de la cotización por parte del cliente podrá manifestarse a través de cualquiera de las siguientes acciones: el pago correspondiente al servicio, el envío de la orden de servicio, o el envío de un correo electrónico confirmando la aceptación del servicio según la presente cotización, al correo asesorcomercial@geofal.com.pe y/o mediante mensaje de WhatsApp al número del asesor comercial, en señal de conformidad.
B54: Atentamente,
B56: Geofal SAC
B57: Av. Marañón N° 763, Los Olivos, Lima, Perù
B58: Teléfono laboratorio: (01) 7543070 / Teléfono Oficina: (01) 9051911
B59: Web: www.geofal.com.pe
B61: COM-F-01 Página 2 de 2 Versión: 04 (10-11-2025) | M61: Fin del documento

Sheet DENS-AG5 (2)
G3: 43 | P3: ID CLIENTE | Q3: 1276
B5: CLIENTE: | D5: =VLOOKUP($Q$3,BD_Clientes,2,FALSE) -> INVERSIONES INMOBILIARIAS DE PUERTO MADERO S.A. (IMAGINA) | J5: PROYECTO1: | L5: =VLOOKUP($Q$3,BD_Clientes,9,FALSE) -> ALTO METRO PARK ETAPA 1 | P5: 222
B6: R.U.C.1: | D6: =VLOOKUP($Q$3,BD_Clientes,3,FALSE) -> 20538391001 | P6: 222
B7: CONTACTO: | D7: =VLOOKUP($Q$3,BD_Clientes,5,FALSE) -> Ing. Luis Montesinos | J7: UBICACIÓN1: | L7: =VLOOKUP($Q$3,BD_Clientes,10,FALSE) -> Av. Óscar R. Benavides 262-264 - Callao | P7: 222
B8: TELÉFONO DE CONTACTO: | E8: =VLOOKUP($Q$3,BD_Clientes,7,FALSE) -> - | J8: PERSONAL COMERCIAL: | L8: Silvia Peralta
B9: CORREO: | D9: =VLOOKUP($Q$3,BD_Clientes,8,FALSE) -> Luis.Montesinos@imagina.pe | J9: TELÉFONO DE COMERCIAL: | L9: 982429895
B10: FECHA SOLICITUD: | E10: 46031 | J10: FECHA DE EMISIÓN: | L10: 46031
B11: REFERENCIA: Segùn lo solicitado vìa correo electrònico / Whatsapp / Teléfono / Personalmente.
B12: 1: Información no considerada para las personas naturales.
B13: Por medio de la presente, tenemos el agrado de remitirle nuestra cotización en base a su solicitud, por los servicios de los siguientes ensayos de laboratorio.
B16: CÓDIGO | C16: DESCRIPCIÓN | J16: NORMA | K16: ACREDITADO | L16: COSTO UNITARIO | M16: CANTIDAD | N16: COSTO PARCIAL
C17: ENSAYOS EN CONCRETO
B18: CO12 | C18: =VLOOKUP(B18,ENS.!$B$5:$H$167,2,FALSE) -> Compresión de testigos cilíndricos de concreto | J18: =VLOOKUP(B18,ENS.!$B$5:$H$167,3,FALSE) -> ASTM C39/C39M-24 | K18: =VLOOKUP(B18,ENS.!$B$5:$H$167,4,FALSE) -> SI | L18: =VLOOKUP(B18,ENS.!$B$5:$H$167,7,FALSE) -> 15 | M18: 1 | N18: =+L18*M18 -> 15
C19: ENSAYO PROCTOR MODIFICADO
B20: SU19 | C20: =VLOOKUP(B20,ENS.!$B$5:$H$167,2,FALSE) -> Próctor modificado | J20: =VLOOKUP(B20,ENS.!$B$5:$H$167,3,FALSE) -> ASTM D1557-12 (Reapproved 2021) | K20: =VLOOKUP(B20,ENS.!$B$5:$H$167,4,FALSE) -> SI | L20: =VLOOKUP(B20,ENS.!$B$5:$H$167,7,FALSE) -> 150 | M20: 1 | N20: =+L20*M20 -> 150
B21: SU32 | C21: =VLOOKUP(B21,ENS.!$B$5:$H$167,2,FALSE) -> Gravedad específica de los sólidos del suelo. | J21: =VLOOKUP(B21,ENS.!$B$5:$H$167,3,FALSE) -> ASTM D854-14 | K21: =VLOOKUP(B21,ENS.!$B$5:$H$167,4,FALSE) -> NO | L21: =VLOOKUP(B21,ENS.!$B$5:$H$167,7,FALSE) -> 120 | M21: 1 | N21: =+L21*M21 -> 120
B22: AG28 | C22: =VLOOKUP(B22,ENS.!$B$5:$H$167,2,FALSE) -> Gravedad especifica y absorción de agregado grueso | J22: =VLOOKUP(B22,ENS.!$B$5:$H$167,3,FALSE) -> ASTM C127-24 | K22: =VLOOKUP(B22,ENS.!$B$5:$H$167,4,FALSE) -> SI | L22: =VLOOKUP(B22,ENS.!$B$5:$H$167,7,FALSE) -> 120 | M22: 1 | N22: =+L22*M22 -> 120
B23: SU24 | C23: =VLOOKUP(B23,ENS.!$B$5:$H$167,2,FALSE) -> Análisis granulométrico por tamizado en Suelo | J23: =VLOOKUP(B23,ENS.!$B$5:$H$167,3,FALSE) -> ASTM D6913/D6913M-17 | K23: =VLOOKUP(B23,ENS.!$B$5:$H$167,4,FALSE) -> SI | L23: =VLOOKUP(B23,ENS.!$B$5:$H$167,7,FALSE) -> 100 | M23: 1 | N23: =+L23*M23 -> 100
C24: ENSAYOS DE CLASIFICACIÓN
B25: SU22 | C25: =VLOOKUP(B25,ENS.!$B$5:$H$167,2,FALSE) -> Clasificación suelo SUCS - AASHTO | J25: =VLOOKUP(B25,ENS.!$B$5:$H$167,3,FALSE) -> ASTM D2487-17 (Reapproved 2025) / ASTM D3282-24 | K25: =VLOOKUP(B25,ENS.!$B$5:$H$167,4,FALSE) -> SI | L25: =VLOOKUP(B25,ENS.!$B$5:$H$167,7,FALSE) -> 20 | M25: 1 | N25: =+L25*M25 -> 20
B26: SU23 | C26: =VLOOKUP(B26,ENS.!$B$5:$H$167,2,FALSE) -> Límite líquido y Límite Plástico del Suelo | J26: =VLOOKUP(B26,ENS.!$B$5:$H$167,3,FALSE) -> ASTM D4318-17ε1 | K26: =VLOOKUP(B26,ENS.!$B$5:$H$167,4,FALSE) -> SI | L26: =VLOOKUP(B26,ENS.!$B$5:$H$167,7,FALSE) -> 90 | M26: 1 | N26: =+L26*M26 -> 90
B27: SU24 | C27: =VLOOKUP(B27,ENS.!$B$5:$H$167,2,FALSE) -> Análisis granulométrico por tamizado en Suelo | J27: =VLOOKUP(B27,ENS.!$B$5:$H$167,3,FALSE) -> ASTM D6913/D6913M-17 | K27: =VLOOKUP(B27,ENS.!$B$5:$H$167,4,FALSE) -> SI | L27: =VLOOKUP(B27,ENS.!$B$5:$H$167,7,FALSE) -> 100 | M27: 1 | N27: =+L27*M27 -> 100
B28: SU20 | C28: =VLOOKUP(B28,ENS.!$B$5:$H$167,2,FALSE) -> Contenido de humedad en suelos | J28: =VLOOKUP(B28,ENS.!$B$5:$H$167,3,FALSE) -> ASTM D2216-19 | K28: =VLOOKUP(B28,ENS.!$B$5:$H$167,4,FALSE) -> SI | L28: =VLOOKUP(B28,ENS.!$B$5:$H$167,7,FALSE) -> 30 | M28: 1 | N28: =+L28*M28 -> 30
C29: ENSAYO DE DENSIDAD EN CAMPO - CONO DE ARENA 6"
B30: SU06A | C30: =VLOOKUP(B30,ENS.!$B$5:$H$167,2,FALSE) -> Densidad del suelo IN-SITU, Cono de Arena 6" | J30: =VLOOKUP(B30,ENS.!$B$5:$H$167,3,FALSE) -> NTP 339.143:1999 (revisada el 2019) | K30: =VLOOKUP(B30,ENS.!$B$5:$H$167,4,FALSE) -> SI | L30: =VLOOKUP(B30,ENS.!$B$5:$H$167,7,FALSE) -> 50 | M30: 4 | N30: =+L30*M30 -> 200
B31: SU20 | C31: =VLOOKUP(B31,ENS.!$B$5:$H$167,2,FALSE) -> Contenido de humedad en suelos | J31: =VLOOKUP(B31,ENS.!$B$5:$H$167,3,FALSE) -> ASTM D2216-19 | K31: =VLOOKUP(B31,ENS.!$B$5:$H$167,4,FALSE) -> SI | L31: 20 | M31: 4 | N31: =+L31*M31 -> 80
B32: SER01 | C32: =VLOOKUP(B32,ENS.!$B$5:$H$167,2,FALSE) -> Movilización de personal y equipo (Densidad campo). | J32: =VLOOKUP(B32,ENS.!$B$5:$H$167,3,FALSE) -> - | K32: =VLOOKUP(B32,ENS.!$B$5:$H$167,4,FALSE) -> NO | L32: 60 | M32: 1 | N32: =+L32*M32 -> 60
C33: ENSAYO DE DENSIDAD EN CAMPO - CONO DE ARENA 12"
B34: SU06B | C34: =VLOOKUP(B34,ENS.!$B$5:$H$167,2,FALSE) -> Densidad del suelo IN-SITU, Cono de Arena 12". | J34: =VLOOKUP(B34,ENS.!$B$5:$H$167,3,FALSE) -> NTP 339.143:1999 (revisada el 2019) | K34: =VLOOKUP(B34,ENS.!$B$5:$H$167,4,FALSE) -> NO | L34: =VLOOKUP(B34,ENS.!$B$5:$H$167,7,FALSE) -> 80 | M34: 4 | N34: =+L34*M34 -> 320
B35: SU20 | C35: =VLOOKUP(B35,ENS.!$B$5:$H$167,2,FALSE) -> Contenido de humedad en suelos | J35: =VLOOKUP(B35,ENS.!$B$5:$H$167,3,FALSE) -> ASTM D2216-19 | K35: =VLOOKUP(B35,ENS.!$B$5:$H$167,4,FALSE) -> SI | L35: 20 | M35: 4 | N35: =+L35*M35 -> 80
B36: SER01 | C36: =VLOOKUP(B36,ENS.!$B$5:$H$167,2,FALSE) -> Movilización de personal y equipo (Densidad campo). | J36: =VLOOKUP(B36,ENS.!$B$5:$H$167,3,FALSE) -> - | K36: =VLOOKUP(B36,ENS.!$B$5:$H$167,4,FALSE) -> NO | L36: 60 | M36: 1 | N36: =+L36*M36 -> 60
L37: Costo parci4al | N37: =SUM(N17:N36) -> 1545
L38: IGV 18% | N38: =+N37*0.18 -> 278.1
L39: Costo Total (S/) | N39: =+N37+N38 -> 1823.1
B41: VALIDEZ DE LA OFERTA: 30 días calendario. Si la cotización llegó al límite de su validez, solicite una actualización.
B42: COM-F-01 Página 1 de 2 Versión: 04 (10-11-2025)
B43: CONDICIONES ESPECÍFICAS PARA LOS ENSAYOS DE LABORATORIO: - El cliente deberá de enviar al laboratorio, para los ensayos del material, la cantidad mínima de 80 kg por cada tipo de muestra. - El cliente deberá de entregar las muestras debidamente identificadas. - Para el ensayo de Densidad de campo, la cantidad de puntos/salida mínimo 04 und. - El cliente deberá de programar el servicio, Densidad de campo, con 24 horas de anticipación. - El cliente deberá especificar la Norma a ser utilizada para la ejecución del ensayo, caso contrario se considera Norma ASTM o NTP vigente de acuerdo con el alcance del laboratorio.
B44: PLAZO ESTIMADO DE EJECUCIÓN DE SERVICIO: - El plazo de entrega de los resultados se estima en 05 días hábiles, este tiempo será evaluado de acuerdo a la cantidad de muestra recepcionada y está sujeto a la programacion enviada por el Laboratorio de Ensayos de Materiales. - El laboratorio enviará un correo de confirmación de recepción y fecha de entrega del informe.
B45: CONTRAMUESTRA Al finalizar los ensayos, la muestra sobrante/contramuestra permanecerán en custodia por un tiempo de 10 dias calendario después de emitido el informe de ensayo. Siempre que se trate de una muestra dirimente, las contramuestras serán devueltas a los clientes, previa coordinación y autorización, caso contrario, serán eliminadas si se trata de residuos del ensayo o contramuestras de ensayo.
B46: CONFIDENCIALIDAD: GEOFAL S.A.C mantiene acuerdos de confidencialidad entre el cliente y el laboratorio, la divulgación de la información sin la autorización de las partes, no es permitida. El laboratorio mantiene reserva de la información brindada por el cliente, salvo solicitud de la información por ley, o por entidades gubernamentales inmersos dentro del presente servicio de ensayo.
B47: QUEJAS Y SUGERENCIAS: El plazo máximo para la recepción de quejas relacionadas con un informe técnico es de diez (10) días calendarios, contados a partir de la fecha de emisión del documento correspondiente. Transcurrido dicho plazo, no se aceptarán quejas bajo ninguna circunstancia. En caso de tener alguna queja o sugerencia, lo invitamos a conocer nuestro Proceso de Atención de Quejas, el cual dará inicio 24 horas después de la recepción formal de la queja.
B48: ENTREGA DE INFORME DE ENSAYO: - De acuerdo a los lineamientos de INACAL - DM, los informes de ensayo son emitidos de forma digital con firma electrónica y QR. - La entrega de los informes de ensayo será mediante la plataforma de Intranet de la pagina web www.geofal.com.pe, y se enviará un correo de confirmación al cliente con el usuario y clave para el acceso. Asi mismo el cliente puede ingresar a la gruía deusuario que es visible en la página web. - Geofal no declara conformidad de sus informes de ensayo. - En caso se requiera la modificación del informe de ensayo a consecuencia de los datos proporcionados por el cliente, esta se realizará mediante la emisión de un nuevo informe que tendrá un costo adicional de acuerdo a evaluación.
B49: HORARIO DE ATENCIÓN El horario para recepción de muestra y entrega de informes es de Lunes a Viernes de 8:30am a 1:00pm y 2:00pm a 5:30pm, y Sábado de 8:30am a 12:30pm
B52: CONDICIÓN: El pago del servicio Crédito a 30 días, previa orden de servicio. | P52: CONDICIONES DE PAGO
B53: RAZON SOCIAL: Geofal S.A.C. RUC: 20549356762 | P53: CONDICIÓN: El pago del servicio se realizara de acuerdo a la valorización mensual
B54: Sírvase realizar el depósito correspondiente de los servicios a nuestra cuenta bancaria: | P54: CONDICIÓN: El pago del servicio deberá ser realizado por Adelantado.
B55: Cuenta de detraccion Banco de La Nación: | P55: CONDICIÓN: El pago del servicio Adelanto el 50% y saldo previo a la entrega del Informe.
B56: - Cuenta de detraccion Banco de La Nación: Nº 00-074-045472 | P56: CONDICIÓN: El pago del servicio Crédito a 7 días, previa orden de servicio.
B57: Cuenta corriente Interbank: | P57: CONDICIÓN: El pago del servicio Crédito a 30 días, previa orden de servicio.
B58: - Cuenta Corriente en Soles de Interbank: Nº 200-3005201096 | P58: CONDICIÓN: El pago del servicio Crédito a 15 días, previa orden de servicio.
B59: - Código Interbancario (CCI) de Interbank: Nº 003-200- 003005201096-31
B60: Cuenta corriente BCP:
B61: - Cuenta Corriente en Soles del Banco de Crédito del Perú (BCP): Nº 192 2024 3030 04
B62: - Código Interbancario (CCI) del Banco de Crédito del Perú (BCP): Nº 002-192-002 02430 3004-34
B63: Cuenta corriente BBVA:
B64: - Cuenta Corriente en Soles BBVA: Nº 0011-0174-0100082311-00
B65: - Código Interbancario (CCI) BBVA: Nº 011-174-000100082311-00
B69: La aceptación de la cotización por parte del cliente podrá manifestarse a través de cualquiera de las siguientes acciones: el pago correspondiente al servicio, el envío de la orden de servicio, o el envío de un correo electrónico confirmando la aceptación del servicio según la presente cotización, al correo asesorcomercial@geofal.com.pe y/o mediante mensaje de WhatsApp al número del asesor comercial, en señal de conformidad.
B71: Atentamente,
B73: Geofal SAC
B74: Av. Marañón N° 763, Los Olivos, Lima, Perù
B75: Teléfono laboratorio: (01) 7543070 / Teléfono Oficina: (01) 9051911
B76: Web: www.geofal.com.pe
B78: COM-F-01 Página 2 de 2 Versión: 04 (10-11-2025) | M78: Fin del documento

Sheet PROB6 (2)
G3: 43 | P3: ID CLIENTE | Q3: 1275
B5: CLIENTE: | D5: =VLOOKUP($Q$3,BD_Clientes,2,FALSE) -> INVERSIONES INMOBILIARIAS DE LAS CONDES S.A. (IMAGINA) | J5: PROYECTO1: | L5: =VLOOKUP($Q$3,BD_Clientes,9,FALSE) -> OCEAN BREATH | P5: 222
B6: R.U.C.1: | D6: =VLOOKUP($Q$3,BD_Clientes,3,FALSE) -> 20537745631 | P6: 222
B7: CONTACTO: | D7: =VLOOKUP($Q$3,BD_Clientes,5,FALSE) -> Ing. Vania Carhuamaca | J7: UBICACIÓN1: | L7: =VLOOKUP($Q$3,BD_Clientes,10,FALSE) -> Av. Costanera 2880 - San Miguel | P7: 222
B8: TELÉFONO DE CONTACTO: | E8: =VLOOKUP($Q$3,BD_Clientes,7,FALSE) -> 933372811 | J8: PERSONAL COMERCIAL: | L8: Silvia Peralta
B9: CORREO: | D9: =VLOOKUP($Q$3,BD_Clientes,8,FALSE) -> Vania.Carhuamaca@imagina.pe | J9: TELÉFONO DE COMERCIAL: | L9: 982429895
B10: FECHA SOLICITUD: | E10: 46031 | J10: FECHA DE EMISIÓN: | L10: 46031
B11: REFERENCIA: Según lo solicitado vía correo electrónico / Whatsapp / Teléfono / Personalmente.
B12: 1: Información no considerada para las personas naturales.
B13: Por medio de la presente, tenemos el agrado de remitirle nuestra cotización en base a su solicitud, por los servicios de los siguientes ensayos de laboratorio.
B16: CÓDIGO | C16: DESCRIPCIÓN | J16: NORMA | K16: ACREDITADO | L16: COSTO UNITARIO | M16: CANTIDAD | N16: COSTO PARCIAL
C17: Control de Calidad de Testigos de Concreto en Obra
B18: CO12 | C18: =VLOOKUP(B18,ENS.!$B$5:$H$167,2,FALSE) -> Compresión de testigos cilíndricos de concreto | J18: =VLOOKUP(B18,ENS.!$B$5:$H$167,3,FALSE) -> ASTM C39/C39M-24 | K18: =VLOOKUP(B18,ENS.!$B$5:$H$167,4,FALSE) -> SI | L18: 90 | M18: 1 | N18: =+L18*M18 -> 90
C19: El servicio incluye: - Suministro de modulo de madera, moldes para probetas cilíndricas de 4x8", varilla compactadora, comba de goma y cucharón. - Recojo de probetas. - Compresión de testigos cilíndricos de concreto. - Emisión de informe. - Cantidad: Kit por 06 unidades | J19: - | K19: -
L20: Costo parcial | N20: =SUM(N17:N19) -> 90
L21: IGV 18% | N21: =+N20*0.18 -> 16.2
L22: Costo Total (S/) | N22: =+N20+N21 -> 106.2
B24: VALIDEZ DE LA OFERTA: 30 días calendario. Si la cotización llegó al límite de su validez, solicite una actualización.
B25: CONDICIONES ESPECÍFICAS PARA LOS ENSAYOS DE LABORATORIO: - Se brindará capacitación al personal responsable de realizar el muestreo y elaboración de los testigos de concreto en obra. - Se proporcionará en calidad de préstamo 01 modulo de madera, 01 kit de 6 moldes de pvc de 4"x8", 01 varilla compactadora, 01 comba de goma, 01 cucharón. - Se realizará el recojo en obra de los testigos de concreto, al día siguiente de efectuado el muestreo, en el horario de lunes a viernes de 8:00 a.m. a 4:00 p.m. y sábados de 8:00 a.m. a 12:00 p.m. - El cliente entregará los testigos de concreto debidamente identificados. - Los testigos de concreto serán curados en cámaras con humedad y temperatura controlada, hasta la edad programada de ensayo. - El horario para los ensayos es de lunes a viernes de 8:00 a.m. a 6:00 p.m. y sábados de 8:00 a.m. a 01:00 pm. En caso de que la programación coincida con días no laborables, los ensayos serán reprogramados para el día hábil inmediato siguiente. - El ensayo de compresión será de 03 testigos a 07 días y 03 testigos a 28 días de edad, bajo la norma ASTM C39/C39M-24. - La emisión y envio de informe de ensayo será firmado por un ingeniero civil colegiado. - Los informes de ensayo serán emitidos bajo la acreditación de INACAL únicamente si la fuerza de falla aplicada a la probeta se encuentra dentro del rango de 50 kN a 800 kN. - Para el inicio del servicio, se requiere una cantidad mínima de 20 kits por mes. - En caso de extravíos o daños de los módulos de madera, moldes de plástico y accesorios complementarios para muestreo se considera un costo adicional por reposición, según el siguiente detalle: Módulo de madera: S/. 80.00, Moldes plásticos: S/. 15.00, Varilla compactadora: S/. 50.00 y Comba de goma: S/. 30.00.
B26: COM-F-01 Página 1 de 2 Versión: 04 (10-11-2025)
B27: PLAZO ESTIMADO DE EJECUCIÓN DE SERVICIO: - El plazo de entrega de los resultados se estima de acuerdo a su programación de recepción, este tiempo será evaluado de acuerdo a la cantidad de muestra recepcionada y está sujeto a la programacion enviada por el área de LEM. - El laboratorio enviará un correo de confirmación de recepción y fecha de entrega del informe.
B28: CONTRAMUESTRA Al finalizar los ensayos, la muestra sobrante/contramuestra permanecerán en custodia por un tiempo de 10 dias calendario después de emitido el informe de ensayo. Siempre que se trate de una muestra dirimente, las contramuestras serán devueltas a los clientes, previa coordinación y autorización, caso contrario, serán eliminadas si se trata de residuos del ensayo o contramuestras de ensayo.
B29: CONFIDENCIALIDAD: GEOFAL S.A.C mantiene acuerdos de confidencialidad entre el cliente y el laboratorio, la divulgación de la información sin la autorización de las partes, no es permitida. El laboratorio mantiene reserva de la información brindada por el cliente, salvo solicitud de la información por ley, o por entidades gubernamentales inmersos dentro del presente servicio de ensayo.
B30: QUEJAS Y SUGERENCIAS: El plazo máximo para la recepción de quejas relacionadas con un informe técnico es de diez (10) días calendarios, contados a partir de la fecha de emisión del documento correspondiente. Transcurrido dicho plazo, no se aceptarán quejas bajo ninguna circunstancia. En caso de tener alguna queja o sugerencia, lo invitamos a conocer nuestro Proceso de Atención de Quejas, el cual dará inicio 24 horas después de la recepción formal de la queja.
B31: ENTREGA DE INFORME DE ENSAYO: - De acuerdo a los lineamientos de INACAL - DM, los informes de ensayo son emitidos de forma digital con firma electrónica y QR. - La entrega de los informes de ensayo será mediante la plataforma de Intranet de la pagina web www.geofal.com.pe, y se enviará un correo de confirmación al cliente con el usuario y clave para el acceso. Asi mismo el cliente puede ingresar a la gruía deusuario que es visible en la página web. - Geofal no declara conformidad de sus informes de ensayo. - En caso se requiera la modificación del informe de ensayo a consecuencia de los datos proporcionados por el cliente, esta se realizará mediante la emisión de un nuevo informe que tendrá un costo adicional de acuerdo a evaluación.
B32: HORARIO DE ATENCIÓN El horario para recepción de muestra y entrega de informes es de Lunes a Viernes de 8:30am a 1:00pm y 2:00pm a 5:30pm, y Sábado de 8:30am a 12:30pm
B35: CONDICIÓN: Valorización mensual y emisión de factura con credito a 15 días. | P35: CONDICIONES DE PAGO
B36: RAZON SOCIAL: Geofal S.A.C. RUC: 20549356762 | P36: CONDICIÓN: El pago del servicio se realizara de acuerdo a la valorización mensual
B37: Sírvase realizar el depósito correspondiente de los servicios a nuestra cuenta bancaria: | P37: CONDICIÓN: El pago del servicio deberá ser realizado por Adelantado.
B38: Cuenta de detraccion Banco de La Nación: | P38: CONDICIÓN: El pago del servicio Adelanto el 50% y saldo previo a la entrega del Informe.
B39: - Cuenta de detraccion Banco de La Nación: Nº 00-074-045472 | P39: CONDICIÓN: El pago del servicio Crédito a 7 días, previa orden de servicio.
B40: Cuenta corriente Interbank: | P40: CONDICIÓN: El pago del servicio Crédito a 30 días, previa orden de servicio.
B41: - Cuenta Corriente en Soles de Interbank: Nº 200-3005201096 | P41: CONDICIÓN: El pago del servicio Crédito a 15 días, previa orden de servicio.
B42: - Código Interbancario (CCI) de Interbank: Nº 003-200- 003005201096-31
B43: Cuenta corriente BCP:
B44: - Cuenta Corriente en Soles del Banco de Crédito del Perú (BCP): Nº 192 2024 3030 04
B45: - Código Interbancario (CCI) del Banco de Crédito del Perú (BCP): Nº 002-192-002 02430 3004-34
B46: Cuenta corriente BBVA:
B47: - Cuenta Corriente en Soles BBVA: Nº 0011-0174-0100082311-00
B48: - Código Interbancario (CCI) BBVA: Nº 011-174-000100082311-00
B52: La aceptación de la cotización por parte del cliente podrá manifestarse a través de cualquiera de las siguientes acciones: el pago correspondiente al servicio, el envío de la orden de servicio, o el envío de un correo electrónico confirmando la aceptación del servicio según la presente cotización, al correo asesorcomercial@geofal.com.pe y/o mediante mensaje de WhatsApp al número del asesor comercial, en señal de conformidad.
B54: Atentamente,
B56: Geofal SAC
B57: Av. Marañón N° 763, Los Olivos, Lima, Perù
B58: Teléfono laboratorio: (01) 7543070 / Teléfono Oficina: (01) 9051911
B59: Web: www.geofal.com.pe
B61: COM-F-01 Página 2 de 2 Versión: 04 (10-11-2025) | M61: Fin del documento

Sheet PROB6 (3)
G3: 42 | P3: ID CLIENTE | Q3: 1103
B5: CLIENTE: | D5: =VLOOKUP($Q$3,BD_Clientes,2,FALSE) -> CHINA ROAD AND BRIDGE CORPORATION SUCURSAL PERU | J5: PROYECTO1: | L5: =VLOOKUP($Q$3,BD_Clientes,9,FALSE) -> Hospital Papa Francisco | P5: 222
B6: R.U.C.1: | D6: =VLOOKUP($Q$3,BD_Clientes,3,FALSE) -> 20605171941 | P6: 222
B7: CONTACTO: | D7: =VLOOKUP($Q$3,BD_Clientes,5,FALSE) -> Ing. Fernando Revatta Paz | J7: UBICACIÓN1: | L7: =VLOOKUP($Q$3,BD_Clientes,10,FALSE) -> Manchay - Pachacamac - Lima | P7: 222
B8: TELÉFONO DE CONTACTO: | E8: =VLOOKUP($Q$3,BD_Clientes,7,FALSE) -> 994198563 | J8: PERSONAL COMERCIAL: | L8: Silvia Peralta
B9: CORREO: | D9: =VLOOKUP($Q$3,BD_Clientes,8,FALSE) -> frevatta@crbcperu.com | J9: TELÉFONO DE COMERCIAL: | L9: 982429895
B10: FECHA SOLICITUD: | E10: 46031 | J10: FECHA DE EMISIÓN: | L10: 46031
B11: REFERENCIA: Según lo solicitado vía correo electrónico / Whatsapp / Teléfono / Personalmente.
B12: 1: Información no considerada para las personas naturales.
B13: Por medio de la presente, tenemos el agrado de remitirle nuestra cotización en base a su solicitud, por los servicios de los siguientes ensayos de laboratorio.
B16: CÓDIGO | C16: DESCRIPCIÓN | J16: NORMA | K16: ACREDITADO | L16: COSTO UNITARIO | M16: CANTIDAD | N16: COSTO PARCIAL
C17: Control de Calidad de Testigos de Concreto en Obra
B18: CO12A | C18: =VLOOKUP(B18,ENS.!$B$5:$H$167,2,FALSE) -> El servicio incluye: - Suministro de modulo de madera, moldes para probetas cilíndricas de 4x8", varilla compactadora, comba de goma y cucharón. - Recojo de probetas. - Compresión de testigos cilíndricos de concreto - Emisión de informe. - Cantidad: Kit por 06 unidades | J18: =VLOOKUP(B18,ENS.!$B$5:$H$167,3,FALSE) -> ASTM C39/C39M-24 | K18: =VLOOKUP(B18,ENS.!$B$5:$H$167,4,FALSE) -> NO | L18: =VLOOKUP(B18,ENS.!$B$5:$H$167,7,FALSE) -> 90 | M18: 1 | N18: =+L18*M18 -> 90
C19: El servicio incluye: - Suministro de modulo de madera, moldes para probetas cilíndricas de 4x8", varilla compactadora, comba de goma y cucharón. - Recojo de probetas. - Compresión de testigos cilíndricos de concreto. - Emisión de informe. - Cantidad: Kit por 06 unidades | J19: - | K19: -
L20: Costo parcial | N20: =SUM(N17:N19) -> 90
L21: IGV 18% | N21: =+N20*0.18 -> 16.2
L22: Costo Total (S/) | N22: =+N20+N21 -> 106.2
B24: VALIDEZ DE LA OFERTA: 30 días calendario. Si la cotización llegó al límite de su validez, solicite una actualización.
B25: CONDICIONES ESPECÍFICAS PARA LOS ENSAYOS DE LABORATORIO: - Se brindará capacitación al personal responsable de realizar el muestreo y elaboración de los testigos de concreto en obra. - Se proporcionará en calidad de préstamo 01 modulo de madera, 01 kit de 6 moldes de pvc de 4"x8", 01 varilla compactadora, 01 comba de goma, 01 cucharón. - Se realizará el recojo en obra de los testigos de concreto, al día siguiente de efectuado el muestreo, en el horario de lunes a viernes de 8:00 a.m. a 4:00 p.m. y sábados de 8:00 a.m. a 12:00 p.m. - El cliente entregará los testigos de concreto debidamente identificados. - Los testigos de concreto serán curados en cámaras con humedad y temperatura controlada, hasta la edad programada de ensayo. - El horario para los ensayos es de lunes a viernes de 8:00 a.m. a 6:00 p.m. y sábados de 8:00 a.m. a 01:00 pm. En caso de que la programación coincida con días no laborables, los ensayos serán reprogramados para el día hábil inmediato siguiente. - El ensayo de compresión será de 03 testigos a 07 días y 03 testigos a 28 días de edad, bajo la norma ASTM C39/C39M-24. - La emisión y envio de informe de ensayo será firmado por un ingeniero civil colegiado. - Los informes de ensayo serán emitidos bajo la acreditación de INACAL únicamente si la fuerza de falla aplicada a la probeta se encuentra dentro del rango de 50 kN a 800 kN. - Para el inicio del servicio, se requiere una cantidad mínima de 20 kits por mes. - En caso de extravíos o daños de los módulos de madera, moldes de plástico y accesorios complementarios para muestreo se considera un costo adicional por reposición, según el siguiente detalle: Módulo de madera: S/. 80.00, Moldes plásticos: S/. 15.00, Varilla compactadora: S/. 50.00 y Comba de goma: S/. 30.00.
B26: COM-F-01 Página 1 de 2 Versión: 04 (10-11-2025)
B27: PLAZO ESTIMADO DE EJECUCIÓN DE SERVICIO: - El plazo de entrega de los resultados se estima de acuerdo a su programación de recepción, este tiempo será evaluado de acuerdo a la cantidad de muestra recepcionada y está sujeto a la programacion enviada por el área de LEM. - El laboratorio enviará un correo de confirmación de recepción y fecha de entrega del informe.
B28: CONTRAMUESTRA Al finalizar los ensayos, la muestra sobrante/contramuestra permanecerán en custodia por un tiempo de 10 dias calendario después de emitido el informe de ensayo. Siempre que se trate de una muestra dirimente, las contramuestras serán devueltas a los clientes, previa coordinación y autorización, caso contrario, serán eliminadas si se trata de residuos del ensayo o contramuestras de ensayo.
B29: CONFIDENCIALIDAD: GEOFAL S.A.C mantiene acuerdos de confidencialidad entre el cliente y el laboratorio, la divulgación de la información sin la autorización de las partes, no es permitida. El laboratorio mantiene reserva de la información brindada por el cliente, salvo solicitud de la información por ley, o por entidades gubernamentales inmersos dentro del presente servicio de ensayo.
B30: QUEJAS Y SUGERENCIAS: El plazo máximo para la recepción de quejas relacionadas con un informe técnico es de diez (10) días calendarios, contados a partir de la fecha de emisión del documento correspondiente. Transcurrido dicho plazo, no se aceptarán quejas bajo ninguna circunstancia. En caso de tener alguna queja o sugerencia, lo invitamos a conocer nuestro Proceso de Atención de Quejas, el cual dará inicio 24 horas después de la recepción formal de la queja.
B31: ENTREGA DE INFORME DE ENSAYO: - De acuerdo a los lineamientos de INACAL - DM, los informes de ensayo son emitidos de forma digital con firma electrónica y QR. - La entrega de los informes de ensayo será mediante la plataforma de Intranet de la pagina web www.geofal.com.pe, y se enviará un correo de confirmación al cliente con el usuario y clave para el acceso. Asi mismo el cliente puede ingresar a la gruía deusuario que es visible en la página web. - Geofal no declara conformidad de sus informes de ensayo. - En caso se requiera la modificación del informe de ensayo a consecuencia de los datos proporcionados por el cliente, esta se realizará mediante la emisión de un nuevo informe que tendrá un costo adicional de acuerdo a evaluación.
B32: HORARIO DE ATENCIÓN El horario para recepción de muestra y entrega de informes es de Lunes a Viernes de 8:30am a 1:00pm y 2:00pm a 5:30pm, y Sábado de 8:30am a 12:30pm
B35: CONDICIÓN: Valorización mensual y emisión de factura con credito a 15 días. | P35: CONDICIONES DE PAGO
B36: RAZON SOCIAL: Geofal S.A.C. RUC: 20549356762 | P36: CONDICIÓN: El pago del servicio se realizara de acuerdo a la valorización mensual
B37: Sírvase realizar el depósito correspondiente de los servicios a nuestra cuenta bancaria: | P37: CONDICIÓN: El pago del servicio deberá ser realizado por Adelantado.
B38: Cuenta de detraccion Banco de La Nación: | P38: CONDICIÓN: El pago del servicio Adelanto el 50% y saldo previo a la entrega del Informe.
B39: - Cuenta de detraccion Banco de La Nación: Nº 00-074-045472 | P39: CONDICIÓN: El pago del servicio Crédito a 7 días, previa orden de servicio.
B40: Cuenta corriente Interbank: | P40: CONDICIÓN: El pago del servicio Crédito a 30 días, previa orden de servicio.
B41: - Cuenta Corriente en Soles de Interbank: Nº 200-3005201096 | P41: CONDICIÓN: El pago del servicio Crédito a 15 días, previa orden de servicio.
B42: - Código Interbancario (CCI) de Interbank: Nº 003-200- 003005201096-31
B43: Cuenta corriente BCP:
B44: - Cuenta Corriente en Soles del Banco de Crédito del Perú (BCP): Nº 192 2024 3030 04
B45: - Código Interbancario (CCI) del Banco de Crédito del Perú (BCP): Nº 002-192-002 02430 3004-34
B46: Cuenta corriente BBVA:
B47: - Cuenta Corriente en Soles BBVA: Nº 0011-0174-0100082311-00
B48: - Código Interbancario (CCI) BBVA: Nº 011-174-000100082311-00
B52: La aceptación de la cotización por parte del cliente podrá manifestarse a través de cualquiera de las siguientes acciones: el pago correspondiente al servicio, el envío de la orden de servicio, o el envío de un correo electrónico confirmando la aceptación del servicio según la presente cotización, al correo asesorcomercial@geofal.com.pe y/o mediante mensaje de WhatsApp al número del asesor comercial, en señal de conformidad.
B54: Atentamente,
B56: Geofal SAC
B57: Av. Marañón N° 763, Los Olivos, Lima, Perù
B58: Teléfono laboratorio: (01) 7543070 / Teléfono Oficina: (01) 9051911
B59: Web: www.geofal.com.pe
B61: COM-F-01 Página 2 de 2 Versión: 04 (10-11-2025) | M61: Fin del documento

Sheet D.MEZCLA3
G3: 30 | P3: ID CLIENTE | Q3: 1248
B5: CLIENTE: | D5: =VLOOKUP($Q$3,BD_Clientes,2,FALSE) -> CONDUTO PERU S.A.C. | J5: PROYECTO1: | L5: =VLOOKUP($Q$3,BD_Clientes,9,FALSE) -> - | P5: 222
B6: R.U.C.1: | D6: =VLOOKUP($Q$3,BD_Clientes,3,FALSE) -> 20512864644 | P6: 222
B7: CONTACTO: | D7: =VLOOKUP($Q$3,BD_Clientes,5,FALSE) -> Ing. Kateryne Santana | J7: UBICACIÓN1: | L7: =VLOOKUP($Q$3,BD_Clientes,10,FALSE) -> - | P7: 222
B8: TELÉFONO DE CONTACTO: | E8: =VLOOKUP($Q$3,BD_Clientes,7,FALSE) -> 989228691 | J8: PERSONAL COMERCIAL: | L8: Silvia Peralta
B9: CORREO: | D9: =VLOOKUP($Q$3,BD_Clientes,8,FALSE) -> ksantana@conduto.com.pe | J9: TELÉFONO DE COMERCIAL: | L9: 982429895
B10: FECHA SOLICITUD: | E10: 46030 | J10: FECHA DE EMISIÓN: | L10: 46030
B11: REFERENCIA: Segùn lo solicitado vía correo electrónico / Whatsapp / Teléfono / Personalmente.
B12: 1: Información no considerada para las personas naturales.
B13: Por medio de la presente, tenemos el agrado de remitirle nuestra cotización en base a su solicitud, por los servicios de los siguientes ensayos de laboratorio.
B16: CÓDIGO | C16: DESCRIPCIÓN | J16: NORMA | K16: ACREDITADO | L16: COSTO UNITARIO | M16: CANTIDAD | N16: COSTO PARCIAL
C17: ANALISIS DE MATERIAL PARA RELLENO
B18: AG19 | C18: =VLOOKUP(B18,ENS.!$B$5:$H$167,2,FALSE) -> Análisis granulométrico por tamizado en agregado | J18: =VLOOKUP(B18,ENS.!$B$5:$H$167,3,FALSE) -> ASTM C136/C136M-19 | K18: =VLOOKUP(B18,ENS.!$B$5:$H$167,4,FALSE) -> SI | L18: =VLOOKUP(B18,ENS.!$B$5:$H$167,7,FALSE) -> 100 | M18: 1 | N18: =+L18*M18 -> 100
B19: AG20 | C19: =VLOOKUP(B19,ENS.!$B$5:$H$167,2,FALSE) -> Contenido de humedad en agregado | J19: =VLOOKUP(B19,ENS.!$B$5:$H$167,3,FALSE) -> ASTM C566-19 | K19: =VLOOKUP(B19,ENS.!$B$5:$H$167,4,FALSE) -> SI | L19: =VLOOKUP(B19,ENS.!$B$5:$H$167,7,FALSE) -> 30 | M19: 1 | N19: =+L19*M19 -> 30
B20: SU23 | C20: =VLOOKUP(B20,ENS.!$B$5:$H$167,2,FALSE) -> Límite líquido y Límite Plástico del Suelo | J20: =VLOOKUP(B20,ENS.!$B$5:$H$167,3,FALSE) -> ASTM D4318-17ε1 | K20: =VLOOKUP(B20,ENS.!$B$5:$H$167,4,FALSE) -> SI | L20: =VLOOKUP(B20,ENS.!$B$5:$H$167,7,FALSE) -> 90 | M20: 1 | N20: =+L20*M20 -> 90
B21: SU19 | C21: =VLOOKUP(B21,ENS.!$B$5:$H$167,2,FALSE) -> Próctor modificado | J21: =VLOOKUP(B21,ENS.!$B$5:$H$167,3,FALSE) -> ASTM D1557-12 (Reapproved 2021) | K21: =VLOOKUP(B21,ENS.!$B$5:$H$167,4,FALSE) -> SI | L21: =VLOOKUP(B21,ENS.!$B$5:$H$167,7,FALSE) -> 150 | M21: 1 | N21: =+L21*M21 -> 150
B22: SU32 | C22: =VLOOKUP(B22,ENS.!$B$5:$H$167,2,FALSE) -> Gravedad específica de los sólidos del suelo. | J22: =VLOOKUP(B22,ENS.!$B$5:$H$167,3,FALSE) -> ASTM D854-14 | K22: =VLOOKUP(B22,ENS.!$B$5:$H$167,4,FALSE) -> NO | L22: =VLOOKUP(B22,ENS.!$B$5:$H$167,7,FALSE) -> 120 | M22: 1 | N22: =+L22*M22 -> 120
B23: AG28 | C23: =VLOOKUP(B23,ENS.!$B$5:$H$167,2,FALSE) -> Gravedad especifica y absorción de agregado grueso | J23: =VLOOKUP(B23,ENS.!$B$5:$H$167,3,FALSE) -> ASTM C127-24 | K23: =VLOOKUP(B23,ENS.!$B$5:$H$167,4,FALSE) -> SI | L23: =VLOOKUP(B23,ENS.!$B$5:$H$167,7,FALSE) -> 120 | M23: 1 | N23: =+L23*M23 -> 120
B24: SU31 | C24: =VLOOKUP(B24,ENS.!$B$5:$H$167,2,FALSE) -> Corrección de Peso Unitario para Partícula de gran tamaño. | J24: =VLOOKUP(B24,ENS.!$B$5:$H$167,3,FALSE) -> ASTM D4718-87 | K24: =VLOOKUP(B24,ENS.!$B$5:$H$167,4,FALSE) -> NO | L24: =VLOOKUP(B24,ENS.!$B$5:$H$167,7,FALSE) -> 20 | M24: 1 | N24: =+L24*M24 -> 20
C25: DISEÑO DE MEZCLA DE CONCRETO - SIN ADITIVO
B26: DIS01 | C26: Diseño de mezcla incl. Verificación F'c= 100, 210, 280 kg/cm2 | J26: =VLOOKUP(B26,ENS.!$B$5:$H$167,3,FALSE) -> ACI 211 | K26: =VLOOKUP(B26,ENS.!$B$5:$H$167,4,FALSE) -> NO | L26: =VLOOKUP(B26,ENS.!$B$5:$H$167,7,FALSE) -> 250 | M26: 3 | N26: =+L26*M26 -> 750
C27: ENSAYOS EN AGREGADO GRUESO
B28: AG19 | C28: =VLOOKUP(B28,ENS.!$B$5:$H$167,2,FALSE) -> Análisis granulométrico por tamizado en agregado | J28: =VLOOKUP(B28,ENS.!$B$5:$H$167,3,FALSE) -> ASTM C136/C136M-19 | K28: =VLOOKUP(B28,ENS.!$B$5:$H$167,4,FALSE) -> SI | L28: =VLOOKUP(B28,ENS.!$B$5:$H$167,7,FALSE) -> 100 | M28: 1 | N28: =+L28*M28 -> 100
B29: AG22 | C29: =VLOOKUP(B29,ENS.!$B$5:$H$167,2,FALSE) -> Peso Unitario y Vacío de agregados | J29: =VLOOKUP(B29,ENS.!$B$5:$H$167,3,FALSE) -> ASTM C29/C29M-23 | K29: =VLOOKUP(B29,ENS.!$B$5:$H$167,4,FALSE) -> SI | L29: =VLOOKUP(B29,ENS.!$B$5:$H$167,7,FALSE) -> 120 | M29: 1 | N29: =+L29*M29 -> 120
B30: AG20 | C30: =VLOOKUP(B30,ENS.!$B$5:$H$167,2,FALSE) -> Contenido de humedad en agregado | J30: =VLOOKUP(B30,ENS.!$B$5:$H$167,3,FALSE) -> ASTM C566-19 | K30: =VLOOKUP(B30,ENS.!$B$5:$H$167,4,FALSE) -> SI | L30: =VLOOKUP(B30,ENS.!$B$5:$H$167,7,FALSE) -> 30 | M30: 1 | N30: =+L30*M30 -> 30
B31: AG28 | C31: =VLOOKUP(B31,ENS.!$B$5:$H$167,2,FALSE) -> Gravedad especifica y absorción de agregado grueso | J31: =VLOOKUP(B31,ENS.!$B$5:$H$167,3,FALSE) -> ASTM C127-24 | K31: =VLOOKUP(B31,ENS.!$B$5:$H$167,4,FALSE) -> SI | L31: =VLOOKUP(B31,ENS.!$B$5:$H$167,7,FALSE) -> 120 | M31: 1 | N31: =+L31*M31 -> 120
B32: AG23 | C32: =VLOOKUP(B32,ENS.!$B$5:$H$167,2,FALSE) -> Pasante de la malla No.200 | J32: =VLOOKUP(B32,ENS.!$B$5:$H$167,3,FALSE) -> ASTM C117-23 | K32: =VLOOKUP(B32,ENS.!$B$5:$H$167,4,FALSE) -> SI | L32: =VLOOKUP(B32,ENS.!$B$5:$H$167,7,FALSE) -> 120 | M32: 1 | N32: =+L32*M32 -> 120
B33: AG25 | C33: =VLOOKUP(B33,ENS.!$B$5:$H$167,2,FALSE) -> Terrones de arcilla y partículas friables, Fino o grueso. | J33: =VLOOKUP(B33,ENS.!$B$5:$H$167,3,FALSE) -> NTP 400.015 | K33: =VLOOKUP(B33,ENS.!$B$5:$H$167,4,FALSE) -> NO | L33: =VLOOKUP(B33,ENS.!$B$5:$H$167,7,FALSE) -> 120 | M33: 1 | N33: =+L33*M33 -> 120
B34: AG24 | C34: =VLOOKUP(B34,ENS.!$B$5:$H$167,2,FALSE) -> Partículas Liviana en los agregados (carbon y lignito), Fino o grueso. | J34: =VLOOKUP(B34,ENS.!$B$5:$H$167,3,FALSE) -> NTP 400.023 | K34: =VLOOKUP(B34,ENS.!$B$5:$H$167,4,FALSE) -> NO | L34: =VLOOKUP(B34,ENS.!$B$5:$H$167,7,FALSE) -> 220 | M34: 1 | N34: =+L34*M34 -> 220
B35: AG35 | C35: =VLOOKUP(B35,ENS.!$B$5:$H$167,2,FALSE) -> Porcentaje de Caras fracturadas en agregado grueso | J35: =VLOOKUP(B35,ENS.!$B$5:$H$167,3,FALSE) -> ASTM D5821-13 (Reapproved 2017) | K35: =VLOOKUP(B35,ENS.!$B$5:$H$167,4,FALSE) -> SI | L35: =VLOOKUP(B35,ENS.!$B$5:$H$167,7,FALSE) -> 120 | M35: 1 | N35: =+L35*M35 -> 120
B36: AG34 | C36: =VLOOKUP(B36,ENS.!$B$5:$H$167,2,FALSE) -> Partículas planas y alargadas en agregado grueso | J36: =VLOOKUP(B36,ENS.!$B$5:$H$167,3,FALSE) -> ASTM D4791-19 (Reapproved 2023) | K36: =VLOOKUP(B36,ENS.!$B$5:$H$167,4,FALSE) -> SI | L36: =VLOOKUP(B36,ENS.!$B$5:$H$167,7,FALSE) -> 120 | M36: 1 | N36: =+L36*M36 -> 120
B37: AG08A | C37: =VLOOKUP(B37,ENS.!$B$5:$H$167,2,FALSE) -> Inalterabilidad Agregado Grueso con Sulfato de Magnesio. | J37: =VLOOKUP(B37,ENS.!$B$5:$H$167,3,FALSE) -> NTP 400.016 | K37: =VLOOKUP(B37,ENS.!$B$5:$H$167,4,FALSE) -> NO | L37: =VLOOKUP(B37,ENS.!$B$5:$H$167,7,FALSE) -> 350 | M37: 1 | N37: =+L37*M37 -> 350
C38: ENSAYOS EN AGREGADO FINO
B39: AG19 | C39: =VLOOKUP(B39,ENS.!$B$5:$H$167,2,FALSE) -> Análisis granulométrico por tamizado en agregado | J39: =VLOOKUP(B39,ENS.!$B$5:$H$167,3,FALSE) -> ASTM C136/C136M-19 | K39: =VLOOKUP(B39,ENS.!$B$5:$H$167,4,FALSE) -> SI | L39: =VLOOKUP(B39,ENS.!$B$5:$H$167,7,FALSE) -> 100 | M39: 1 | N39: =+L39*M39 -> 100
B40: AG22 | C40: =VLOOKUP(B40,ENS.!$B$5:$H$167,2,FALSE) -> Peso Unitario y Vacío de agregados | J40: =VLOOKUP(B40,ENS.!$B$5:$H$167,3,FALSE) -> ASTM C29/C29M-23 | K40: =VLOOKUP(B40,ENS.!$B$5:$H$167,4,FALSE) -> SI | L40: =VLOOKUP(B40,ENS.!$B$5:$H$167,7,FALSE) -> 120 | M40: 1 | N40: =+L40*M40 -> 120 | P40: AG08A
B41: AG20 | C41: =VLOOKUP(B41,ENS.!$B$5:$H$167,2,FALSE) -> Contenido de humedad en agregado | J41: =VLOOKUP(B41,ENS.!$B$5:$H$167,3,FALSE) -> ASTM C566-19 | K41: =VLOOKUP(B41,ENS.!$B$5:$H$167,4,FALSE) -> SI | L41: =VLOOKUP(B41,ENS.!$B$5:$H$167,7,FALSE) -> 30 | M41: 1 | N41: =+L41*M41 -> 30
B42: AG18 | C42: =VLOOKUP(B42,ENS.!$B$5:$H$167,2,FALSE) -> Gravedad específica y absorción del agregado fino | J42: =VLOOKUP(B42,ENS.!$B$5:$H$167,3,FALSE) -> ASTM C128-22 | K42: =VLOOKUP(B42,ENS.!$B$5:$H$167,4,FALSE) -> SI | L42: =VLOOKUP(B42,ENS.!$B$5:$H$167,7,FALSE) -> 150 | M42: 1 | N42: =+L42*M42 -> 150
B43: AG23 | C43: =VLOOKUP(B43,ENS.!$B$5:$H$167,2,FALSE) -> Pasante de la malla No.200 | J43: =VLOOKUP(B43,ENS.!$B$5:$H$167,3,FALSE) -> ASTM C117-23 | K43: =VLOOKUP(B43,ENS.!$B$5:$H$167,4,FALSE) -> SI | L43: =VLOOKUP(B43,ENS.!$B$5:$H$167,7,FALSE) -> 120 | M43: 1 | N43: =+L43*M43 -> 120
B44: AG25 | C44: =VLOOKUP(B44,ENS.!$B$5:$H$167,2,FALSE) -> Terrones de arcilla y partículas friables, Fino o grueso. | J44: =VLOOKUP(B44,ENS.!$B$5:$H$167,3,FALSE) -> NTP 400.015 | K44: =VLOOKUP(B44,ENS.!$B$5:$H$167,4,FALSE) -> NO | L44: =VLOOKUP(B44,ENS.!$B$5:$H$167,7,FALSE) -> 120 | M44: 1 | N44: =+L44*M44 -> 120 | P44: AG13
B45: AG24 | C45: =VLOOKUP(B45,ENS.!$B$5:$H$167,2,FALSE) -> Partículas Liviana en los agregados (carbon y lignito), Fino o grueso. | J45: =VLOOKUP(B45,ENS.!$B$5:$H$167,3,FALSE) -> NTP 400.023 | K45: =VLOOKUP(B45,ENS.!$B$5:$H$167,4,FALSE) -> NO | L45: =VLOOKUP(B45,ENS.!$B$5:$H$167,7,FALSE) -> 220 | M45: 1 | N45: =+L45*M45 -> 220
B46: AG13 | C46: =VLOOKUP(B46,ENS.!$B$5:$H$167,2,FALSE) -> Impurezas Orgánicas en los áridos finos. | J46: =VLOOKUP(B46,ENS.!$B$5:$H$167,3,FALSE) -> ASTM C40-99 | K46: =VLOOKUP(B46,ENS.!$B$5:$H$167,4,FALSE) -> NO | L46: =VLOOKUP(B46,ENS.!$B$5:$H$167,7,FALSE) -> 150 | M46: 1 | N46: =+L46*M46 -> 150
B47: AG08B | C47: =VLOOKUP(B47,ENS.!$B$5:$H$167,2,FALSE) -> Inalterabilidad Agregado Fino con Sulfato de Magnesio. | J47: =VLOOKUP(B47,ENS.!$B$5:$H$167,3,FALSE) -> NTP 400.016 | K47: =VLOOKUP(B47,ENS.!$B$5:$H$167,4,FALSE) -> NO | L47: =VLOOKUP(B47,ENS.!$B$5:$H$167,7,FALSE) -> 350 | M47: 1 | N47: =+L47*M47 -> 350
B48: SU21 | C48: =VLOOKUP(B48,ENS.!$B$5:$H$167,2,FALSE) -> Equivalente de arena | J48: =VLOOKUP(B48,ENS.!$B$5:$H$167,3,FALSE) -> ASTM D2419-22 | K48: =VLOOKUP(B48,ENS.!$B$5:$H$167,4,FALSE) -> SI | L48: =VLOOKUP(B48,ENS.!$B$5:$H$167,7,FALSE) -> 150 | M48: 1 | N48: =+L48*M48 -> 150
C49: ENSAYOS EN AGUA | P49: AG35
B50: CO17 | C50: =VLOOKUP(B50,ENS.!$B$5:$H$167,2,FALSE) -> Determinar el contenido del ion cloruro en las aguas usadas en la elaboración de concretos y morteros de cemento Pórtland. | J50: =VLOOKUP(B50,ENS.!$B$5:$H$167,3,FALSE) -> NTP 339.076:2017 | K50: =VLOOKUP(B50,ENS.!$B$5:$H$167,4,FALSE) -> NO | L50: =VLOOKUP(B50,ENS.!$B$5:$H$167,7,FALSE) -> 120 | M50: 1 | N50: =+L50*M50 -> 120
B51: CO16 | C51: =VLOOKUP(B51,ENS.!$B$5:$H$167,2,FALSE) -> Determinar el contenido de sulfatos en las aguas usadas en la elaboración de morteros y concretos de cemento Pórtland. | J51: =VLOOKUP(B51,ENS.!$B$5:$H$167,3,FALSE) -> NTP 339.227:2016 | K51: =VLOOKUP(B51,ENS.!$B$5:$H$167,4,FALSE) -> NO | L51: =VLOOKUP(B51,ENS.!$B$5:$H$167,7,FALSE) -> 120 | M51: 1 | N51: =+L51*M51 -> 120
B52: CO15 | C52: =VLOOKUP(B52,ENS.!$B$5:$H$167,2,FALSE) -> Determinar el pH de las aguas usadas para elaborar morteros y concretos. | J52: =VLOOKUP(B52,ENS.!$B$5:$H$167,3,FALSE) -> NTP 334.190:2016 | K52: =VLOOKUP(B52,ENS.!$B$5:$H$167,4,FALSE) -> NO | L52: =VLOOKUP(B52,ENS.!$B$5:$H$167,7,FALSE) -> 100 | M52: 1 | N52: =+L52*M52 -> 100
L53: Costo parcial | N53: =SUM(N17:N52) -> 4650
B54: COM-F-01 Página 1 de 2 Versión: 04 (10-11-2025) | L54: IGV 18% | N54: =+N53*0.18 -> 837
L55: Costo Total (S/) | N55: =+N53+N54 -> 5487
B59: VALIDEZ DE LA OFERTA: 30 días calendario. Si la cotización llegó al límite de su validez, solicite una actualización.
B60: CONDICIONES ESPECÍFICAS PARA LOS ENSAYOS DE LABORATORIO: - El cliente deberá enviar al laboratorio, para los ensayos del material de relleno, la cantidad mínima de 80 kg por cada tipo de muestra. - El cliente deberá enviar al laboratorio, para el diseño de mezcla de concreto, la cantidad mínima de 200 kg de agregado grueso, 200 kg de agregado fino y 02 bolsas de cemento. - El cliente deberá enviar al laboratorio, para los ensayos en agua, la cantidad mínima de 03 litros por cada tipo de muestra. - El cliente deberá entregar las muestras debidamente identificadas. - El cliente deberá especificar la Norma a ser utilizada para la ejecución del ensayo, caso contrario se considera Norma ASTM, NTP, ACI vigente de acuerdo con el alcance del laboratorio. - El cliente deberá entregar las muestras en las instalaciones del LEM, ubicado en la Av. Marañón N° 763, Los Olivos, Lima.
B61: PLAZO ESTIMADO DE EJECUCIÓN DE SERVICIO: - El plazo de entrega de los resultados se estima en 10 días hábiles, este tiempo será evaluado de acuerdo a la cantidad de muestra recepcionada y está sujeto a la programacion enviada por el Laboratorio de Ensayos de Materiales. - El laboratorio enviará un correo de confirmación de recepción y fecha de entrega del informe.
B62: CONTRAMUESTRA Al finalizar los ensayos, la muestra sobrante/contramuestra permanecerán en custodia por un tiempo de 10 dias calendario después de emitido el informe de ensayo. Siempre que se trate de una muestra dirimente, las contramuestras serán devueltas a los clientes, previa coordinación y autorización, caso contrario, serán eliminadas si se trata de residuos del ensayo o contramuestras de ensayo.
B63: CONFIDENCIALIDAD: GEOFAL S.A.C mantiene acuerdos de confidencialidad entre el cliente y el laboratorio, la divulgación de la información sin la autorización de las partes, no es permitida. El laboratorio mantiene reserva de la información brindada por el cliente, salvo solicitud de la información por ley, o por entidades gubernamentales inmersos dentro del presente servicio de ensayo.
B64: QUEJAS Y SUGERENCIAS: El plazo máximo para la recepción de quejas relacionadas con un informe técnico es de diez (10) días calendarios, contados a partir de la fecha de emisión del documento correspondiente. Transcurrido dicho plazo, no se aceptarán quejas bajo ninguna circunstancia. En caso de tener alguna queja o sugerencia, lo invitamos a conocer nuestro Proceso de Atención de Quejas, el cual dará inicio 24 horas después de la recepción formal de la queja.
B65: ENTREGA DE INFORME DE ENSAYO: - De acuerdo a los lineamientos de INACAL - DM, los informes de ensayo son emitidos de forma digital con firma electrónica y QR. - La entrega de los informes de ensayo será mediante la plataforma de Intranet de la pagina web www.geofal.com.pe, y se enviará un correo de confirmación al cliente con el usuario y clave para el acceso. Asi mismo el cliente puede ingresar a la gruía deusuario que es visible en la página web. - Geofal no declara conformidad de sus informes de ensayo. - En caso se requiera la modificación del informe de ensayo a consecuencia de los datos proporcionados por el cliente, esta se realizará mediante la emisión de un nuevo informe que tendrá un costo adicional de acuerdo a evaluación.
B66: HORARIO DE ATENCIÓN El horario para recepción de muestra y entrega de informes es de Lunes a Viernes de 8:30am a 1:00pm y 2:00pm a 5:30pm, y Sábado de 8:30am a 12:30pm
B69: CONDICIÓN: El pago del servicio deberá ser realizado por Adelantado. | P69: CONDICIONES DE PAGO
B70: RAZON SOCIAL: Geofal S.A.C. RUC: 20549356762 | P70: CONDICIÓN: El pago del servicio se realizara de acuerdo a la valorización mensual
B71: Sírvase realizar el depósito correspondiente de los servicios a nuestra cuenta bancaria: | P71: CONDICIÓN: El pago del servicio deberá ser realizado por Adelantado.
B72: Cuenta de detraccion Banco de La Nación: | P72: CONDICIÓN: El pago del servicio Adelanto el 50% y saldo previo a la entrega del Informe.
B73: - Cuenta de detraccion Banco de La Nación: Nº 00-074-045472 | P73: CONDICIÓN: El pago del servicio Crédito a 7 días, previa orden de servicio.
B74: Cuenta corriente Interbank: | P74: CONDICIÓN: El pago del servicio Crédito a 30 días, previa orden de servicio.
B75: - Cuenta Corriente en Soles de Interbank: Nº 200-3005201096 | P75: CONDICIÓN: El pago del servicio Crédito a 15 días, previa orden de servicio.
B76: - Código Interbancario (CCI) de Interbank: Nº 003-200- 003005201096-31
B77: Cuenta corriente BCP:
B78: - Cuenta Corriente en Soles del Banco de Crédito del Perú (BCP): Nº 192 2024 3030 04
B79: - Código Interbancario (CCI) del Banco de Crédito del Perú (BCP): Nº 002-192-002 02430 3004-34
B80: Cuenta corriente BBVA:
B81: - Cuenta Corriente en Soles BBVA: Nº 0011-0174-0100082311-00
B82: - Código Interbancario (CCI) BBVA: Nº 011-174-000100082311-00
B86: La aceptación de la cotización por parte del cliente podrá manifestarse a través de cualquiera de las siguientes acciones: el pago correspondiente al servicio, el envío de la orden de servicio, o el envío de un correo electrónico confirmando la aceptación del servicio según la presente cotización, al correo asesorcomercial@geofal.com.pe y/o mediante mensaje de WhatsApp al número del asesor comercial, en señal de conformidad.
B88: Atentamente,
B90: Geofal SAC
B91: Av. Marañón N° 763, Los Olivos, Lima, Perù
B92: Teléfono laboratorio: (01) 7543070 / Teléfono Oficina: (01) 9051911
B93: Web: www.geofal.com.pe
B95: COM-F-01 Página 2 de 2 Versión: 04 (10-11-2025) | M95: Fin del documento

Sheet SU-AG1
G3: 19 | P3: ID CLIENTE | Q3: 1270
B5: CLIENTE: | D5: =VLOOKUP($Q$3,BD_Clientes,2,FALSE) -> CONSORCIO HIDRAULICO TUTI | J5: PROYECTO1: | L5: =VLOOKUP($Q$3,BD_Clientes,9,FALSE) -> Reservorio Tuti | P5: 222
B6: R.U.C.1: | D6: =VLOOKUP($Q$3,BD_Clientes,3,FALSE) -> 20613329251 | P6: 222
B7: CONTACTO: | D7: =VLOOKUP($Q$3,BD_Clientes,5,FALSE) -> Ing. Jessika Contreras | J7: UBICACIÓN1: | L7: =VLOOKUP($Q$3,BD_Clientes,10,FALSE) -> Arequipa | P7: 222
B8: TELÉFONO DE CONTACTO: | E8: =VLOOKUP($Q$3,BD_Clientes,7,FALSE) -> 908888486 | J8: PERSONAL COMERCIAL: | L8: Silvia Peralta
B9: CORREO: | D9: =VLOOKUP($Q$3,BD_Clientes,8,FALSE) -> hidraulicotuti@gmail.com | J9: TELÉFONO DE COMERCIAL: | L9: 982429895
B10: FECHA SOLICITUD: | E10: 45664 | J10: FECHA DE EMISIÓN: | L10: 46029
B11: REFERENCIA: Según lo solicitado vía correo electrónico / Whatsapp / Teléfono / Personalmente.
B12: 1: Información no considerada para las personas naturales.
B13: Por medio de la presente, tenemos el agrado de remitirle nuestra cotización en base a su solicitud, por los servicios de los siguientes ensayos de laboratorio.
B16: CÓDIGO | C16: DESCRIPCIÓN | J16: NORMA | K16: ACREDITADO | L16: COSTO UNITARIO | M16: CANTIDAD | N16: COSTO PARCIAL
B17: RO04 | C17: =VLOOKUP(B17,ENS.!$B$5:$H$167,2,FALSE) -> Método de prueba para la resistencia a la compresión (uniaxial) - Método C | J17: =VLOOKUP(B17,ENS.!$B$5:$H$167,3,FALSE) -> ASTM D 7012-14e1 | K17: =VLOOKUP(B17,ENS.!$B$5:$H$167,4,FALSE) -> NO | L17: =VLOOKUP(B17,ENS.!$B$5:$H$167,7,FALSE) -> 400 | M17: 4 | N17: =+L17*M17 -> 1600
B18: RO02 | C18: =VLOOKUP(B18,ENS.!$B$5:$H$167,2,FALSE) -> Gravedad especifica y absorción de roca. | J18: =VLOOKUP(B18,ENS.!$B$5:$H$167,3,FALSE) -> ASTM D 6473 | K18: =VLOOKUP(B18,ENS.!$B$5:$H$167,4,FALSE) -> NO | L18: =VLOOKUP(B18,ENS.!$B$5:$H$167,7,FALSE) -> 250 | M18: 4 | N18: =+L18*M18 -> 1000
B19: RO03 | C19: =VLOOKUP(B19,ENS.!$B$5:$H$167,2,FALSE) -> Densidad y peso unitario de muestra roca. | J19: =VLOOKUP(B19,ENS.!$B$5:$H$167,3,FALSE) -> ASTM D 7263 | K19: =VLOOKUP(B19,ENS.!$B$5:$H$167,4,FALSE) -> NO | L19: =VLOOKUP(B19,ENS.!$B$5:$H$167,7,FALSE) -> 250 | M19: 4 | N19: =+L19*M19 -> 1000
L20: Costo parcial | N20: =SUM(N17:N19) -> 3600
L21: IGV 18% | N21: =+N20*0.18 -> 648
L22: Costo Total (S/) | N22: =+N20+N21 -> 4248
B24: VALIDEZ DE LA OFERTA: 30 días calendario. Si la cotización llegó al límite de su validez, solicite una actualización.
B25: CONDICIONES ESPECÍFICAS PARA LOS ENSAYOS DE LABORATORIO: - Para la realización de los ensayos del material, se requiere un peso mínimo de 10 kg de roca. - El cliente deberá de entregar las muestras debidamente identificadas. - El cliente deberá especificar la Norma a ser utilizada para la ejecución del ensayo, caso contrario se considera Norma ASTM vigente de acuerdo con el alcance del laboratorio. - El cliente deberá entregar las muestras en las instalaciones del LEM, ubicado en la Av. Marañón N° 763, Los Olivos, Lima.
B26: PLAZO ESTIMADO DE EJECUCIÓN DE SERVICIO: - El plazo de entrega de los resultados se estima en 05 días hábiles, este tiempo será evaluado de acuerdo a la cantidad de muestra recepcionada y está sujeto a la programacion enviada por el Laboratorio de Ensayos de Materiales. - El laboratorio enviará un correo de confirmación de recepción y fecha de entrega del informe.
B27: COM-F-01 Página 1 de 2 Versión: 04 (10-11-2025)
B28: CONTRAMUESTRA Al finalizar los ensayos, la muestra sobrante/contramuestra permanecerán en custodia por un tiempo de 10 dias calendario después de emitido el informe de ensayo. Siempre que se trate de una muestra dirimente, las contramuestras serán devueltas a los clientes, previa coordinación y autorización, caso contrario, serán eliminadas si se trata de residuos del ensayo o contramuestras de ensayo.
B29: CONFIDENCIALIDAD: GEOFAL S.A.C mantiene acuerdos de confidencialidad entre el cliente y el laboratorio, la divulgación de la información sin la autorización de las partes, no es permitida. El laboratorio mantiene reserva de la información brindada por el cliente, salvo solicitud de la información por ley, o por entidades gubernamentales inmersos dentro del presente servicio de ensayo.
B30: QUEJAS Y SUGERENCIAS: El plazo máximo para la recepción de quejas relacionadas con un informe técnico es de diez (10) días calendarios, contados a partir de la fecha de emisión del documento correspondiente. Transcurrido dicho plazo, no se aceptarán quejas bajo ninguna circunstancia. En caso de tener alguna queja o sugerencia, lo invitamos a conocer nuestro Proceso de Atención de Quejas, el cual dará inicio 24 horas después de la recepción formal de la queja.
B31: ENTREGA DE INFORME DE ENSAYO: - De acuerdo a los lineamientos de INACAL - DM, los informes de ensayo son emitidos de forma digital con firma electrónica y QR. - La entrega de los informes de ensayo será mediante la plataforma de Intranet de la pagina web www.geofal.com.pe, y se enviará un correo de confirmación al cliente con el usuario y clave para el acceso. Asi mismo el cliente puede ingresar a la gruía deusuario que es visible en la página web. - Geofal no declara conformidad de sus informes de ensayo. - En caso se requiera la modificación del informe de ensayo a consecuencia de los datos proporcionados por el cliente, esta se realizará mediante la emisión de un nuevo informe que tendrá un costo adicional de acuerdo a evaluación.
B32: HORARIO DE ATENCIÓN El horario para recepción de muestra y entrega de informes es de Lunes a Viernes de 8:30am a 1:00pm y 2:00pm a 5:30pm, y Sábado de 8:30am a 12:30pm
B35: CONDICIÓN: El pago del servicio deberá ser realizado por Adelantado. | P35: CONDICIONES DE PAGO
B36: RAZON SOCIAL: Geofal S.A.C. RUC: 20549356762 | P36: CONDICIÓN: El pago del servicio se realizara de acuerdo a la valorización mensual
B37: Sírvase realizar el depósito correspondiente de los servicios a nuestra cuenta bancaria: | P37: CONDICIÓN: El pago del servicio deberá ser realizado por Adelantado.
B38: Cuenta de detraccion Banco de La Nación: | P38: CONDICIÓN: El pago del servicio Adelanto el 50% y saldo previo a la entrega del Informe.
B39: - Cuenta de detraccion Banco de La Nación: Nº 00-074-045472 | P39: CONDICIÓN: El pago del servicio Crédito a 7 días, previa orden de servicio.
B40: Cuenta corriente Interbank: | P40: CONDICIÓN: El pago del servicio Crédito a 30 días, previa orden de servicio.
B41: - Cuenta Corriente en Soles de Interbank: Nº 200-3005201096 | P41: CONDICIÓN: El pago del servicio Crédito a 15 días, previa orden de servicio.
B42: - Código Interbancario (CCI) de Interbank: Nº 003-200- 003005201096-31
B43: Cuenta corriente BCP:
B44: - Cuenta Corriente en Soles del Banco de Crédito del Perú (BCP): Nº 192 2024 3030 04
B45: - Código Interbancario (CCI) del Banco de Crédito del Perú (BCP): Nº 002-192-002 02430 3004-34
B46: Cuenta corriente BBVA:
B47: - Cuenta Corriente en Soles BBVA: Nº 0011-0174-0100082311-00
B48: - Código Interbancario (CCI) BBVA: Nº 011-174-000100082311-00
B52: La aceptación de la cotización por parte del cliente podrá manifestarse a través de cualquiera de las siguientes acciones: el pago correspondiente al servicio, el envío de la orden de servicio, o el envío de un correo electrónico confirmando la aceptación del servicio según la presente cotización, al correo asesorcomercial@geofal.com.pe y/o mediante mensaje de WhatsApp al número del asesor comercial, en señal de conformidad.
B54: Atentamente,
B56: Geofal SAC
B57: Av. Marañón N° 763, Los Olivos, Lima, Perù
B58: Teléfono laboratorio: (01) 7543070 / Teléfono Oficina: (01) 9051911
B59: Web: www.geofal.com.pe
B61: COM-F-01 Página 2 de 2 Versión: 04 (10-11-2025) | M61: Fin del documento

Sheet SU-AG2
G3: 11 | P3: ID CLIENTE | Q3: 1267
B5: CLIENTE: | D5: =VLOOKUP($Q$3,BD_Clientes,2,FALSE) -> ALEXANDER COTRINA VÁSQUEZ | J5: PROYECTO1: | L5: =VLOOKUP($Q$3,BD_Clientes,9,FALSE) -> Vía de Evitamiento Cusco | P5: 222
B6: R.U.C.1: | D6: =VLOOKUP($Q$3,BD_Clientes,3,FALSE) -> - | P6: 222
B7: CONTACTO: | D7: =VLOOKUP($Q$3,BD_Clientes,5,FALSE) -> ALEXANDER COTRINA VÁSQUEZ | J7: UBICACIÓN1: | L7: =VLOOKUP($Q$3,BD_Clientes,10,FALSE) -> Cusco | P7: 222
B8: TELÉFONO DE CONTACTO: | E8: =VLOOKUP($Q$3,BD_Clientes,7,FALSE) -> 997520578 | J8: PERSONAL COMERCIAL: | L8: Silvia Peralta
B9: CORREO: | D9: =VLOOKUP($Q$3,BD_Clientes,8,FALSE) -> cotrinlex@gmail.com | J9: TELÉFONO DE COMERCIAL: | L9: 982429895
B10: FECHA SOLICITUD: | E10: 46027 | J10: FECHA DE EMISIÓN: | L10: 46027
B11: REFERENCIA: Segùn lo solicitado vía correo electrónico / Whatsapp / Teléfono / Personalmente.
B12: 1: Información no considerada para las personas naturales.
B13: Por medio de la presente, tenemos el agrado de remitirle nuestra cotización en base a su solicitud, por los servicios de los siguientes ensayos de laboratorio.
B16: CÓDIGO | C16: DESCRIPCIÓN | J16: NORMA | K16: ACREDITADO | L16: COSTO UNITARIO | M16: CANTIDAD | N16: COSTO PARCIAL
B17: SU22 | C17: =VLOOKUP(B17,ENS.!$B$5:$H$167,2,FALSE) -> Clasificación suelo SUCS - AASHTO | J17: =VLOOKUP(B17,ENS.!$B$5:$H$167,3,FALSE) -> ASTM D2487-17 (Reapproved 2025) / ASTM D3282-24 | K17: =VLOOKUP(B17,ENS.!$B$5:$H$167,4,FALSE) -> SI | L17: =VLOOKUP(B17,ENS.!$B$5:$H$167,7,FALSE) -> 20 | M17: 240 | N17: =+L17*M17 -> 4800
B18: SU20 | C18: =VLOOKUP(B18,ENS.!$B$5:$H$167,2,FALSE) -> Contenido de humedad en suelos | J18: =VLOOKUP(B18,ENS.!$B$5:$H$167,3,FALSE) -> ASTM D2216-19 | K18: =VLOOKUP(B18,ENS.!$B$5:$H$167,4,FALSE) -> SI | L18: =VLOOKUP(B18,ENS.!$B$5:$H$167,7,FALSE) -> 30 | M18: 240 | N18: =+L18*M18 -> 7200
B19: SU23 | C19: =VLOOKUP(B19,ENS.!$B$5:$H$167,2,FALSE) -> Límite líquido y Límite Plástico del Suelo | J19: =VLOOKUP(B19,ENS.!$B$5:$H$167,3,FALSE) -> ASTM D4318-17ε1 | K19: =VLOOKUP(B19,ENS.!$B$5:$H$167,4,FALSE) -> SI | L19: =VLOOKUP(B19,ENS.!$B$5:$H$167,7,FALSE) -> 90 | M19: 240 | N19: =+L19*M19 -> 21600
B20: SU24 | C20: =VLOOKUP(B20,ENS.!$B$5:$H$167,2,FALSE) -> Análisis granulométrico por tamizado en Suelo | J20: =VLOOKUP(B20,ENS.!$B$5:$H$167,3,FALSE) -> ASTM D6913/D6913M-17 | K20: =VLOOKUP(B20,ENS.!$B$5:$H$167,4,FALSE) -> SI | L20: =VLOOKUP(B20,ENS.!$B$5:$H$167,7,FALSE) -> 100 | M20: 240 | N20: =+L20*M20 -> 24000
B21: SU26 | C21: =VLOOKUP(B21,ENS.!$B$5:$H$167,2,FALSE) -> Contenido de materia orgánica. | J21: =VLOOKUP(B21,ENS.!$B$5:$H$167,3,FALSE) -> AASHTO T267 | K21: =VLOOKUP(B21,ENS.!$B$5:$H$167,4,FALSE) -> NO | L21: =VLOOKUP(B21,ENS.!$B$5:$H$167,7,FALSE) -> 120 | M21: 80 | N21: =+L21*M21 -> 9600
B22: SU13 | C22: =VLOOKUP(B22,ENS.!$B$5:$H$167,2,FALSE) -> Sales solubles en Suelos y Agua. | J22: =VLOOKUP(B22,ENS.!$B$5:$H$167,3,FALSE) -> NTP 339.152 | K22: =VLOOKUP(B22,ENS.!$B$5:$H$167,4,FALSE) -> NO | L22: =VLOOKUP(B22,ENS.!$B$5:$H$167,7,FALSE) -> 80 | M22: 50 | N22: =+L22*M22 -> 4000
B23: SU14 | C23: =VLOOKUP(B23,ENS.!$B$5:$H$167,2,FALSE) -> Cloruros Solubles en Suelos y Agua. | J23: =VLOOKUP(B23,ENS.!$B$5:$H$167,3,FALSE) -> NTP 339.177 | K23: =VLOOKUP(B23,ENS.!$B$5:$H$167,4,FALSE) -> NO | L23: =VLOOKUP(B23,ENS.!$B$5:$H$167,7,FALSE) -> 80 | M23: 50 | N23: =+L23*M23 -> 4000
B24: SU15 | C24: =VLOOKUP(B24,ENS.!$B$5:$H$167,2,FALSE) -> Sulfatos Solubles en Suelos y Agua. | J24: =VLOOKUP(B24,ENS.!$B$5:$H$167,3,FALSE) -> NTP 339.178 | K24: =VLOOKUP(B24,ENS.!$B$5:$H$167,4,FALSE) -> NO | L24: =VLOOKUP(B24,ENS.!$B$5:$H$167,7,FALSE) -> 120 | M24: 50 | N24: =+L24*M24 -> 6000
B25: SU37 | C25: =VLOOKUP(B25,ENS.!$B$5:$H$167,2,FALSE) -> California Bearing Ratio (CBR) | J25: =VLOOKUP(B25,ENS.!$B$5:$H$167,3,FALSE) -> ASTM D1883-21 | K25: =VLOOKUP(B25,ENS.!$B$5:$H$167,4,FALSE) -> SI | L25: =VLOOKUP(B25,ENS.!$B$5:$H$167,7,FALSE) -> 300 | M25: 30 | N25: =+L25*M25 -> 9000
B26: SU19 | C26: =VLOOKUP(B26,ENS.!$B$5:$H$167,2,FALSE) -> Próctor modificado | J26: =VLOOKUP(B26,ENS.!$B$5:$H$167,3,FALSE) -> ASTM D1557-12 (Reapproved 2021) | K26: =VLOOKUP(B26,ENS.!$B$5:$H$167,4,FALSE) -> SI | L26: =VLOOKUP(B26,ENS.!$B$5:$H$167,7,FALSE) -> 150 | M26: 30 | N26: =+L26*M26 -> 4500
B27: SU32 | C27: =VLOOKUP(B27,ENS.!$B$5:$H$167,2,FALSE) -> Gravedad específica de los sólidos del suelo. | J27: =VLOOKUP(B27,ENS.!$B$5:$H$167,3,FALSE) -> ASTM D854-14 | K27: =VLOOKUP(B27,ENS.!$B$5:$H$167,4,FALSE) -> NO | L27: =VLOOKUP(B27,ENS.!$B$5:$H$167,7,FALSE) -> 120 | M27: 30 | N27: =+L27*M27 -> 3600
B28: AG28 | C28: =VLOOKUP(B28,ENS.!$B$5:$H$167,2,FALSE) -> Gravedad especifica y absorción de agregado grueso | J28: =VLOOKUP(B28,ENS.!$B$5:$H$167,3,FALSE) -> ASTM C127-24 | K28: =VLOOKUP(B28,ENS.!$B$5:$H$167,4,FALSE) -> SI | L28: =VLOOKUP(B28,ENS.!$B$5:$H$167,7,FALSE) -> 120 | M28: 30 | N28: =+L28*M28 -> 3600
... B30: SU46 | C30: =VLOOKUP(B30,ENS.!$B$5:$H$167,2,FALSE) -> Compresión triaxial consolidado no drenado CU, diametro 75 mm | J30: =VLOOKUP(B30,ENS.!$B$5:$H$167,3,FALSE) -> ASTM D4767 | K30: =VLOOKUP(B30,ENS.!$B$5:$H$167,4,FALSE) -> NO | L30: =VLOOKUP(B30,ENS.!$B$5:$H$167,7,FALSE) -> 2000 | M30: 18 | N30: =+L30*M30 -> 36000
B31: SU47 | C31: =VLOOKUP(B31,ENS.!$B$5:$H$167,2,FALSE) -> Compresión triaxial consolidado drenado CD, diametro 75 mm | J31: =VLOOKUP(B31,ENS.!$B$5:$H$167,3,FALSE) -> ASTM D7181 | K31: =VLOOKUP(B31,ENS.!$B$5:$H$167,4,FALSE) -> NO | L31: 2500 | M31: 17 | N31: =+L31*M31 -> 42500 | P31: SU20
B32: EE01 | C32: =VLOOKUP(B32,ENS.!$B$5:$H$167,2,FALSE) -> Consolidación unidimensional. | J32: =VLOOKUP(B32,ENS.!$B$5:$H$167,3,FALSE) -> ASTM D2435 | K32: =VLOOKUP(B32,ENS.!$B$5:$H$167,4,FALSE) -> NO | L32: =VLOOKUP(B32,ENS.!$B$5:$H$167,7,FALSE) -> 800 | M32: 18 | N32: =+L32*M32 -> 14400
B33: AG35 | C33: =VLOOKUP(B33,ENS.!$B$5:$H$167,2,FALSE) -> Porcentaje de Caras fracturadas en agregado grueso | J33: =VLOOKUP(B33,ENS.!$B$5:$H$167,3,FALSE) -> ASTM D5821-13 (Reapproved 2017) | K33: =VLOOKUP(B33,ENS.!$B$5:$H$167,4,FALSE) -> SI | L33: =VLOOKUP(B33,ENS.!$B$5:$H$167,7,FALSE) -> 120 | M33: 18 | N33: =+L33*M33 -> 2160
B34: AG25 | C34: =VLOOKUP(B34,ENS.!$B$5:$H$167,2,FALSE) -> Terrones de arcilla y partículas friables, Fino o grueso. | J34: =VLOOKUP(B34,ENS.!$B$5:$H$167,3,FALSE) -> NTP 400.015 | K34: =VLOOKUP(B34,ENS.!$B$5:$H$167,4,FALSE) -> NO | L34: =VLOOKUP(B34,ENS.!$B$5:$H$167,7,FALSE) -> 120 | M34: 36 | N34: =+L34*M34 -> 4320
B35: SU21 | C35: =VLOOKUP(B35,ENS.!$B$5:$H$167,2,FALSE) -> Equivalente de arena | J35: =VLOOKUP(B35,ENS.!$B$5:$H$167,3,FALSE) -> ASTM D2419-22 | K35: =VLOOKUP(B35,ENS.!$B$5:$H$167,4,FALSE) -> SI | L35: =VLOOKUP(B35,ENS.!$B$5:$H$167,7,FALSE) -> 150 | M35: 18 | N35: =+L35*M35 -> 2700
B36: AG36 | C36: =VLOOKUP(B36,ENS.!$B$5:$H$167,2,FALSE) -> Abrasión los Ángeles de agregado grueso de tamaño pequeño. | J36: =VLOOKUP(B36,ENS.!$B$5:$H$167,3,FALSE) -> ASTM C131/C131M-20 | K36: =VLOOKUP(B36,ENS.!$B$5:$H$167,4,FALSE) -> SI | L36: =VLOOKUP(B36,ENS.!$B$5:$H$167,7,FALSE) -> 250 | M36: 18 | N36: =+L36*M36 -> 4500
B37: AG26 | C37: =VLOOKUP(B37,ENS.!$B$5:$H$167,2,FALSE) -> Abrasión los Ángeles de agregado grueso de gran tamaño | J37: =VLOOKUP(B37,ENS.!$B$5:$H$167,3,FALSE) -> ASTM C535-16 (Reapproved 2024) | K37: =VLOOKUP(B37,ENS.!$B$5:$H$167,4,FALSE) -> SI | L37: =VLOOKUP(B37,ENS.!$B$5:$H$167,7,FALSE) -> 350 | M37: 18 | N37: =+L37*M37 -> 6300 | P37: EE01
B38: AG08A | C38: =VLOOKUP(B38,ENS.!$B$5:$H$167,2,FALSE) -> Inalterabilidad Agregado Grueso con Sulfato de Magnesio. | J38: =VLOOKUP(B38,ENS.!$B$5:$H$167,3,FALSE) -> NTP 400.016 | K38: =VLOOKUP(B38,ENS.!$B$5:$H$167,4,FALSE) -> NO | L38: =VLOOKUP(B38,ENS.!$B$5:$H$167,7,FALSE) -> 350 | M38: 18 | N38: =+L38*M38 -> 6300
B39: AG08B | C39: =VLOOKUP(B39,ENS.!$B$5:$H$167,2,FALSE) -> Inalterabilidad Agregado Fino con Sulfato de Magnesio. | J39: =VLOOKUP(B39,ENS.!$B$5:$H$167,3,FALSE) -> NTP 400.016 | K39: =VLOOKUP(B39,ENS.!$B$5:$H$167,4,FALSE) -> NO | L39: =VLOOKUP(B39,ENS.!$B$5:$H$167,7,FALSE) -> 350 | M39: 18 | N39: =+L39*M39 -> 6300
L40: Costo parcial | N40: =SUM(N17:N39) -> 253630
L41: IGV 18% | N41: =+N40*0.18 -> 45653.4
L42: Costo Total (S/) | N42: =+N40+N41 -> 299283.4
B44: VALIDEZ DE LA OFERTA: 30 días calendario. Si la cotización llegó al límite de su validez, solicite una actualización.
B45: COM-F-01 Página 1 de 2 Versión: 04 (10-11-2025)
B46: CONDICIONES ESPECÍFICAS PARA LOS ENSAYOS DE LABORATORIO: - El cliente deberá enviar al laboratorio, para los ensayos del material, la cantidad mínima de 150 kg por cada tipo de muestra. - El cliente deberá de entregar las muestras debidamente identificadas. - El cliente deberá especificar la Norma a ser utilizada para la ejecución del ensayo, caso contrario se considera Norma ASTM, NTP, AASHTO vigente deacuerdo con el alcance del laboratorio. - El cliente deberá entregar las muestras en las instalaciones del LEM, ubicado en la Av. Marañón N° 763, Los Olivos, Lima.
B47: PLAZO ESTIMADO DE EJECUCIÓN DE SERVICIO: - El plazo de entrega de los resultados se estima de acuerdo a su programación de recepción, este tiempo será evaluado de acuerdo a la cantidad de muestra recepcionada y está sujeto a la programacion enviada por el Laboratorio de Ensayos de Materiales. - El laboratorio enviará un correo de confirmación de recepción y fecha de entrega del informe.
B48: CONTRAMUESTRA Al finalizar los ensayos, la muestra sobrante/contramuestra permanecerán en custodia por un tiempo de 10 dias calendario después de emitido el informe de ensayo. Siempre que se trate de una muestra dirimente, las contramuestras serán devueltas a los clientes, previa coordinación y autorización, caso contrario, serán eliminadas si se trata de residuos del ensayo o contramuestras de ensayo.
B49: CONFIDENCIALIDAD: GEOFAL S.A.C mantiene acuerdos de confidencialidad entre el cliente y el laboratorio, la divulgación de la información sin la autorización de las partes, no es permitida. El laboratorio mantiene reserva de la información brindada por el cliente, salvo solicitud de la información por ley, o por entidades gubernamentales inmersos dentro del presente servicio de ensayo.
B50: QUEJAS Y SUGERENCIAS: El plazo máximo para la recepción de quejas relacionadas con un informe técnico es de diez (10) días calendarios, contados a partir de la fecha de emisión del documento correspondiente. Transcurrido dicho plazo, no se aceptarán quejas bajo ninguna circunstancia. En caso de tener alguna queja o sugerencia, lo invitamos a conocer nuestro Proceso de Atención de Quejas, el cual dará inicio 24 horas después de la recepción formal de la queja.
B51: ENTREGA DE INFORME DE ENSAYO: - De acuerdo a los lineamientos de INACAL - DM, los informes de ensayo son emitidos de forma digital con firma electrónica y QR. - La entrega de los informes de ensayo será mediante la plataforma de Intranet de la pagina web www.geofal.com.pe, y se enviará un correo de confirmación al cliente con el usuario y clave para el acceso. Asi mismo el cliente puede ingresar a la gruía deusuario que es visible en la página web. - Geofal no declara conformidad de sus informes de ensayo. - En caso se requiera la modificación del informe de ensayo a consecuencia de los datos proporcionados por el cliente, esta se realizará mediante la emisión de un nuevo informe que tendrá un costo adicional de acuerdo a evaluación.
B52: HORARIO DE ATENCIÓN El horario para recepción de muestra y entrega de informes es de Lunes a Viernes de 8:30am a 1:00pm y 2:00pm a 5:30pm, y Sábado de 8:30am a 12:30pm
B55: CONDICIÓN: El pago del servicio deberá ser realizado por Adelantado. | P55: CONDICIONES DE PAGO
B56: RAZON SOCIAL: Geofal S.A.C. RUC: 20549356762 | P56: CONDICIÓN: El pago del servicio se realizara de acuerdo a la valorización mensual
B57: Sírvase realizar el depósito correspondiente de los servicios a nuestra cuenta bancaria: | P57: CONDICIÓN: El pago del servicio deberá ser realizado por Adelantado.
B58: Cuenta de detraccion Banco de La Nación: | P58: CONDICIÓN: El pago del servicio Adelanto el 50% y saldo previo a la entrega del Informe.
B59: - Cuenta de detraccion Banco de La Nación: Nº 00-074-045472 | P59: CONDICIÓN: El pago del servicio Crédito a 7 días, previa orden de servicio.
B60: Cuenta corriente Interbank: | P60: CONDICIÓN: El pago del servicio Crédito a 30 días, previa orden de servicio.
B61: - Cuenta Corriente en Soles de Interbank: Nº 200-3005201096 | P61: CONDICIÓN: El pago del servicio Crédito a 15 días, previa orden de servicio.
B62: - Código Interbancario (CCI) de Interbank: Nº 003-200- 003005201096-31
B63: Cuenta corriente BCP:
B64: - Cuenta Corriente en Soles del Banco de Crédito del Perú (BCP): Nº 192 2024 3030 04
B65: - Código Interbancario (CCI) del Banco de Crédito del Perú (BCP): Nº 002-192-002 02430 3004-34
B66: Cuenta corriente BBVA:
B67: - Cuenta Corriente en Soles BBVA: Nº 0011-0174-0100082311-00
B68: - Código Interbancario (CCI) BBVA: Nº 011-174-000100082311-00
B72: La aceptación de la cotización por parte del cliente podrá manifestarse a través de cualquiera de las siguientes acciones: el pago correspondiente al servicio, el envío de la orden de servicio, o el envío de un correo electrónico confirmando la aceptación del servicio según la presente cotización, al correo asesorcomercial@geofal.com.pe y/o mediante mensaje de WhatsApp al número del asesor comercial, en señal de conformidad.
B74: Atentamente,
B76: Geofal SAC
B77: Av. Marañón N° 763, Los Olivos, Lima, Perù
B78: Teléfono laboratorio: (01) 7543070 / Teléfono Oficina: (01) 9051911
B79: Web: www.geofal.com.pe
B81: COM-F-01 Página 2 de 2 Versión: 04 (10-11-2025) | M81: Fin del documento

Sheet SU-AG3
G3: 222 | P3: ID CLIENTE | Q3: 1130
B5: CLIENTE: | D5: =VLOOKUP($Q$3,BD_Clientes,2,FALSE) -> CONSORCIO LIMA NORTE | J5: PROYECTO1: | L5: =VLOOKUP($Q$3,BD_Clientes,9,FALSE) -> Mejoramiento y Ampliación del Sistema de Agua Potable y Alcantarillado de Los Sectores 359 y 360 y Nuevas Habilitaciones Esquema Integral de Carabayllo | P5: 222
B6: R.U.C.1: | D6: =VLOOKUP($Q$3,BD_Clientes,3,FALSE) -> 20614164833 | P6: 222
B7: CONTACTO: | D7: =VLOOKUP($Q$3,BD_Clientes,5,FALSE) -> Ing. Erick Aponte / Joao Cano | J7: UBICACIÓN1: | L7: =VLOOKUP($Q$3,BD_Clientes,10,FALSE) -> Carabayllo - Lima | P7: 222
B8: TELÉFONO DE CONTACTO: | E8: =VLOOKUP($Q$3,BD_Clientes,7,FALSE) -> 969934305 | J8: PERSONAL COMERCIAL: | L8: Silvia Peralta
B9: CORREO: | D9: =VLOOKUP($Q$3,BD_Clientes,8,FALSE) -> eaponte@ciolimanorte.com / jcano@ciolimanorte.com / joao.rinc.oftec@gmail.com | J9: TELÉFONO DE COMERCIAL: | L9: 982429895
B10: FECHA SOLICITUD: | E10: 46002 | J10: FECHA DE EMISIÓN: | L10: 46002
B11: REFERENCIA: Segùn lo solicitado vía correo electrónico / Whatsapp / Teléfono / Personalmente.
B12: 1: Información no considerada para las personas naturales.
B13: Por medio de la presente, tenemos el agrado de remitirle nuestra cotización en base a su solicitud, por los servicios de los siguientes ensayos de laboratorio.
B16: CÓDIGO | C16: DESCRIPCIÓN | J16: NORMA | K16: ACREDITADO | L16: COSTO UNITARIO | M16: CANTIDAD | N16: COSTO PARCIAL
C17: ANALISIS DE MATERIAL - AFIRMADO
B18: SU19 | C18: =VLOOKUP(B18,ENS.!$B$5:$H$167,2,FALSE) -> Próctor modificado | J18: =VLOOKUP(B18,ENS.!$B$5:$H$167,3,FALSE) -> ASTM D1557-12 (Reapproved 2021) | K18: =VLOOKUP(B18,ENS.!$B$5:$H$167,4,FALSE) -> SI | L18: =VLOOKUP(B18,ENS.!$B$5:$H$167,7,FALSE) -> 150 | M18: 1 | N18: =+L18*M18 -> 150
B19: SU32 | C19: =VLOOKUP(B19,ENS.!$B$5:$H$167,2,FALSE) -> Gravedad específica de los sólidos del suelo. | J19: =VLOOKUP(B19,ENS.!$B$5:$H$167,3,FALSE) -> ASTM D854-14 | K19: =VLOOKUP(B19,ENS.!$B$5:$H$167,4,FALSE) -> NO | L19: 100 | M19: 1 | N19: =+L19*M19 -> 100
B20: AG28 | C20: =VLOOKUP(B20,ENS.!$B$5:$H$167,2,FALSE) -> Gravedad especifica y absorción de agregado grueso | J20: =VLOOKUP(B20,ENS.!$B$5:$H$167,3,FALSE) -> ASTM C127-24 | K20: =VLOOKUP(B20,ENS.!$B$5:$H$167,4,FALSE) -> SI | L20: 110 | M20: 1 | N20: =+L20*M20 -> 110
B21: AG19 | C21: =VLOOKUP(B21,ENS.!$B$5:$H$167,2,FALSE) -> Análisis granulométrico por tamizado en agregado | J21: =VLOOKUP(B21,ENS.!$B$5:$H$167,3,FALSE) -> ASTM C136/C136M-19 | K21: =VLOOKUP(B21,ENS.!$B$5:$H$167,4,FALSE) -> SI | L21: 90 | M21: 1 | N21: =+L21*M21 -> 90
B22: SU23 | C22: =VLOOKUP(B22,ENS.!$B$5:$H$167,2,FALSE) -> Límite líquido y Límite Plástico del Suelo | J22: =VLOOKUP(B22,ENS.!$B$5:$H$167,3,FALSE) -> ASTM D4318-17ε1 | K22: =VLOOKUP(B22,ENS.!$B$5:$H$167,4,FALSE) -> SI | L22: =VLOOKUP(B22,ENS.!$B$5:$H$167,7,FALSE) -> 90 | M22: 1 | N22: =+L22*M22 -> 90
B23: SU22 | C23: =VLOOKUP(B23,ENS.!$B$5:$H$167,2,FALSE) -> Clasificación suelo SUCS - AASHTO | J23: =VLOOKUP(B23,ENS.!$B$5:$H$167,3,FALSE) -> ASTM D2487-17 (Reapproved 2025) / ASTM D3282-24 | K23: =VLOOKUP(B23,ENS.!$B$5:$H$167,4,FALSE) -> SI | L23: =VLOOKUP(B23,ENS.!$B$5:$H$167,7,FALSE) -> 20 | M23: 1 | N23: =+L23*M23 -> 20
L24: Costo parcial | N24: =SUM(N17:N23) -> 560
L25: IGV 18% | N25: =+N24*0.18 -> 100.8
L26: Costo Total (S/) | N26: =+N24+N25 -> 660.8
B28: VALIDEZ DE LA OFERTA: 30 días calendario. Si la cotización llegó al límite de su validez, solicite una actualización.
B29: CONDICIONES ESPECÍFICAS PARA LOS ENSAYOS DE LABORATORIO: - El cliente deberá enviar al laboratorio, para los ensayos del material, la cantidad mínima de 80 kg por cada tipo de muestra. - El cliente deberá de entregar las muestras debidamente identificadas. - El cliente deberá especificar la Norma a ser utilizada para la ejecución del ensayo, caso contrario se considera Norma ASTM vigente de acuerdo con el alcance del laboratorio. - El cliente deberá entregar las muestras en las instalaciones del LEM, ubicado en la Av. Marañón N° 763, Los Olivos, Lima.
B30: PLAZO ESTIMADO DE EJECUCIÓN DE SERVICIO: - El plazo de entrega de los resultados se estima en 04 días hábiles, este tiempo será evaluado de acuerdo a la cantidad de muestra recepcionada y está sujeto a la programacion enviada por el Laboratorio de Ensayos de Materiales. - El laboratorio enviará un correo de confirmación de recepción y fecha de entrega del informe.
B31: COM-F-01 Página 1 de 2 Versión: 04 (10-11-2025)
B32: CONTRAMUESTRA Al finalizar los ensayos, la muestra sobrante/contramuestra permanecerán en custodia por un tiempo de 10 dias calendario después de emitido el informe de ensayo. Siempre que se trate de una muestra dirimente, las contramuestras serán devueltas a los clientes, previa coordinación y autorización, caso contrario, serán eliminadas si se trata de residuos del ensayo o contramuestras de ensayo.
B33: CONFIDENCIALIDAD: GEOFAL S.A.C mantiene acuerdos de confidencialidad entre el cliente y el laboratorio, la divulgación de la información sin la autorización de las partes, no es permitida. El laboratorio mantiene reserva de la información brindada por el cliente, salvo solicitud de la información por ley, o por entidades gubernamentales inmersos dentro del presente servicio de ensayo.
B34: QUEJAS Y SUGERENCIAS: El plazo máximo para la recepción de quejas relacionadas con un informe técnico es de diez (10) días calendarios, contados a partir de la fecha de emisión del documento correspondiente. Transcurrido dicho plazo, no se aceptarán quejas bajo ninguna circunstancia. En caso de tener alguna queja o sugerencia, lo invitamos a conocer nuestro Proceso de Atención de Quejas, el cual dará inicio 24 horas después de la recepción formal de la queja.
B35: ENTREGA DE INFORME DE ENSAYO: - De acuerdo a los lineamientos de INACAL - DM, los informes de ensayo son emitidos de forma digital con firma electrónica y QR. - La entrega de los informes de ensayo será mediante la plataforma de Intranet de la pagina web www.geofal.com.pe, y se enviará un correo de confirmación al cliente con el usuario y clave para el acceso. Asi mismo el cliente puede ingresar a la gruía deusuario que es visible en la página web. - Geofal no declara conformidad de sus informes de ensayo. - En caso se requiera la modificación del informe de ensayo a consecuencia de los datos proporcionados por el cliente, esta se realizará mediante la emisión de un nuevo informe que tendrá un costo adicional de acuerdo a evaluación.
B36: HORARIO DE ATENCIÓN El horario para recepción de muestra y entrega de informes es de Lunes a Viernes de 8:30am a 1:00pm y 2:00pm a 5:30pm, y Sábado de 8:30am a 12:30pm
B39: CONDICIÓN: El pago del servicio deberá ser realizado por Adelantado. | P39: CONDICIONES DE PAGO
B40: RAZON SOCIAL: Geofal S.A.C. RUC: 20549356762 | P40: CONDICIÓN: El pago del servicio se realizara de acuerdo a la valorización mensual
B41: Sírvase realizar el depósito correspondiente de los servicios a nuestra cuenta bancaria: | P41: CONDICIÓN: El pago del servicio deberá ser realizado por Adelantado.
B42: Cuenta de detraccion Banco de La Nación: | P42: CONDICIÓN: El pago del servicio Adelanto el 50% y saldo previo a la entrega del Informe.
B43: - Cuenta de detraccion Banco de La Nación: Nº 00-074-045472 | P43: CONDICIÓN: El pago del servicio Crédito a 7 días, previa orden de servicio.
B44: Cuenta corriente Interbank: | P44: CONDICIÓN: El pago del servicio Crédito a 30 días, previa orden de servicio.
B45: - Cuenta Corriente en Soles de Interbank: Nº 200-3005201096 | P45: CONDICIÓN: El pago del servicio Crédito a 15 días, previa orden de servicio.
B46: - Código Interbancario (CCI) de Interbank: Nº 003-200- 003005201096-31
B47: Cuenta corriente BCP:
B48: - Cuenta Corriente en Soles del Banco de Crédito del Perú (BCP): Nº 192 2024 3030 04
B49: - Código Interbancario (CCI) del Banco de Crédito del Perú (BCP): Nº 002-192-002 02430 3004-34
B50: Cuenta corriente BBVA:
B51: - Cuenta Corriente en Soles BBVA: Nº 0011-0174-0100082311-00
B52: - Código Interbancario (CCI) BBVA: Nº 011-174-000100082311-00
B56: La aceptación de la cotización por parte del cliente podrá manifestarse a través de cualquiera de las siguientes acciones: el pago correspondiente al servicio, el envío de la orden de servicio, o el envío de un correo electrónico confirmando la aceptación del servicio según la presente cotización, al correo asesorcomercial@geofal.com.pe y/o mediante mensaje de WhatsApp al número del asesor comercial, en señal de conformidad.
B58: Atentamente,
B60: Geofal SAC
B61: Av. Marañón N° 763, Los Olivos, Lima, Perù
B62: Teléfono laboratorio: (01) 7543070 / Teléfono Oficina: (01) 9051911
B63: Web: www.geofal.com.pe
B65: COM-F-01 Página 2 de 2 Versión: 04 (10-11-2025) | M65: Fin del documento

Sheet SU-AG4
G3: 18 | P3: ID CLIENTE | Q3: 1217
B5: CLIENTE: | D5: =VLOOKUP($Q$3,BD_Clientes,2,FALSE) -> SISTEMA Y GESTIÓN DE INGENIERÍA PERÚ S.A.C. | J5: PROYECTO1: | L5: =VLOOKUP($Q$3,BD_Clientes,9,FALSE) -> Mejoramiento y ampliación del sistema de agua potable y alcantarillado de los sectores 353 y 360 y nuevas habitaciones esquema integral Carabayllo - Sectores 352, 355, 356, 357, 358 | P5: 222
B6: R.U.C.1: | D6: =VLOOKUP($Q$3,BD_Clientes,3,FALSE) -> 20611630370 | P6: 222
B7: CONTACTO: | D7: =VLOOKUP($Q$3,BD_Clientes,5,FALSE) -> Winnie Allison Ñahui Cervantes | J7: UBICACIÓN1: | L7: =VLOOKUP($Q$3,BD_Clientes,10,FALSE) -> Carabayllo - Lima | P7: 222
B8: TELÉFONO DE CONTACTO: | E8: =VLOOKUP($Q$3,BD_Clientes,7,FALSE) -> 951714829 | J8: PERSONAL COMERCIAL: | L8: Silvia Peralta
B9: CORREO: | D9: =VLOOKUP($Q$3,BD_Clientes,8,FALSE) -> supervisorqc@sygingenieria.pe | J9: TELÉFONO DE COMERCIAL: | L9: 982429895
B10: FECHA SOLICITUD: | E10: 46028 | J10: FECHA DE EMISIÓN: | L10: 46028
B11: REFERENCIA: Segùn lo solicitado vía correo electrónico / Whatsapp / Teléfono / Personalmente.
B12: 1: Información no considerada para las personas naturales.
B13: Por medio de la presente, tenemos el agrado de remitirle nuestra cotización en base a su solicitud, por los servicios de los siguientes ensayos de laboratorio.
B16: CÓDIGO | C16: DESCRIPCIÓN | J16: NORMA | K16: ACREDITADO | L16: COSTO UNITARIO | M16: CANTIDAD | N16: COSTO PARCIAL
B17: SU24 | C17: =VLOOKUP(B17,ENS.!$B$5:$H$167,2,FALSE) -> Análisis granulométrico por tamizado en Suelo | J17: =VLOOKUP(B17,ENS.!$B$5:$H$167,3,FALSE) -> ASTM D6913/D6913M-17 | K17: =VLOOKUP(B17,ENS.!$B$5:$H$167,4,FALSE) -> SI | L17: 90 | M17: 1 | N17: =+L17*M17 -> 90
L18: Costo parcial | N18: =SUM(N17:N17) -> 90
L19: IGV 18% | N19: =+N18*0.18 -> 16.2
L20: Costo Total (S/) | N20: =+N18+N19 -> 106.2
B22: VALIDEZ DE LA OFERTA: 30 días calendario. Si la cotización llegó al límite de su validez, solicite una actualización.
B23: CONDICIONES ESPECÍFICAS PARA LOS ENSAYOS DE LABORATORIO: - El cliente deberá enviar al laboratorio, para los ensayos del material, la cantidad mínima de 20 kg por cada tipo de muestra. - El cliente deberá de entregar las muestras debidamente identificadas. - El cliente deberá especificar la Norma a ser utilizada para la ejecución del ensayo, caso contrario se considera Norma ASTM vigente de acuerdo con el alcance del laboratorio. - El cliente deberá entregar las muestras en las instalaciones del LEM, ubicado en la Av. Marañón N° 763, Los Olivos, Lima.
B24: PLAZO ESTIMADO DE EJECUCIÓN DE SERVICIO: - El plazo de entrega de los resultados se estima en 03 días hábiles, este tiempo será evaluado de acuerdo a la cantidad de muestra recepcionada y está sujeto a la programacion enviada por el Laboratorio de Ensayos de Materiales. - El laboratorio enviará un correo de confirmación de recepción y fecha de entrega del informe.
B25: COM-F-01 Página 1 de 2 Versión: 04 (10-11-2025)
B26: CONTRAMUESTRA Al finalizar los ensayos, la muestra sobrante/contramuestra permanecerán en custodia por un tiempo de 10 dias calendario después de emitido el informe de ensayo. Siempre que se trate de una muestra dirimente, las contramuestras serán devueltas a los clientes, previa coordinación y autorización, caso contrario, serán eliminadas si se trata de residuos del ensayo o contramuestras de ensayo.
B27: CONFIDENCIALIDAD: GEOFAL S.A.C mantiene acuerdos de confidencialidad entre el cliente y el laboratorio, la divulgación de la información sin la autorización de las partes, no es permitida. El laboratorio mantiene reserva de la información brindada por el cliente, salvo solicitud de la información por ley, o por entidades gubernamentales inmersos dentro del presente servicio de ensayo.
B28: QUEJAS Y SUGERENCIAS: El plazo máximo para la recepción de quejas relacionadas con un informe técnico es de diez (10) días calendarios, contados a partir de la fecha de emisión del documento correspondiente. Transcurrido dicho plazo, no se aceptarán quejas bajo ninguna circunstancia. En caso de tener alguna queja o sugerencia, lo invitamos a conocer nuestro Proceso de Atención de Quejas, el cual dará inicio 24 horas después de la recepción formal de la queja.
B29: ENTREGA DE INFORME DE ENSAYO: - De acuerdo a los lineamientos de INACAL - DM, los informes de ensayo son emitidos de forma digital con firma electrónica y QR. - La entrega de los informes de ensayo será mediante la plataforma de Intranet de la pagina web www.geofal.com.pe, y se enviará un correo de confirmación al cliente con el usuario y clave para el acceso. Asi mismo el cliente puede ingresar a la gruía deusuario que es visible en la página web. - Geofal no declara conformidad de sus informes de ensayo. - En caso se requiera la modificación del informe de ensayo a consecuencia de los datos proporcionados por el cliente, esta se realizará mediante la emisión de un nuevo informe que tendrá un costo adicional de acuerdo a evaluación.
B30: HORARIO DE ATENCIÓN El horario para recepción de muestra y entrega de informes es de Lunes a Viernes de 8:30am a 1:00pm y 2:00pm a 5:30pm, y Sábado de 8:30am a 12:30pm
B33: CONDICIÓN: El pago del servicio deberá ser realizado por Adelantado. | P33: CONDICIONES DE PAGO
B34: RAZON SOCIAL: Geofal S.A.C. RUC: 20549356762 | P34: CONDICIÓN: El pago del servicio se realizara de acuerdo a la valorización mensual
B35: Sírvase realizar el depósito correspondiente de los servicios a nuestra cuenta bancaria: | P35: CONDICIÓN: El pago del servicio deberá ser realizado por Adelantado.
B36: Cuenta de detraccion Banco de La Nación: | P36: CONDICIÓN: El pago del servicio Adelanto el 50% y saldo previo a la entrega del Informe.
B37: - Cuenta de detraccion Banco de La Nación: Nº 00-074-045472 | P37: CONDICIÓN: El pago del servicio Crédito a 7 días, previa orden de servicio.
B38: Cuenta corriente Interbank: | P38: CONDICIÓN: El pago del servicio Crédito a 30 días, previa orden de servicio.
B39: - Cuenta Corriente en Soles de Interbank: Nº 200-3005201096 | P39: CONDICIÓN: El pago del servicio Crédito a 15 días, previa orden de servicio.
B40: - Código Interbancario (CCI) de Interbank: Nº 003-200- 003005201096-31
B41: Cuenta corriente BCP:
B42: - Cuenta Corriente en Soles del Banco de Crédito del Perú (BCP): Nº 192 2024 3030 04
B43: - Código Interbancario (CCI) del Banco de Crédito del Perú (BCP): Nº 002-192-002 02430 3004-34
B44: Cuenta corriente BBVA:
B45: - Cuenta Corriente en Soles BBVA: Nº 0011-0174-0100082311-00
B46: - Código Interbancario (CCI) BBVA: Nº 011-174-000100082311-00
B50: La aceptación de la cotización por parte del cliente podrá manifestarse a través de cualquiera de las siguientes acciones: el pago correspondiente al servicio, el envío de la orden de servicio, o el envío de un correo electrónico confirmando la aceptación del servicio según la presente cotización, al correo asesorcomercial@geofal.com.pe y/o mediante mensaje de WhatsApp al número del asesor comercial, en señal de conformidad.
B52: Atentamente,
B54: Geofal SAC
B55: Av. Marañón N° 763, Los Olivos, Lima, Perù
B56: Teléfono laboratorio: (01) 7543070 / Teléfono Oficina: (01) 9051911
B57: Web: www.geofal.com.pe
B59: COM-F-01 Página 2 de 2 Versión: 04 (10-11-2025) | M59: Fin del documento

Sheet SU-AG5
G3: 222 | P3: ID CLIENTE | Q3: 979
B5: CLIENTE: | D5: =VLOOKUP($Q$3,BD_Clientes,2,FALSE) -> NS ANDINA SAC | J5: PROYECTO1: | L5: =VLOOKUP($Q$3,BD_Clientes,9,FALSE) -> Parque Eólico Caravelí | P5: 222
B6: R.U.C.1: | D6: =VLOOKUP($Q$3,BD_Clientes,3,FALSE) -> 20613516124 | P6: 222
B7: CONTACTO: | D7: =VLOOKUP($Q$3,BD_Clientes,5,FALSE) -> Ing. Jilberth Ovalles | J7: UBICACIÓN1: | L7: =VLOOKUP($Q$3,BD_Clientes,10,FALSE) -> San Juan de Marcona - Ica | P7: 222
B8: TELÉFONO DE CONTACTO: | E8: =VLOOKUP($Q$3,BD_Clientes,7,FALSE) -> 912548581 | J8: PERSONAL COMERCIAL: | L8: Silvia Peralta
B9: CORREO: | D9: =VLOOKUP($Q$3,BD_Clientes,8,FALSE) -> jilberth.ovalles@grupo-asp.com | J9: TELÉFONO DE COMERCIAL: | L9: 982429895
B10: FECHA SOLICITUD: | E10: 45973 | J10: FECHA DE EMISIÓN: | L10: 45973
B11: REFERENCIA: Segùn lo solicitado vía correo electrónico / Whatsapp / Teléfono / Personalmente.
B12: 1: Información no considerada para las personas naturales.
B13: Por medio de la presente, tenemos el agrado de remitirle nuestra cotización en base a su solicitud, por los servicios de los siguientes ensayos de laboratorio.
B16: CÓDIGO | C16: DESCRIPCIÓN | J16: NORMA | K16: ACREDITADO | L16: COSTO UNITARIO | M16: CANTIDAD | N16: COSTO PARCIAL
C17: BASE MATERIAL TRITURADO - ACOPIO EJE 05
B18: AG19 | C18: =VLOOKUP(B18,ENS.!$B$5:$H$167,2,FALSE) -> Análisis granulométrico por tamizado en agregado | J18: =VLOOKUP(B18,ENS.!$B$5:$H$167,3,FALSE) -> ASTM C136/C136M-19 | K18: =VLOOKUP(B18,ENS.!$B$5:$H$167,4,FALSE) -> SI | L18: =VLOOKUP(B18,ENS.!$B$5:$H$167,7,FALSE) -> 100 | M18: 1 | N18: =+L18*M18 -> 100
B19: SU37 | C19: =VLOOKUP(B19,ENS.!$B$5:$H$167,2,FALSE) -> California Bearing Ratio (CBR) | J19: =VLOOKUP(B19,ENS.!$B$5:$H$167,3,FALSE) -> ASTM D1883-21 | K19: =VLOOKUP(B19,ENS.!$B$5:$H$167,4,FALSE) -> SI | L19: 250 | M19: 1 | N19: =+L19*M19 -> 250
B20: SU19 | C20: =VLOOKUP(B20,ENS.!$B$5:$H$167,2,FALSE) -> Próctor modificado | J20: =VLOOKUP(B20,ENS.!$B$5:$H$167,3,FALSE) -> ASTM D1557-12 (Reapproved 2021) | K20: =VLOOKUP(B20,ENS.!$B$5:$H$167,4,FALSE) -> SI | L20: =VLOOKUP(B20,ENS.!$B$5:$H$167,7,FALSE) -> 150 | M20: 1 | N20: =+L20*M20 -> 150
B21: SU32 | C21: =VLOOKUP(B21,ENS.!$B$5:$H$167,2,FALSE) -> Gravedad específica de los sólidos del suelo. | J21: =VLOOKUP(B21,ENS.!$B$5:$H$167,3,FALSE) -> ASTM D854-14 | K21: =VLOOKUP(B21,ENS.!$B$5:$H$167,4,FALSE) -> NO | L21: 80 | M21: 1 | N21: =+L21*M21 -> 80
B22: AG28 | C22: =VLOOKUP(B22,ENS.!$B$5:$H$167,2,FALSE) -> Gravedad especifica y absorción de agregado grueso | J22: =VLOOKUP(B22,ENS.!$B$5:$H$167,3,FALSE) -> ASTM C127-24 | K22: =VLOOKUP(B22,ENS.!$B$5:$H$167,4,FALSE) -> SI | L22: 100 | M22: 1 | N22: =+L22*M22 -> 100
B23: SU23 | C23: =VLOOKUP(B23,ENS.!$B$5:$H$167,2,FALSE) -> Límite líquido y Límite Plástico del Suelo | J23: =VLOOKUP(B23,ENS.!$B$5:$H$167,3,FALSE) -> ASTM D4318-17ε1 | K23: =VLOOKUP(B23,ENS.!$B$5:$H$167,4,FALSE) -> SI | L23: 80 | M23: 1 | N23: =+L23*M23 -> 80
B24: AG08A | C24: =VLOOKUP(B24,ENS.!$B$5:$H$167,2,FALSE) -> Inalterabilidad Agregado Grueso con Sulfato de Magnesio. | J24: =VLOOKUP(B24,ENS.!$B$5:$H$167,3,FALSE) -> NTP 400.016 | K24: =VLOOKUP(B24,ENS.!$B$5:$H$167,4,FALSE) -> NO | L24: =VLOOKUP(B24,ENS.!$B$5:$H$167,7,FALSE) -> 350 | M24: 1 | N24: =+L24*M24 -> 350
B25: AG08B | C25: =VLOOKUP(B25,ENS.!$B$5:$H$167,2,FALSE) -> Inalterabilidad Agregado Fino con Sulfato de Magnesio. | J25: =VLOOKUP(B25,ENS.!$B$5:$H$167,3,FALSE) -> NTP 400.016 | K25: =VLOOKUP(B25,ENS.!$B$5:$H$167,4,FALSE) -> NO | L25: =VLOOKUP(B25,ENS.!$B$5:$H$167,7,FALSE) -> 350 | M25: 1 | N25: =+L25*M25 -> 350
B26: AG36 | C26: =VLOOKUP(B26,ENS.!$B$5:$H$167,2,FALSE) -> Abrasión los Ángeles de agregado grueso de tamaño pequeño. | J26: =VLOOKUP(B26,ENS.!$B$5:$H$167,3,FALSE) -> ASTM C131/C131M-20 | K26: =VLOOKUP(B26,ENS.!$B$5:$H$167,4,FALSE) -> SI | L26: 200 | M26: 1 | N26: =+L26*M26 -> 200
B27: AG25 | C27: =VLOOKUP(B27,ENS.!$B$5:$H$167,2,FALSE) -> Terrones de arcilla y partículas friables, Fino o grueso. | J27: =VLOOKUP(B27,ENS.!$B$5:$H$167,3,FALSE) -> NTP 400.015 | K27: =VLOOKUP(B27,ENS.!$B$5:$H$167,4,FALSE) -> NO | L27: =VLOOKUP(B27,ENS.!$B$5:$H$167,7,FALSE) -> 120 | M27: 1 | N27: =+L27*M27 -> 120
B28: SU21 | C28: =VLOOKUP(B28,ENS.!$B$5:$H$167,2,FALSE) -> Equivalente de arena | J28: =VLOOKUP(B28,ENS.!$B$5:$H$167,3,FALSE) -> ASTM D2419-22 | K28: =VLOOKUP(B28,ENS.!$B$5:$H$167,4,FALSE) -> SI | L28: =VLOOKUP(B28,ENS.!$B$5:$H$167,7,FALSE) -> 150 | M28: 1 | N28: =+L28*M28 -> 150
B29: AG29 | C29: =VLOOKUP(B29,ENS.!$B$5:$H$167,2,FALSE) -> Valor de azul de metileno. | J29: =VLOOKUP(B29,ENS.!$B$5:$H$167,3,FALSE) -> AASHTO TP57 | K29: =VLOOKUP(B29,ENS.!$B$5:$H$167,4,FALSE) -> NO | L29: =VLOOKUP(B29,ENS.!$B$5:$H$167,7,FALSE) -> 150 | M29: 1 | N29: =+L29*M29 -> 150
B30: AG34 | C30: =VLOOKUP(B30,ENS.!$B$5:$H$167,2,FALSE) -> Partículas planas y alargadas en agregado grueso | J30: =VLOOKUP(B30,ENS.!$B$5:$H$167,3,FALSE) -> ASTM D4791-19 (Reapproved 2023) | K30: =VLOOKUP(B30,ENS.!$B$5:$H$167,4,FALSE) -> SI | L30: 100 | M30: 1 | N30: =+L30*M30 -> 100
B31: AG35 | C31: =VLOOKUP(B31,ENS.!$B$5:$H$167,2,FALSE) -> Porcentaje de Caras fracturadas en agregado grueso | J31: =VLOOKUP(B31,ENS.!$B$5:$H$167,3,FALSE) -> ASTM D5821-13 (Reapproved 2017) | K31: =VLOOKUP(B31,ENS.!$B$5:$H$167,4,FALSE) -> SI | L31: 100 | M31: 1 | N31: =+L31*M31 -> 100
B32: AG33 | C32: =VLOOKUP(B32,ENS.!$B$5:$H$167,2,FALSE) -> Angularidad del agregado fino. | J32: =VLOOKUP(B32,ENS.!$B$5:$H$167,3,FALSE) -> MTC E222 | K32: =VLOOKUP(B32,ENS.!$B$5:$H$167,4,FALSE) -> NO | L32: =VLOOKUP(B32,ENS.!$B$5:$H$167,7,FALSE) -> 120 | M32: 1 | N32: =+L32*M32 -> 120
B33: AG18 | C33: =VLOOKUP(B33,ENS.!$B$5:$H$167,2,FALSE) -> Gravedad específica y absorción del agregado fino | J33: =VLOOKUP(B33,ENS.!$B$5:$H$167,3,FALSE) -> ASTM C128-22 | K33: =VLOOKUP(B33,ENS.!$B$5:$H$167,4,FALSE) -> SI | L33: =VLOOKUP(B33,ENS.!$B$5:$H$167,7,FALSE) -> 150 | M33: 1 | N33: =+L33*M33 -> 150
B34: AG11 | C34: =VLOOKUP(B34,ENS.!$B$5:$H$167,2,FALSE) -> Contenido Sales solubles, fino o grueso. | J34: =VLOOKUP(B34,ENS.!$B$5:$H$167,3,FALSE) -> MTC E-219 | K34: =VLOOKUP(B34,ENS.!$B$5:$H$167,4,FALSE) -> NO | L34: =VLOOKUP(B34,ENS.!$B$5:$H$167,7,FALSE) -> 150 | M34: 2 | N34: =+L34*M34 -> 300
C35: BASE MATERIAL TRITURADO - ACOPIO AERO 27
B36: AG19 | C36: =VLOOKUP(B36,ENS.!$B$5:$H$167,2,FALSE) -> Análisis granulométrico por tamizado en agregado | J36: =VLOOKUP(B36,ENS.!$B$5:$H$167,3,FALSE) -> ASTM C136/C136M-19 | K36: =VLOOKUP(B36,ENS.!$B$5:$H$167,4,FALSE) -> SI | L36: =VLOOKUP(B36,ENS.!$B$5:$H$167,7,FALSE) -> 100 | M36: 1 | N36: =+L36*M36 -> 100
B37: SU37 | C37: =VLOOKUP(B37,ENS.!$B$5:$H$167,2,FALSE) -> California Bearing Ratio (CBR) | J37: =VLOOKUP(B37,ENS.!$B$5:$H$167,3,FALSE) -> ASTM D1883-21 | K37: =VLOOKUP(B37,ENS.!$B$5:$H$167,4,FALSE) -> SI | L37: 250 | M37: 1 | N37: =+L37*M37 -> 250
B38: SU19 | C38: =VLOOKUP(B38,ENS.!$B$5:$H$167,2,FALSE) -> Próctor modificado | J38: =VLOOKUP(B38,ENS.!$B$5:$H$167,3,FALSE) -> ASTM D1557-12 (Reapproved 2021) | K38: =VLOOKUP(B38,ENS.!$B$5:$H$167,4,FALSE) -> SI | L38: =VLOOKUP(B38,ENS.!$B$5:$H$167,7,FALSE) -> 150 | M38: 1 | N38: =+L38*M38 -> 150
B39: SU32 | C39: =VLOOKUP(B39,ENS.!$B$5:$H$167,2,FALSE) -> Gravedad específica de los sólidos del suelo. | J39: =VLOOKUP(B39,ENS.!$B$5:$H$167,3,FALSE) -> ASTM D854-14 | K39: =VLOOKUP(B39,ENS.!$B$5:$H$167,4,FALSE) -> NO | L39: 80 | M39: 1 | N39: =+L39*M39 -> 80
B40: AG28 | C40: =VLOOKUP(B40,ENS.!$B$5:$H$167,2,FALSE) -> Gravedad especifica y absorción de agregado grueso | J40: =VLOOKUP(B40,ENS.!$B$5:$H$167,3,FALSE) -> ASTM C127-24 | K40: =VLOOKUP(B40,ENS.!$B$5:$H$167,4,FALSE) -> SI | L40: 100 | M40: 1 | N40: =+L40*M40 -> 100
B41: SU23 | C41: =VLOOKUP(B41,ENS.!$B$5:$H$167,2,FALSE) -> Límite líquido y Límite Plástico del Suelo | J41: =VLOOKUP(B41,ENS.!$B$5:$H$167,3,FALSE) -> ASTM D4318-17ε1 | K41: =VLOOKUP(B41,ENS.!$B$5:$H$167,4,FALSE) -> SI | L41: 80 | M41: 1 | N41: =+L41*M41 -> 80
B42: AG08A | C42: =VLOOKUP(B42,ENS.!$B$5:$H$167,2,FALSE) -> Inalterabilidad Agregado Grueso con Sulfato de Magnesio. | J42: =VLOOKUP(B42,ENS.!$B$5:$H$167,3,FALSE) -> NTP 400.016 | K42: =VLOOKUP(B42,ENS.!$B$5:$H$167,4,FALSE) -> NO | L42: =VLOOKUP(B42,ENS.!$B$5:$H$167,7,FALSE) -> 350 | M42: 1 | N42: =+L42*M42 -> 350
B43: AG08B | C43: =VLOOKUP(B43,ENS.!$B$5:$H$167,2,FALSE) -> Inalterabilidad Agregado Fino con Sulfato de Magnesio. | J43: =VLOOKUP(B43,ENS.!$B$5:$H$167,3,FALSE) -> NTP 400.016 | K43: =VLOOKUP(B43,ENS.!$B$5:$H$167,4,FALSE) -> NO | L43: =VLOOKUP(B43,ENS.!$B$5:$H$167,7,FALSE) -> 350 | M43: 1 | N43: =+L43*M43 -> 350
B44: AG36 | C44: =VLOOKUP(B44,ENS.!$B$5:$H$167,2,FALSE) -> Abrasión los Ángeles de agregado grueso de tamaño pequeño. | J44: =VLOOKUP(B44,ENS.!$B$5:$H$167,3,FALSE) -> ASTM C131/C131M-20 | K44: =VLOOKUP(B44,ENS.!$B$5:$H$167,4,FALSE) -> SI | L44: 200 | M44: 1 | N44: =+L44*M44 -> 200
B45: AG25 | C45: =VLOOKUP(B45,ENS.!$B$5:$H$167,2,FALSE) -> Terrones de arcilla y partículas friables, Fino o grueso. | J45: =VLOOKUP(B45,ENS.!$B$5:$H$167,3,FALSE) -> NTP 400.015 | K45: =VLOOKUP(B45,ENS.!$B$5:$H$167,4,FALSE) -> NO | L45: =VLOOKUP(B45,ENS.!$B$5:$H$167,7,FALSE) -> 120 | M45: 1 | N45: =+L45*M45 -> 120
B46: SU21 | C46: =VLOOKUP(B46,ENS.!$B$5:$H$167,2,FALSE) -> Equivalente de arena | J46: =VLOOKUP(B46,ENS.!$B$5:$H$167,3,FALSE) -> ASTM D2419-22 | K46: =VLOOKUP(B46,ENS.!$B$5:$H$167,4,FALSE) -> SI | L46: =VLOOKUP(B46,ENS.!$B$5:$H$167,7,FALSE) -> 150 | M46: 1 | N46: =+L46*M46 -> 150
B47: AG29 | C47: =VLOOKUP(B47,ENS.!$B$5:$H$167,2,FALSE) -> Valor de azul de metileno. | J47: =VLOOKUP(B47,ENS.!$B$5:$H$167,3,FALSE) -> AASHTO TP57 | K47: =VLOOKUP(B47,ENS.!$B$5:$H$167,4,FALSE) -> NO | L47: =VLOOKUP(B47,ENS.!$B$5:$H$167,7,FALSE) -> 150 | M47: 1 | N47: =+L47*M47 -> 150
B48: AG34 | C48: =VLOOKUP(B48,ENS.!$B$5:$H$167,2,FALSE) -> Partículas planas y alargadas en agregado grueso | J48: =VLOOKUP(B48,ENS.!$B$5:$H$167,3,FALSE) -> ASTM D4791-19 (Reapproved 2023) | K48: =VLOOKUP(B48,ENS.!$B$5:$H$167,4,FALSE) -> SI | L48: 100 | M48: 1 | N48: =+L48*M48 -> 100
B49: AG35 | C49: =VLOOKUP(B49,ENS.!$B$5:$H$167,2,FALSE) -> Porcentaje de Caras fracturadas en agregado grueso | J49: =VLOOKUP(B49,ENS.!$B$5:$H$167,3,FALSE) -> ASTM D5821-13 (Reapproved 2017) | K49: =VLOOKUP(B49,ENS.!$B$5:$H$167,4,FALSE) -> SI | L49: 100 | M49: 1 | N49: =+L49*M49 -> 100
B50: AG33 | C50: =VLOOKUP(B50,ENS.!$B$5:$H$167,2,FALSE) -> Angularidad del agregado fino. | J50: =VLOOKUP(B50,ENS.!$B$5:$H$167,3,FALSE) -> MTC E222 | K50: =VLOOKUP(B50,ENS.!$B$5:$H$167,4,FALSE) -> NO | L50: =VLOOKUP(B50,ENS.!$B$5:$H$167,7,FALSE) -> 120 | M50: 1 | N50: =+L50*M50 -> 120
B51: AG18 | C51: =VLOOKUP(B51,ENS.!$B$5:$H$167,2,FALSE) -> Gravedad específica y absorción del agregado fino | J51: =VLOOKUP(B51,ENS.!$B$5:$H$167,3,FALSE) -> ASTM C128-22 | K51: =VLOOKUP(B51,ENS.!$B$5:$H$167,4,FALSE) -> SI | L51: =VLOOKUP(B51,ENS.!$B$5:$H$167,7,FALSE) -> 150 | M51: 1 | N51: =+L51*M51 -> 150
B52: AG11 | C52: =VLOOKUP(B52,ENS.!$B$5:$H$167,2,FALSE) -> Contenido Sales solubles, fino o grueso. | J52: =VLOOKUP(B52,ENS.!$B$5:$H$167,3,FALSE) -> MTC E-219 | K52: =VLOOKUP(B52,ENS.!$B$5:$H$167,4,FALSE) -> NO | L52: =VLOOKUP(B52,ENS.!$B$5:$H$167,7,FALSE) -> 150 | M52: 2 | N52: =+L52*M52 -> 300
L53: Costo parcial | N53: =SUM(N17:N52) -> 5700
B54: COM-F-01 Página 1 de 2 Versión: 04 (10-11-2025) | L54: IGV 18% | N54: =+N53*0.18 -> 1026
L55: Costo Total (S/) | N55: =+N53+N54 -> 6726
B58: VALIDEZ DE LA OFERTA: 30 días calendario. Si la cotización llegó al límite de su validez, solicite una actualización.
B59: CONDICIONES ESPECÍFICAS PARA LOS ENSAYOS DE LABORATORIO: - El cliente deberá enviar al laboratorio, para los ensayos del material, la cantidad mínima de 150 kg por cada tipo de muestra. - El cliente deberá de entregar las muestras debidamente identificadas. - El cliente deberá especificar la Norma a ser utilizada para la ejecución del ensayo, caso contrario se considera Norma ASTM vigente de acuerdo con el alcance del laboratorio. - El cliente deberá entregar las muestras en las instalaciones del LEM, ubicado en la Av. Marañón N° 763, Los Olivos, Lima.
B60: PLAZO ESTIMADO DE EJECUCIÓN DE SERVICIO: - El plazo de entrega de los resultados se estima en 10 días hábiles, este tiempo será evaluado de acuerdo a la cantidad de muestra recepcionada y está sujeto a la programacion enviada por el Laboratorio de Ensayos de Materiales. - El laboratorio enviará un correo de confirmación de recepción y fecha de entrega del informe.
B61: CONTRAMUESTRA Al finalizar los ensayos, la muestra sobrante/contramuestra permanecerán en custodia por un tiempo de 10 dias calendario después de emitido el informe de ensayo. Siempre que se trate de una muestra dirimente, las contramuestras serán devueltas a los clientes, previa coordinación y autorización, caso contrario, serán eliminadas si se trata de residuos del ensayo o contramuestras de ensayo.
B62: CONFIDENCIALIDAD: GEOFAL S.A.C mantiene acuerdos de confidencialidad entre el cliente y el laboratorio, la divulgación de la información sin la autorización de las partes, no es permitida. El laboratorio mantiene reserva de la información brindada por el cliente, salvo solicitud de la información por ley, o por entidades gubernamentales inmersos dentro del presente servicio de ensayo.
B63: QUEJAS Y SUGERENCIAS: El plazo máximo para la recepción de quejas relacionadas con un informe técnico es de diez (10) días calendarios, contados a partir de la fecha de emisión del documento correspondiente. Transcurrido dicho plazo, no se aceptarán quejas bajo ninguna circunstancia. En caso de tener alguna queja o sugerencia, lo invitamos a conocer nuestro Proceso de Atención de Quejas, el cual dará inicio 24 horas después de la recepción formal de la queja.
B64: ENTREGA DE INFORME DE ENSAYO: - De acuerdo a los lineamientos de INACAL - DM, los informes de ensayo son emitidos de forma digital con firma electrónica y QR. - La entrega de los informes de ensayo será mediante la plataforma de Intranet de la pagina web www.geofal.com.pe, y se enviará un correo de confirmación al cliente con el usuario y clave para el acceso. Asi mismo el cliente puede ingresar a la gruía deusuario que es visible en la página web. - Geofal no declara conformidad de sus informes de ensayo. - En caso se requiera la modificación del informe de ensayo a consecuencia de los datos proporcionados por el cliente, esta se realizará mediante la emisión de un nuevo informe que tendrá un costo adicional de acuerdo a evaluación.
B65: HORARIO DE ATENCIÓN El horario para recepción de muestra y entrega de informes es de Lunes a Viernes de 8:30am a 1:00pm y 2:00pm a 5:30pm, y Sábado de 8:30am a 12:30pm
B68: CONDICIÓN: El pago del servicio deberá ser realizado por Adelantado. | P68: CONDICIONES DE PAGO
B69: RAZON SOCIAL: Geofal S.A.C. RUC: 20549356762 | P69: CONDICIÓN: El pago del servicio se realizara de acuerdo a la valorización mensual
B70: Sírvase realizar el depósito correspondiente de los servicios a nuestra cuenta bancaria: | P70: CONDICIÓN: El pago del servicio deberá ser realizado por Adelantado.
B71: Cuenta de detraccion Banco de La Nación: | P71: CONDICIÓN: El pago del servicio Adelanto el 50% y saldo previo a la entrega del Informe.
B72: - Cuenta de detraccion Banco de La Nación: Nº 00-074-045472 | P72: CONDICIÓN: El pago del servicio Crédito a 7 días, previa orden de servicio.
B73: Cuenta corriente Interbank: | P73: CONDICIÓN: El pago del servicio Crédito a 30 días, previa orden de servicio.
B74: - Cuenta Corriente en Soles de Interbank: Nº 200-3005201096 | P74: CONDICIÓN: El pago del servicio Crédito a 15 días, previa orden de servicio.
B75: - Código Interbancario (CCI) de Interbank: Nº 003-200- 003005201096-31
B76: Cuenta corriente BCP:
B77: - Cuenta Corriente en Soles del Banco de Crédito del Perú (BCP): Nº 192 2024 3030 04
B78: - Código Interbancario (CCI) del Banco de Crédito del Perú (BCP): Nº 002-192-002 02430 3004-34
B79: Cuenta corriente BBVA:
B80: - Cuenta Corriente en Soles BBVA: Nº 0011-0174-0100082311-00
B81: - Código Interbancario (CCI) BBVA: Nº 011-174-000100082311-00
B85: La aceptación de la cotización por parte del cliente podrá manifestarse a través de cualquiera de las siguientes acciones: el pago correspondiente al servicio, el envío de la orden de servicio, o el envío de un correo electrónico confirmando la aceptación del servicio según la presente cotización, al correo asesorcomercial@geofal.com.pe y/o mediante mensaje de WhatsApp al número del asesor comercial, en señal de conformidad.
B87: Atentamente,
B89: Geofal SAC
B90: Av. Marañón N° 763, Los Olivos, Lima, Perù
B91: Teléfono laboratorio: (01) 7543070 / Teléfono Oficina: (01) 9051911
B92: Web: www.geofal.com.pe
B94: COM-F-01 Página 2 de 2 Versión: 04 (10-11-2025) | M94: Fin del documento

Sheet SU-AG6
G3: 222 | P3: ID CLIENTE | Q3: 1130
B5: CLIENTE: | D5: =VLOOKUP($Q$3,BD_Clientes,2,FALSE) -> CONSORCIO LIMA NORTE | J5: PROYECTO1: | L5: =VLOOKUP($Q$3,BD_Clientes,9,FALSE) -> Mejoramiento y Ampliación del Sistema de Agua Potable y Alcantarillado de Los Sectores 359 y 360 y Nuevas Habilitaciones Esquema Integral de Carabayllo | P5: 222
B6: R.U.C.1: | D6: =VLOOKUP($Q$3,BD_Clientes,3,FALSE) -> 20614164833 | P6: 222
B7: CONTACTO: | D7: =VLOOKUP($Q$3,BD_Clientes,5,FALSE) -> Ing. Erick Aponte / Joao Cano | J7: UBICACIÓN1: | L7: =VLOOKUP($Q$3,BD_Clientes,10,FALSE) -> Carabayllo - Lima | P7: 222
B8: TELÉFONO DE CONTACTO: | E8: =VLOOKUP($Q$3,BD_Clientes,7,FALSE) -> 969934305 | J8: PERSONAL COMERCIAL: | L8: Silvia Peralta
B9: CORREO: | D9: =VLOOKUP($Q$3,BD_Clientes,8,FALSE) -> eaponte@ciolimanorte.com / jcano@ciolimanorte.com / joao.rinc.oftec@gmail.com | J9: TELÉFONO DE COMERCIAL: | L9: 982429895
B10: FECHA SOLICITUD: | E10: 46009 | J10: FECHA DE EMISIÓN: | L10: 46009
B11: REFERENCIA: Según lo solicitado vía correo electrónico / Whatsapp / Teléfono / Personalmente.
B12: 1: Información no considerada para las personas naturales.
B13: Por medio de la presente, tenemos el agrado de remitirle nuestra cotización en base a su solicitud, por los servicios de los siguientes ensayos de laboratorio.
B16: CÓDIGO | C16: DESCRIPCIÓN | J16: NORMA | K16: ACREDITADO | L16: COSTO UNITARIO | M16: CANTIDAD | N16: COSTO PARCIAL
C17: ARENA GRUESA - CANTERA ACUÑA
B18: AG25 | C18: =VLOOKUP(B18,ENS.!$B$5:$H$167,2,FALSE) -> Terrones de arcilla y partículas friables, Fino o grueso. | J18: =VLOOKUP(B18,ENS.!$B$5:$H$167,3,FALSE) -> NTP 400.015 | K18: =VLOOKUP(B18,ENS.!$B$5:$H$167,4,FALSE) -> NO | L18: =VLOOKUP(B18,ENS.!$B$5:$H$167,7,FALSE) -> 120 | M18: 1 | N18: =+L18*M18 -> 120
B19: AG24 | C19: =VLOOKUP(B19,ENS.!$B$5:$H$167,2,FALSE) -> Partículas Liviana en los agregados (carbon y lignito), Fino o grueso. | J19: =VLOOKUP(B19,ENS.!$B$5:$H$167,3,FALSE) -> NTP 400.023 | K19: =VLOOKUP(B19,ENS.!$B$5:$H$167,4,FALSE) -> NO | L19: =VLOOKUP(B19,ENS.!$B$5:$H$167,7,FALSE) -> 220 | M19: 1 | N19: =+L19*M19 -> 220
B20: AG16 | C20: =VLOOKUP(B20,ENS.!$B$5:$H$167,2,FALSE) -> Contenido de cloruros solubles. | J20: =VLOOKUP(B20,ENS.!$B$5:$H$167,3,FALSE) -> NTP 400.042 | K20: =VLOOKUP(B20,ENS.!$B$5:$H$167,4,FALSE) -> NO | L20: =VLOOKUP(B20,ENS.!$B$5:$H$167,7,FALSE) -> 90 | M20: 1 | N20: =+L20*M20 -> 90
B21: AG17 | C21: =VLOOKUP(B21,ENS.!$B$5:$H$167,2,FALSE) -> Contenido de sulfatos solubles. | J21: =VLOOKUP(B21,ENS.!$B$5:$H$167,3,FALSE) -> NTP 400.042 | K21: =VLOOKUP(B21,ENS.!$B$5:$H$167,4,FALSE) -> NO | L21: =VLOOKUP(B21,ENS.!$B$5:$H$167,7,FALSE) -> 150 | M21: 1 | N21: =+L21*M21 -> 150
B22: AG19 | C22: =VLOOKUP(B22,ENS.!$B$5:$H$167,2,FALSE) -> Análisis granulométrico por tamizado en agregado | J22: =VLOOKUP(B22,ENS.!$B$5:$H$167,3,FALSE) -> ASTM C136/C136M-19 | K22: =VLOOKUP(B22,ENS.!$B$5:$H$167,4,FALSE) -> SI | L22: 90 | M22: 1 | N22: =+L22*M22 -> 90
B23: AG23 | C23: =VLOOKUP(B23,ENS.!$B$5:$H$167,2,FALSE) -> Pasante de la malla No.200 | J23: =VLOOKUP(B23,ENS.!$B$5:$H$167,3,FALSE) -> ASTM C117-23 | K23: =VLOOKUP(B23,ENS.!$B$5:$H$167,4,FALSE) -> SI | L23: =VLOOKUP(B23,ENS.!$B$5:$H$167,7,FALSE) -> 120 | M23: 1 | N23: =+L23*M23 -> 120
L24: Costo parcial | N24: =SUM(N17:N23) -> 790
L25: IGV 18% | N25: =+N24*0.18 -> 142.2
L26: Costo Total (S/) | N26: =+N24+N25 -> 932.2
B28: VALIDEZ DE LA OFERTA: 30 días calendario. Si la cotización llegó al límite de su validez, solicite una actualización.
B29: CONDICIONES ESPECÍFICAS PARA LOS ENSAYOS DE LABORATORIO: - El cliente deberá enviar al laboratorio, para los ensayos del material, la cantidad mínima de 50 kg por cada tipo de muestra. - El cliente deberá de entregar las muestras debidamente identificadas. - El cliente deberá especificar la Norma a ser utilizada para la ejecución del ensayo, caso contrario se considera Norma ASTM, NTP vigente de acuerdo con el alcance del laboratorio. - El cliente deberá entregar las muestras en las instalaciones del LEM, ubicado en la Av. Marañón N° 763, Los Olivos, Lima.
B30: PLAZO ESTIMADO DE EJECUCIÓN DE SERVICIO: - El plazo de entrega de los resultados se estima en 03 días hábiles, este tiempo será evaluado de acuerdo a la cantidad de muestra recepcionada y está sujeto a la programacion enviada por el Laboratorio de Ensayos de Materiales. - El laboratorio enviará un correo de confirmación de recepción y fecha de entrega del informe.
B31: COM-F-01 Página 1 de 2 Versión: 04 (10-11-2025)
B32: CONTRAMUESTRA Al finalizar los ensayos, la muestra sobrante/contramuestra permanecerán en custodia por un tiempo de 10 dias calendario después de emitido el informe de ensayo. Siempre que se trate de una muestra dirimente, las contramuestras serán devueltas a los clientes, previa coordinación y autorización, caso contrario, serán eliminadas si se trata de residuos del ensayo o contramuestras de ensayo.
B33: CONFIDENCIALIDAD: GEOFAL S.A.C mantiene acuerdos de confidencialidad entre el cliente y el laboratorio, la divulgación de la información sin la autorización de las partes, no es permitida. El laboratorio mantiene reserva de la información brindada por el cliente, salvo solicitud de la información por ley, o por entidades gubernamentales inmersos dentro del presente servicio de ensayo.
B34: QUEJAS Y SUGERENCIAS: El plazo máximo para la recepción de quejas relacionadas con un informe técnico es de diez (10) días calendarios, contados a partir de la fecha de emisión del documento correspondiente. Transcurrido dicho plazo, no se aceptarán quejas bajo ninguna circunstancia. En caso de tener alguna queja o sugerencia, lo invitamos a conocer nuestro Proceso de Atención de Quejas, el cual dará inicio 24 horas después de la recepción formal de la queja.
B35: ENTREGA DE INFORME DE ENSAYO: - De acuerdo a los lineamientos de INACAL - DM, los informes de ensayo son emitidos de forma digital con firma electrónica y QR. - La entrega de los informes de ensayo será mediante la plataforma de Intranet de la pagina web www.geofal.com.pe, y se enviará un correo de confirmación al cliente con el usuario y clave para el acceso. Asi mismo el cliente puede ingresar a la gruía deusuario que es visible en la página web. - Geofal no declara conformidad de sus informes de ensayo. - En caso se requiera la modificación del informe de ensayo a consecuencia de los datos proporcionados por el cliente, esta se realizará mediante la emisión de un nuevo informe que tendrá un costo adicional de acuerdo a evaluación.
B36: HORARIO DE ATENCIÓN El horario para recepción de muestra y entrega de informes es de Lunes a Viernes de 8:30am a 1:00pm y 2:00pm a 5:30pm, y Sábado de 8:30am a 12:30pm
B39: CONDICIÓN: El pago del servicio deberá ser realizado por Adelantado. | P39: CONDICIONES DE PAGO
B40: RAZON SOCIAL: Geofal S.A.C. RUC: 20549356762 | P40: CONDICIÓN: El pago del servicio se realizara de acuerdo a la valorización mensual
B41: Sírvase realizar el depósito correspondiente de los servicios a nuestra cuenta bancaria: | P41: CONDICIÓN: El pago del servicio deberá ser realizado por Adelantado.
B42: Cuenta de detraccion Banco de La Nación: | P42: CONDICIÓN: El pago del servicio Adelanto el 50% y saldo previo a la entrega del Informe.
B43: - Cuenta de detraccion Banco de La Nación: Nº 00-074-045472 | P43: CONDICIÓN: El pago del servicio Crédito a 7 días, previa orden de servicio.
B44: Cuenta corriente Interbank: | P44: CONDICIÓN: El pago del servicio Crédito a 30 días, previa orden de servicio.
B45: - Cuenta Corriente en Soles de Interbank: Nº 200-3005201096 | P45: CONDICIÓN: El pago del servicio Crédito a 15 días, previa orden de servicio.
B46: - Código Interbancario (CCI) de Interbank: Nº 003-200- 003005201096-31
B47: Cuenta corriente BCP:
B48: - Cuenta Corriente en Soles del Banco de Crédito del Perú (BCP): Nº 192 2024 3030 04
B49: - Código Interbancario (CCI) del Banco de Crédito del Perú (BCP): Nº 002-192-002 02430 3004-34
B50: Cuenta corriente BBVA:
B51: - Cuenta Corriente en Soles BBVA: Nº 0011-0174-0100082311-00
B52: - Código Interbancario (CCI) BBVA: Nº 011-174-000100082311-00
